Workbook

Sheet SNP-AD-DEN
A1: id | B1: anio | C1: tipo_anp | D1: canal_origen | E1: nro_expediente | F1: estado | G1: nro_expediente_sunged | H1: id_universidad | I1: tipo_gestion | J1: codigo_local | K1: region | L1: provincia | M1: distrito | N1: direccion | O1: modelo | P1: cbc | Q1: indicador | R1: hechos_denunciados | S1: complejidad | T1: prioridad | U1: ultima_accion | V1: fecha_ultima_accion | W1: comentarios | X1: profesional_asignado | Y1: acciones | Z1: comprometido_plan_2026 | AA1: entrega_informe_fecha | AB1: entrega_informe_estado | AC1: revision_jefe_fecha | AD1: revision_jefe_estado | AE1: productos | AF1: inicio_anp_documento | AG1: inicio_anp_fecha_notif | AH1: inicio_anp_dias_habiles | AI1: inicio_anp_fecha_venc | AJ1: inicio_anp_dias_venc | AK1: inicio_anp_alerta_i | AL1: inicio_anp_alerta_ii | AM1: inicio_anp_estado | AN1: inicio_anp_observaciones | AO1: seg_anp_ultima_actuacion | AP1: seg_anp_fecha_entrega | AQ1: seg_anp_tipo_info | AR1: seg_anp_diferencia_dias | AS1: seg_anp_observaciones | AT1: seg_anp_tipo_solicitud | AU1: seg_anp_documento | AV1: seg_anp_fecha_notif | AW1: seg_anp_dias_habiles | AX1: seg_anp_fecha_venc | AY1: seg_anp_dias_venc | AZ1: seg_anp_alerta_i | BA1: seg_anp_alerta_ii | BB1: seg_anp_estado | BC1: seg_anp_observaciones
A2: 1 | B2: 2022 | C2: Accion Directa | D2: Correo electrónico | E2: AD-005-2022 | F2: Archivado/UDRA | H2: 29 | I2: Pública | J2: SL01, SL02 | K2: Apurimac | L2: Andahuaylas | M2: San Jerónimo (SL01) | Talavera de la Reyna (SL02) | N2: Av. José María Arguedas S/N (SL01) | Av. 28 de Julio N° 1103 (SL02) | O2: MLI | P2: III, V, VI | Q2: 19, 27 | R2: La acción directa se motiva ante la falta de evidencia sobre la implementación de ambientes de enseñanza (aulas, laboratorios y talleres) y adquisiciOn de equipamiento necesarios para la prestación del servicio educativo de los cursos desde el tercer año de estudios para los programas nuevos (Contabilidad, Educación Primaria Intercultural e Ingeniería Ambiental), así como incluye también indagaciones respecto a la disponibilidad del servicio de biblioteca. Esto fue advertido a través de un análisis previo realizado por la Dilic y tras el traslado de pronunciamientos de los Centros Federados de la UNJMA. | S2: ALTA | T2: 2 | U2: La Universidad presentó información del acta del 13/11/2025. | V2: 45974 | W2: Están vinculados 2 informes de RCRQ (Informe 0441-2021-SUNEDU-02-12 DEL 17.05.2021 e 1286-2021-SUNEDU-02-12 del 15.12.2021) relacionado con la ejecución de sus proyectos de inversión. Cuenta con 2 supervisiones de campo, 1 realizada en setiembre de 2022 de la cual se obtuvo 1 Informe de Hallazgos y 1 Informe Complementario (no notificados a la Universidad) y 1 realizada en noviembre de 2025, en la cual se realizaron entrevistas y se solicitó información mediante Anexo. Adicionalmente a los hechos que motivaron la supervisión (falta de laboratorios y biblioteca) se identificaron en 2025, aspectos relacionados con la falta de gestión de residuos, seguridad del local y mantenimiento. | X2: VÍCTOR DE LA CRUZ | Y2: OS Antecedentes Barzen Manrique (Feb-26) CBC III Víctor de la Cruz (Feb-26) Priorizada para ser cerrada en marzo 2026. La CBC escala a SNP | Z2: Sí | AA2: 46101 | AB2: =IF(AA2<TODAY(),"VENCIDO","POR VENCER") -> VENCIDO | AC2: 46108 | AD2: EN PROCESO | AE2: Informe N° 00484-2026-SUNEDU-DS-DIRESESU-UVE que recomendó: El archivamiento de la AD-005-2022 en lo referido a la verificación del mantenimiento de las CBC V y VI del Modelo de Licenciamiento, vinculadas a la existencia mínima del 25% de docentes a tiempo completo del total, así como a los procesos de selección, evaluación y capacitación docente, y a la disponibilidad del acervo bibliográfico. 2) Inicio de una supervisión no programada respecto de la CBC III | AF2: {=IFERROR(_xlfn.XLOOKUP(TRIM($E2),TRIM('Año 2026'!$E$3:$E$66),'Año 2026'!$G$3:$G$66),"")} | AG2: {=IFERROR(_xlfn.XLOOKUP(TRIM($E2),TRIM('Año 2026'!$E$3:$E$66),'Año 2026'!$H$3:$H$66),"")} | AH2: {=IFERROR(_xlfn.XLOOKUP(TRIM($E2),TRIM('Año 2026'!$E$3:$E$66),'Año 2026'!$I$3:$I$66),"")} | AI2: {=IFERROR(_xlfn.XLOOKUP(TRIM($E2),TRIM('Año 2026'!$E$3:$E$66),'Año 2026'!$J$3:$J$66),"")} | AJ2: {=IFERROR(_xlfn.XLOOKUP(TRIM($E2),TRIM('Año 2026'!$E$3:$E$66),'Año 2026'!$K$3:$K$66),"")} | AK2: {=IFERROR(_xlfn.XLOOKUP(TRIM($E2),TRIM('Año 2026'!$E$3:$E$66),'Año 2026'!$L$3:$L$66),"")} | AL2: {=IFERROR(_xlfn.XLOOKUP(TRIM($E2),TRIM('Año 2026'!$E$3:$E$66),'Año 2026'!$M$3:$M$66),"")} | AM2: {=IFERROR(_xlfn.XLOOKUP(TRIM($E2),TRIM('Año 2026'!$E$3:$E$66),'Año 2026'!$N$3:$N$66),"")} | AN2: {=IFERROR(_xlfn.XLOOKUP(TRIM($E2),TRIM('Año 2026'!$E$3:$E$66),'Año 2026'!$O$3:$O$66),"")} | AO2: {=IFERROR(_xlfn.XLOOKUP(TRIM($E2),TRIM('Año 2026'!$E$3:$E$66),'Año 2026'!$P$3:$P$66),"")} | AP2: {=IFERROR(_xlfn.XLOOKUP(TRIM($E2),TRIM('Año 2026'!$E$3:$E$66),'Año 2026'!$Q$3:$Q$66),"")} | AQ2: {=IFERROR(_xlfn.XLOOKUP(TRIM($E2),TRIM('Año 2026'!$E$3:$E$66),'Año 2026'!$R$3:$R$66),"")} | AR2: {=IFERROR(_xlfn.XLOOKUP(TRIM($E2),TRIM('Año 2026'!$E$3:$E$66),'Año 2026'!$S$3:$S$66),"")} | AS2: {=IFERROR(_xlfn.XLOOKUP(TRIM($E2),TRIM('Año 2026'!$E$3:$E$66),'Año 2026'!$T$3:$T$66),"")} | AT2: {=IFERROR(_xlfn.XLOOKUP(TRIM($E2),TRIM('Año 2026'!$E$3:$E$66),'Año 2026'!$U$3:$U$66),"")} | AU2: {=IFERROR(_xlfn.XLOOKUP(TRIM($E2),TRIM('Año 2026'!$E$3:$E$66),'Año 2026'!$V$3:$V$66),"")} | AV2: {=IFERROR(_xlfn.XLOOKUP(TRIM($E2),TRIM('Año 2026'!$E$3:$E$66),'Año 2026'!$W$3:$W$66),"")} | AW2: {=IFERROR(_xlfn.XLOOKUP(TRIM($E2),TRIM('Año 2026'!$E$3:$E$66),'Año 2026'!$X$3:$X$66),"")} | AX2: {=IFERROR(_xlfn.XLOOKUP(TRIM($E2),TRIM('Año 2026'!$E$3:$E$66),'Año 2026'!$Y$3:$Y$66),"")} | AY2: {=IFERROR(_xlfn.XLOOKUP(TRIM($E2),TRIM('Año 2026'!$E$3:$E$66),'Año 2026'!$Z$3:$Z$66),"")} | AZ2: {=IFERROR(_xlfn.XLOOKUP(TRIM($E2),TRIM('Año 2026'!$E$3:$E$66),'Año 2026'!$AA$3:$AA$66),"")} | BA2: {=IFERROR(_xlfn.XLOOKUP(TRIM($E2),TRIM('Año 2026'!$E$3:$E$66),'Año 2026'!$AB$3:$AB$66),"")} | BB2: {=IFERROR(_xlfn.XLOOKUP(TRIM($E2),TRIM('Año 2026'!$E$3:$E$66),'Año 2026'!$AC$3:$AC$66),"")} | BC2: {=IFERROR(_xlfn.XLOOKUP(TRIM($E2),TRIM('Año 2026'!$E$3:$E$66),'Año 2026'!$AD$3:$AD$66),"")}
A3: 2 | B3: 2022 | C3: SNP | D3: Correo electrónico | E3: 01028-2022-SUNEDU/02-13 | F3: Atendido | H3: 28 | I3: Pública | J3: SL03 | K3: Huancavelica | L3: Tayacaja | M3: Ahuaycha | N3: Av. Universitaria Mz. A Lt. 12, 13 y 14 | O3: MLI | P3: III, VI | Q3: 17, 19, 20, 21, 22, 23, 24, 27, 29, 30, 44 | R3: Denuncia presentada por estudiantes de la Universidad Nacional Autónoma de Tayacaja, mediante la cual se solicita la intervención de la SUNEDU y la reorganización de los miembros de la Comisión Organizadora, debido a presuntas deficiencias institucionales consistentes en la falta de infraestructura y de pabellones y laboratorios para el desarrollo de los programas académicos, la ausencia de rendición de cuentas del presupuesto anual universitario, la falta de construcción e implementación de la sede administrativa, deficiencias en el servicio y/o contrato del proveedor del comedor universitario, la inexistencia del servicio de internet, deficiencias en el reglamento académico y el no reconocimiento de las juntas estudiantiles de las cinco carreras. | S3: ALTA | T3: 1 | U3: La Universidad remitió información requerida en el Acta de Supervisión, mediante Oficio N° 557 - 2025- UNAT del 21.11.25 | V3: 45982 | W3: El expediente estuvo asignado a Carla, pendiente consultar si se realizó alguna acción. Pendiente inicio de elaboración de IR. | X3: CARLA LA TORRE | Y3: OS Antecedentes: Barzen Manrique (Mar-26) Priorizada para ser cerrada en marzo 2026. CBC III Carla La Torre IR del 23.02.26 al 20.03.26 Priorizada para ser cerrada en marzo 2026. | Z3: Sí | AA3: 46141 | AB3: =IF(AA3<TODAY(),"VENCIDO","POR VENCER") -> VENCIDO | AC3: 46108 | AD3: COMPLETADO | AE3: Informe de Resultados N° 00109-2026-SUNEDU-DS-DIRESESU-UVE que recomienda la derivación a UDRA. | AF3: {=IFERROR(_xlfn.XLOOKUP(TRIM($E3),TRIM('Año 2026'!$E$3:$E$66),'Año 2026'!$G$3:$G$66),"")} | AG3: {=IFERROR(_xlfn.XLOOKUP(TRIM($E3),TRIM('Año 2026'!$E$3:$E$66),'Año 2026'!$H$3:$H$66),"")} | AH3: {=IFERROR(_xlfn.XLOOKUP(TRIM($E3),TRIM('Año 2026'!$E$3:$E$66),'Año 2026'!$I$3:$I$66),"")} | AI3: {=IFERROR(_xlfn.XLOOKUP(TRIM($E3),TRIM('Año 2026'!$E$3:$E$66),'Año 2026'!$J$3:$J$66),"")} | AJ3: {=IFERROR(_xlfn.XLOOKUP(TRIM($E3),TRIM('Año 2026'!$E$3:$E$66),'Año 2026'!$K$3:$K$66),"")} | AK3: {=IFERROR(_xlfn.XLOOKUP(TRIM($E3),TRIM('Año 2026'!$E$3:$E$66),'Año 2026'!$L$3:$L$66),"")} | AL3: {=IFERROR(_xlfn.XLOOKUP(TRIM($E3),TRIM('Año 2026'!$E$3:$E$66),'Año 2026'!$M$3:$M$66),"")} | AM3: {=IFERROR(_xlfn.XLOOKUP(TRIM($E3),TRIM('Año 2026'!$E$3:$E$66),'Año 2026'!$N$3:$N$66),"")} | AN3: {=IFERROR(_xlfn.XLOOKUP(TRIM($E3),TRIM('Año 2026'!$E$3:$E$66),'Año 2026'!$O$3:$O$66),"")} | AO3: {=IFERROR(_xlfn.XLOOKUP(TRIM($E3),TRIM('Año 2026'!$E$3:$E$66),'Año 2026'!$P$3:$P$66),"")} | AP3: {=IFERROR(_xlfn.XLOOKUP(TRIM($E3),TRIM('Año 2026'!$E$3:$E$66),'Año 2026'!$Q$3:$Q$66),"")} | AQ3: {=IFERROR(_xlfn.XLOOKUP(TRIM($E3),TRIM('Año 2026'!$E$3:$E$66),'Año 2026'!$R$3:$R$66),"")} | AR3: {=IFERROR(_xlfn.XLOOKUP(TRIM($E3),TRIM('Año 2026'!$E$3:$E$66),'Año 2026'!$S$3:$S$66),"")} | AS3: {=IFERROR(_xlfn.XLOOKUP(TRIM($E3),TRIM('Año 2026'!$E$3:$E$66),'Año 2026'!$T$3:$T$66),"")} | AT3: {=IFERROR(_xlfn.XLOOKUP(TRIM($E3),TRIM('Año 2026'!$E$3:$E$66),'Año 2026'!$U$3:$U$66),"")} | AU3: {=IFERROR(_xlfn.XLOOKUP(TRIM($E3),TRIM('Año 2026'!$E$3:$E$66),'Año 2026'!$V$3:$V$66),"")} | AV3: {=IFERROR(_xlfn.XLOOKUP(TRIM($E3),TRIM('Año 2026'!$E$3:$E$66),'Año 2026'!$W$3:$W$66),"")} | AW3: {=IFERROR(_xlfn.XLOOKUP(TRIM($E3),TRIM('Año 2026'!$E$3:$E$66),'Año 2026'!$X$3:$X$66),"")} | AX3: {=IFERROR(_xlfn.XLOOKUP(TRIM($E3),TRIM('Año 2026'!$E$3:$E$66),'Año 2026'!$Y$3:$Y$66),"")} | AY3: {=IFERROR(_xlfn.XLOOKUP(TRIM($E3),TRIM('Año 2026'!$E$3:$E$66),'Año 2026'!$Z$3:$Z$66),"")} | AZ3: {=IFERROR(_xlfn.XLOOKUP(TRIM($E3),TRIM('Año 2026'!$E$3:$E$66),'Año 2026'!$AA$3:$AA$66),"")} | BA3: {=IFERROR(_xlfn.XLOOKUP(TRIM($E3),TRIM('Año 2026'!$E$3:$E$66),'Año 2026'!$AB$3:$AB$66),"")} | BB3: {=IFERROR(_xlfn.XLOOKUP(TRIM($E3),TRIM('Año 2026'!$E$3:$E$66),'Año 2026'!$AC$3:$AC$66),"")} | BC3: {=IFERROR(_xlfn.XLOOKUP(TRIM($E3),TRIM('Año 2026'!$E$3:$E$66),'Año 2026'!$AD$3:$AD$66),"")}
A4: 3 | B4: 2022 | C4: SNP | D4: No programada - oficio | E4: 02730-2022-SUNEDU/02-13 | F4: Atendido | H4: 25 | I4: Privada | J4: SL01, SL03, SL10, SL14, F06L02 | K4: SL01,SL03,SL10,SL14: Lima | F06L02: La Libertad | L4: SL01,SL03,SL10,SL14: Lima | F06L02: Trujillo | M4: SL01,SL03,SL10,SL14: Lima | F06L02: Trujillo | N4: SL01: Av. Abel Bergasse Du Petit Thouars 114 y 116 Urb. Santa Beatriz | SL03: Av. Petit Thouars Mz. 3B Lt. 9 urbanización Fundo Santa Beatriz Cercado | SL10: Jirón Hernán Velarde N° 143, N° 149, N° 151 y N° 153; frente al Parque Hernán Velarde N° 33 y N° 35 | SL14: Jirón Manuel Nicolás Corpancho N° 358-360 Cercado | F06L02: Av. Nicolás de Piérola (antes Carretera Panamericana Norte) 1221- 1223-1225-1227- 1229-1231- 1235 | O4: MLI | P4: III | Q4: 17, 20, 27, 28, 30 | R4: Caso referido a presuntas afectaciones en locales licenciados de la Universidad Tecnológica del Perú (SL01, SL03, SL10, SL14 y F06L02), derivadas del traslado (Trujillo) y, en algunos casos (Lima), fusión de laboratorios y talleres entre sedes. La supervisión preliminar identificó la reubicación de ambientes de enseñanza en sótanos y zonas colindantes a estacionamientos, lo que podría comprometer las condiciones de habitabilidad (confort acústico y térmico), seguridad (ausencia de circulación peatonal diferenciada y medios de evacuación, así como falta de actualización de la identificación de riesgos), y la disponibilidad de equipamiento mínimo, al evidenciarse una reducción en la cantidad de equipos respecto a lo declarado en el licenciamiento. | S4: MEDIA | T4: 1 | U4: Respuesta por parte de la Universidad a los requerimientos realizados por la DISUP en el Informe preliminar N° 047-2022-SUNEDU/02-13, del 20.02.23 | V4: 44977 | W4: Está pendiente la elaboración del Informe de Resultados con la última información remitida por la Universidad. | X4: ANTHONY SAAVEDRA | Y4: Pendiente de revisión por Gigi Desde el 09.02.26 al 20.02.26 Priorizada para ser cerrada en febrero 2026 | Z4: Sí | AA4: 46101 | AB4: =IF(AA4<TODAY(),"VENCIDO","POR VENCER") -> VENCIDO | AC4: 46108 | AD4: COMPLETADO | AE4: INFORME DE RESULTADOS N° 00065-2026-SUNEDU-DS-DIRESESU-UVE | AF4: {=IFERROR(_xlfn.XLOOKUP(TRIM($E4),TRIM('Año 2026'!$E$3:$E$66),'Año 2026'!$G$3:$G$66),"")} | AG4: {=IFERROR(_xlfn.XLOOKUP(TRIM($E4),TRIM('Año 2026'!$E$3:$E$66),'Año 2026'!$H$3:$H$66),"")} | AH4: {=IFERROR(_xlfn.XLOOKUP(TRIM($E4),TRIM('Año 2026'!$E$3:$E$66),'Año 2026'!$I$3:$I$66),"")} | AI4: {=IFERROR(_xlfn.XLOOKUP(TRIM($E4),TRIM('Año 2026'!$E$3:$E$66),'Año 2026'!$J$3:$J$66),"")} | AJ4: {=IFERROR(_xlfn.XLOOKUP(TRIM($E4),TRIM('Año 2026'!$E$3:$E$66),'Año 2026'!$K$3:$K$66),"")} | AK4: {=IFERROR(_xlfn.XLOOKUP(TRIM($E4),TRIM('Año 2026'!$E$3:$E$66),'Año 2026'!$L$3:$L$66),"")} | AL4: {=IFERROR(_xlfn.XLOOKUP(TRIM($E4),TRIM('Año 2026'!$E$3:$E$66),'Año 2026'!$M$3:$M$66),"")} | AM4: {=IFERROR(_xlfn.XLOOKUP(TRIM($E4),TRIM('Año 2026'!$E$3:$E$66),'Año 2026'!$N$3:$N$66),"")} | AN4: {=IFERROR(_xlfn.XLOOKUP(TRIM($E4),TRIM('Año 2026'!$E$3:$E$66),'Año 2026'!$O$3:$O$66),"")} | AO4: {=IFERROR(_xlfn.XLOOKUP(TRIM($E4),TRIM('Año 2026'!$E$3:$E$66),'Año 2026'!$P$3:$P$66),"")} | AP4: {=IFERROR(_xlfn.XLOOKUP(TRIM($E4),TRIM('Año 2026'!$E$3:$E$66),'Año 2026'!$Q$3:$Q$66),"")} | AQ4: {=IFERROR(_xlfn.XLOOKUP(TRIM($E4),TRIM('Año 2026'!$E$3:$E$66),'Año 2026'!$R$3:$R$66),"")} | AR4: {=IFERROR(_xlfn.XLOOKUP(TRIM($E4),TRIM('Año 2026'!$E$3:$E$66),'Año 2026'!$S$3:$S$66),"")} | AS4: {=IFERROR(_xlfn.XLOOKUP(TRIM($E4),TRIM('Año 2026'!$E$3:$E$66),'Año 2026'!$T$3:$T$66),"")} | AT4: {=IFERROR(_xlfn.XLOOKUP(TRIM($E4),TRIM('Año 2026'!$E$3:$E$66),'Año 2026'!$U$3:$U$66),"")} | AU4: {=IFERROR(_xlfn.XLOOKUP(TRIM($E4),TRIM('Año 2026'!$E$3:$E$66),'Año 2026'!$V$3:$V$66),"")} | AV4: {=IFERROR(_xlfn.XLOOKUP(TRIM($E4),TRIM('Año 2026'!$E$3:$E$66),'Año 2026'!$W$3:$W$66),"")} | AW4: {=IFERROR(_xlfn.XLOOKUP(TRIM($E4),TRIM('Año 2026'!$E$3:$E$66),'Año 2026'!$X$3:$X$66),"")} | AX4: {=IFERROR(_xlfn.XLOOKUP(TRIM($E4),TRIM('Año 2026'!$E$3:$E$66),'Año 2026'!$Y$3:$Y$66),"")} | AY4: {=IFERROR(_xlfn.XLOOKUP(TRIM($E4),TRIM('Año 2026'!$E$3:$E$66),'Año 2026'!$Z$3:$Z$66),"")} | AZ4: {=IFERROR(_xlfn.XLOOKUP(TRIM($E4),TRIM('Año 2026'!$E$3:$E$66),'Año 2026'!$AA$3:$AA$66),"")} | BA4: {=IFERROR(_xlfn.XLOOKUP(TRIM($E4),TRIM('Año 2026'!$E$3:$E$66),'Año 2026'!$AB$3:$AB$66),"")} | BB4: {=IFERROR(_xlfn.XLOOKUP(TRIM($E4),TRIM('Año 2026'!$E$3:$E$66),'Año 2026'!$AC$3:$AC$66),"")} | BC4: {=IFERROR(_xlfn.XLOOKUP(TRIM($E4),TRIM('Año 2026'!$E$3:$E$66),'Año 2026'!$AD$3:$AD$66),"")}
A5: 4 | B5: 2024 | C5: Denuncia | D5: Correo electrónico | E5: 02438-2024-SUNEDU/02-13 | F5: En trámite | G5: 2024INT0000014220-SUNEDU | H5: 42 | I5: Privada | J5: SL01 | K5: Lima | L5: Lima | M5: La Molina | N5: Av. La Molina N° 3755, Sol de la Molina, distrito de La Molina, provincia y departamento de Lima. | O5: MLI | P5: III, V | Q5: 27 | R5: Hace de conocimiento lo siguiente: (I) La universidad vendría adicionando carreras y admitiría más alumnos, sin contar con los docentes necesarios para el dictado de clases. (II) Se les obligaría a pagar por un seguro que no lo necesitarían.III) El aforo de las aulas estaría excediendo el límite permitido. La Universidad mediante Oficio N° 045-2025-SG-UCAL del 16 de julio de 2025, presentó los ocho (8) puntos de la condicion III y de la condicion VI la contratación del seguro que ofrece UCAL no es obligatoria, el estudiante puede optar por adquirir la póliza que más le convenga.exigencia de pagar por un seguro Jenny proyectó el Oficio de Requirimiento Complementario, pendiente de revisión y envío a la universidad. | S5: MEDIA | T5: 2 | U5: Informacion solicitada mediante Oficio Nº 02404-2025-SUNEDU-DS-DIRESESU-UVE del 01 de Julio de 2025, se solicita ocho (8) puntos de la Condición III (indicadores 27 y 28) del Modelo de Licenciamiento y Condición V (indicadores 39 y 40) del Modelo de Licenciamiento y Condición II (indicador 6) del Modelo para programas semipresenciales y a distancia | V5: 45841 | W5: La Universidad presentó el Oficio N° 045-2025-SG-UCAL del 16.07.2025, respondiendo al Oficio N° 02404-2025-SUNEDU-DS-DIRESESU-UVE con el cual se solicita información acerca de la denuncia. Pendiente de analizar infromación presentada y elaborar IR. | Y5: Pendiente proyectar requerimiento de información de CBC III y V Antecedentes Barzen Manrique CBC III Carla La Torre 01.07.26 al 17.07.26 CBC V pendiente definir evaluador Priorizada para ser cerrada en julio 2026. | Z5: Sí | AA5: 46227 | AB5: =IF(AA5<TODAY(),"VENCIDO","POR VENCER") -> POR VENCER | AC5: 46234 | AD5: EN PROCESO | AE5: Carta y/o Oficio | AF5: {=IFERROR(_xlfn.XLOOKUP(TRIM($E5),TRIM('Año 2026'!$E$3:$E$66),'Año 2026'!$G$3:$G$66),"")} -> OFICIO Nº 02404-2025-SUNEDU-DS-DIRESESU-UVE | AG5: {=IFERROR(_xlfn.XLOOKUP(TRIM($E5),TRIM('Año 2026'!$E$3:$E$66),'Año 2026'!$H$3:$H$66),"")} -> 0 | AH5: {=IFERROR(_xlfn.XLOOKUP(TRIM($E5),TRIM('Año 2026'!$E$3:$E$66),'Año 2026'!$I$3:$I$66),"")} -> 0 | AI5: {=IFERROR(_xlfn.XLOOKUP(TRIM($E5),TRIM('Año 2026'!$E$3:$E$66),'Año 2026'!$J$3:$J$66),"")} -> 0 | AJ5: {=IFERROR(_xlfn.XLOOKUP(TRIM($E5),TRIM('Año 2026'!$E$3:$E$66),'Año 2026'!$K$3:$K$66),"")} -> 0 | AK5: {=IFERROR(_xlfn.XLOOKUP(TRIM($E5),TRIM('Año 2026'!$E$3:$E$66),'Año 2026'!$L$3:$L$66),"")} -> 0 | AL5: {=IFERROR(_xlfn.XLOOKUP(TRIM($E5),TRIM('Año 2026'!$E$3:$E$66),'Año 2026'!$M$3:$M$66),"")} -> 0 | AM5: {=IFERROR(_xlfn.XLOOKUP(TRIM($E5),TRIM('Año 2026'!$E$3:$E$66),'Año 2026'!$N$3:$N$66),"")} -> 0 | AN5: {=IFERROR(_xlfn.XLOOKUP(TRIM($E5),TRIM('Año 2026'!$E$3:$E$66),'Año 2026'!$O$3:$O$66),"")} -> 0 | AO5: {=IFERROR(_xlfn.XLOOKUP(TRIM($E5),TRIM('Año 2026'!$E$3:$E$66),'Año 2026'!$P$3:$P$66),"")} -> 0 | AP5: {=IFERROR(_xlfn.XLOOKUP(TRIM($E5),TRIM('Año 2026'!$E$3:$E$66),'Año 2026'!$Q$3:$Q$66),"")} -> 0 | AQ5: {=IFERROR(_xlfn.XLOOKUP(TRIM($E5),TRIM('Año 2026'!$E$3:$E$66),'Año 2026'!$R$3:$R$66),"")} -> 0 | AR5: {=IFERROR(_xlfn.XLOOKUP(TRIM($E5),TRIM('Año 2026'!$E$3:$E$66),'Año 2026'!$S$3:$S$66),"")} -> 0 | AS5: {=IFERROR(_xlfn.XLOOKUP(TRIM($E5),TRIM('Año 2026'!$E$3:$E$66),'Año 2026'!$T$3:$T$66),"")} -> 0 | AT5: {=IFERROR(_xlfn.XLOOKUP(TRIM($E5),TRIM('Año 2026'!$E$3:$E$66),'Año 2026'!$U$3:$U$66),"")} -> 0 | AU5: {=IFERROR(_xlfn.XLOOKUP(TRIM($E5),TRIM('Año 2026'!$E$3:$E$66),'Año 2026'!$V$3:$V$66),"")} -> 0 | AV5: {=IFERROR(_xlfn.XLOOKUP(TRIM($E5),TRIM('Año 2026'!$E$3:$E$66),'Año 2026'!$W$3:$W$66),"")} -> 0 | AW5: {=IFERROR(_xlfn.XLOOKUP(TRIM($E5),TRIM('Año 2026'!$E$3:$E$66),'Año 2026'!$X$3:$X$66),"")} -> 0 | AX5: {=IFERROR(_xlfn.XLOOKUP(TRIM($E5),TRIM('Año 2026'!$E$3:$E$66),'Año 2026'!$Y$3:$Y$66),"")} -> 0 | AY5: {=IFERROR(_xlfn.XLOOKUP(TRIM($E5),TRIM('Año 2026'!$E$3:$E$66),'Año 2026'!$Z$3:$Z$66),"")} -> 0 | AZ5: {=IFERROR(_xlfn.XLOOKUP(TRIM($E5),TRIM('Año 2026'!$E$3:$E$66),'Año 2026'!$AA$3:$AA$66),"")} -> 0 | BA5: {=IFERROR(_xlfn.XLOOKUP(TRIM($E5),TRIM('Año 2026'!$E$3:$E$66),'Año 2026'!$AB$3:$AB$66),"")} -> 0 | BB5: {=IFERROR(_xlfn.XLOOKUP(TRIM($E5),TRIM('Año 2026'!$E$3:$E$66),'Año 2026'!$AC$3:$AC$66),"")} -> 0 | BC5: {=IFERROR(_xlfn.XLOOKUP(TRIM($E5),TRIM('Año 2026'!$E$3:$E$66),'Año 2026'!$AD$3:$AD$66),"")} -> 0
A6: 5 | B6: 2023 | C6: SNP | D6: Web | E6: 01709-2023-SUNEDU/02-13 | F6: En trámite | G6: 031172-2023-SUNEDU-TD, 2024INT0000006179-SUNEDU | H6: 31 | I6: Pública | J6: SL01, SL05, F01L01, F02L01, F03L01 | K6: Pasco | L6: Pasco | M6: Yanacancha | N6: 1.-SL01, cuya ubicación es Programa de Vivienda Urbanización San Juan Pampa Mz Q Lote 1 Sector Centro Comercial, distrito de Yanacancha, provincia de Pasco, departamento de Pasco. Contiene, entre otras, las facultades de Medicina Humana, Ingeniería de Minas, Ciencias de la Comunicación, Odontología, e Ingeniería. | - SL05, cuya ubicación es Terreno ubicado en Pucayacu, distrito de Yanacancha, provincia de Pasco, departamento de Pasco. Contiene la facultad de Medicina Humana e Ingeniería de Minas | 2.-FILIALES: | F01L01, cuya ubicación es Valle Oxapampa, Sector Miraflores S/N, distrito de Oxapampa, provincia de Oxapampa, departamento de Pasco. Contiene, entre otras, la facultad de Ingeniería. | F03L01, cuya ubicación es Av. Circunvalación Mz 0206 Lt. S/N, Urbanización Pampa del Carmen, distrito de Chanchamayo, provincia de Chanchamayo, departamento de Junín. Contiene, entre otras, la facultad de Ciencias de la Comunicación. | O6: MLI | P6: III, VI | Q6: 19 | R6: Denuncia contra la Universidad Nacional Daniel Alcides Carrión (UNDAC) por presuntas irregularidades que afectarían el mantenimiento de las Condiciones Básicas de Calidad, referidas a: i) paralización de la obra de remodelación de instalaciones eléctricas en la sede central San Juan (Yanacancha), generando riesgos para la seguridad de los estudiantes por zanjas abiertas y cables expuestos (Denuncia 1: RTD 031167-2023-SUNEDU-TD, del 30/06/2023); ii) falta de prestación del servicio de comedor universitario en las filiales de Oxapampa (F01L01), Tarma (F02L01) y Chanchamayo (F03L01) (Denuncia 2: RTD 031172-2023-SUNEDU-TD, del 30/06/2023) | S6: MEDIA | T6: 2 | U6: Se escala, de denunacia a SNP, pendiente de firma de ejecutiva Mediante Oficio N° 000281-2025-UNDAC/R, remitio informacion peticionaria: 1. Informe N°000037-2025-DBU 2.Informe Tecnico N°000024-2025-UEI * Solo se hizo un cotejo de información falta evaluarla | V6: 45797 | W6: A sido trasladado a otro expediente: 4. AD-003-2024 (UNDAC), ya cuenta con Visita de Inspección, la Universidad ha entregado información(además se deberá acumular lo del expediente En la visita de inspección de octubre de 2025, no se solicitó información vinculada a esta denuncia. En cuanto firmen el oficio se eleva a SNP. | Y6: OS Antecedentes Barzen Manrique CBC III Jenny Mendez (Mar-26) CBC VI Ysella Arguedas (Mar-26) Priorizada para ser cerrada en marzo 2026 Para elaboración de IR con información post VI y lo que entregará del exp 01927-2025-SUNEDI/02-13) Priorizada para ser cerrada en abril 2026 | Z6: Sí | AA6: 46129 | AB6: =IF(AA6<TODAY(),"VENCIDO","POR VENCER") -> VENCIDO | AC6: 46136 | AD6: EN PROCESO | AE6: Informe de Resultados | AF6: {=IFERROR(_xlfn.XLOOKUP(TRIM($E6),TRIM('Año 2026'!$E$3:$E$66),'Año 2026'!$G$3:$G$66),"")} | AG6: {=IFERROR(_xlfn.XLOOKUP(TRIM($E6),TRIM('Año 2026'!$E$3:$E$66),'Año 2026'!$H$3:$H$66),"")} | AH6: {=IFERROR(_xlfn.XLOOKUP(TRIM($E6),TRIM('Año 2026'!$E$3:$E$66),'Año 2026'!$I$3:$I$66),"")} | AI6: {=IFERROR(_xlfn.XLOOKUP(TRIM($E6),TRIM('Año 2026'!$E$3:$E$66),'Año 2026'!$J$3:$J$66),"")} | AJ6: {=IFERROR(_xlfn.XLOOKUP(TRIM($E6),TRIM('Año 2026'!$E$3:$E$66),'Año 2026'!$K$3:$K$66),"")} | AK6: {=IFERROR(_xlfn.XLOOKUP(TRIM($E6),TRIM('Año 2026'!$E$3:$E$66),'Año 2026'!$L$3:$L$66),"")} | AL6: {=IFERROR(_xlfn.XLOOKUP(TRIM($E6),TRIM('Año 2026'!$E$3:$E$66),'Año 2026'!$M$3:$M$66),"")} | AM6: {=IFERROR(_xlfn.XLOOKUP(TRIM($E6),TRIM('Año 2026'!$E$3:$E$66),'Año 2026'!$N$3:$N$66),"")} | AN6: {=IFERROR(_xlfn.XLOOKUP(TRIM($E6),TRIM('Año 2026'!$E$3:$E$66),'Año 2026'!$O$3:$O$66),"")} | AO6: {=IFERROR(_xlfn.XLOOKUP(TRIM($E6),TRIM('Año 2026'!$E$3:$E$66),'Año 2026'!$P$3:$P$66),"")} | AP6: {=IFERROR(_xlfn.XLOOKUP(TRIM($E6),TRIM('Año 2026'!$E$3:$E$66),'Año 2026'!$Q$3:$Q$66),"")} | AQ6: {=IFERROR(_xlfn.XLOOKUP(TRIM($E6),TRIM('Año 2026'!$E$3:$E$66),'Año 2026'!$R$3:$R$66),"")} | AR6: {=IFERROR(_xlfn.XLOOKUP(TRIM($E6),TRIM('Año 2026'!$E$3:$E$66),'Año 2026'!$S$3:$S$66),"")} | AS6: {=IFERROR(_xlfn.XLOOKUP(TRIM($E6),TRIM('Año 2026'!$E$3:$E$66),'Año 2026'!$T$3:$T$66),"")} | AT6: {=IFERROR(_xlfn.XLOOKUP(TRIM($E6),TRIM('Año 2026'!$E$3:$E$66),'Año 2026'!$U$3:$U$66),"")} | AU6: {=IFERROR(_xlfn.XLOOKUP(TRIM($E6),TRIM('Año 2026'!$E$3:$E$66),'Año 2026'!$V$3:$V$66),"")} | AV6: {=IFERROR(_xlfn.XLOOKUP(TRIM($E6),TRIM('Año 2026'!$E$3:$E$66),'Año 2026'!$W$3:$W$66),"")} | AW6: {=IFERROR(_xlfn.XLOOKUP(TRIM($E6),TRIM('Año 2026'!$E$3:$E$66),'Año 2026'!$X$3:$X$66),"")} | AX6: {=IFERROR(_xlfn.XLOOKUP(TRIM($E6),TRIM('Año 2026'!$E$3:$E$66),'Año 2026'!$Y$3:$Y$66),"")} | AY6: {=IFERROR(_xlfn.XLOOKUP(TRIM($E6),TRIM('Año 2026'!$E$3:$E$66),'Año 2026'!$Z$3:$Z$66),"")} | AZ6: {=IFERROR(_xlfn.XLOOKUP(TRIM($E6),TRIM('Año 2026'!$E$3:$E$66),'Año 2026'!$AA$3:$AA$66),"")} | BA6: {=IFERROR(_xlfn.XLOOKUP(TRIM($E6),TRIM('Año 2026'!$E$3:$E$66),'Año 2026'!$AB$3:$AB$66),"")} | BB6: {=IFERROR(_xlfn.XLOOKUP(TRIM($E6),TRIM('Año 2026'!$E$3:$E$66),'Año 2026'!$AC$3:$AC$66),"")} | BC6: {=IFERROR(_xlfn.XLOOKUP(TRIM($E6),TRIM('Año 2026'!$E$3:$E$66),'Año 2026'!$AD$3:$AD$66),"")}
A7: 6 | B7: 2023 | C7: Accion Directa | D7: Correo electrónico | E7: AD-013-2023 | F7: Atendido | H7: 17 | I7: Pública | J7: SL01 | K7: Lima | L7: Lima | M7: Lurigancho | N7: Avenida Enrique Guzmán y Valle N° 951 | O7: MLI | P7: III, VI | Q7: 19, 30, 44 | R7: La acción directa se motiva tras la comunicación realizada por la propia universidad (RTD N° 15698-2023-SUNEDU-TD, u Oficios N° 0103-2023-R-UNE del 24/03/2023 y Nº 0149-2023-R-UNE del 11/05/2023) señalando que las circunsancias ambientales de su entorno habrían generado afectación a la prestación del servicio educativo de manera presencial: - Destrucción de los canales de agua y pistas; el enlodamiento de las vIas de acceso a las aulas, ambientes académicos y administrativos; y la filtración de agua a los ambientes de clases y comedor universitario. - Los sistemas de abastecimiento de agua no tendrían capacidad para atender a la comunidad universitaria en un contexto de presencialidad. | S7: BAJA | T7: 1 | U7: Visita de inspección realizada en set2025, al respecto la Universidad presentó información y se cuenta con 1 IR elaborado pendiente de revisión final. | V7: 45911 | W7: En la comunicación inicial de la Universidad, que origina la acción de oficio, presentó el "Plan de Contingencia del Proceso de Formación profesional y eduación contínua 2023" mediante el cual planifica acciones que acompañarían su pedido de "flexibilidad para la prestación del servicio educativo en manera virtual para el semestre 2023-I". Disup tuvo reuniones y realizó seguimiento, siendo que en julio de 2023 solicitó información de las acciones que la Universidad ejecutaría frente a los problemas de techos e infraestructura afectada por lluvias. Cuenta con 2 supervisiones de campo, 1 realizada en noviembre de 2023, en la cual señaló que realizó proyectos IOARR´s para la mejora de techos y atender acciones de emergencia de mantenimiento; y 1 segunda visita de inspección realizada el 10 y 11 de setiembre de 2025. | Y7: CULMINADO Informe de Cierre. Recomendación con derivación da DIGESU | Z7: Sí | AA7: 46101 | AB7: =IF(AA7<TODAY(),"VENCIDO","POR VENCER") -> VENCIDO | AC7: 46108 | AD7: COMPLETADO | AE7: INFORME N° 00210-2026-SUNEDU-DS-DIRESESU-UVE | AF7: {=IFERROR(_xlfn.XLOOKUP(TRIM($E7),TRIM('Año 2026'!$E$3:$E$66),'Año 2026'!$G$3:$G$66),"")} | AG7: {=IFERROR(_xlfn.XLOOKUP(TRIM($E7),TRIM('Año 2026'!$E$3:$E$66),'Año 2026'!$H$3:$H$66),"")} | AH7: {=IFERROR(_xlfn.XLOOKUP(TRIM($E7),TRIM('Año 2026'!$E$3:$E$66),'Año 2026'!$I$3:$I$66),"")} | AI7: {=IFERROR(_xlfn.XLOOKUP(TRIM($E7),TRIM('Año 2026'!$E$3:$E$66),'Año 2026'!$J$3:$J$66),"")} | AJ7: {=IFERROR(_xlfn.XLOOKUP(TRIM($E7),TRIM('Año 2026'!$E$3:$E$66),'Año 2026'!$K$3:$K$66),"")} | AK7: {=IFERROR(_xlfn.XLOOKUP(TRIM($E7),TRIM('Año 2026'!$E$3:$E$66),'Año 2026'!$L$3:$L$66),"")} | AL7: {=IFERROR(_xlfn.XLOOKUP(TRIM($E7),TRIM('Año 2026'!$E$3:$E$66),'Año 2026'!$M$3:$M$66),"")} | AM7: {=IFERROR(_xlfn.XLOOKUP(TRIM($E7),TRIM('Año 2026'!$E$3:$E$66),'Año 2026'!$N$3:$N$66),"")} | AN7: {=IFERROR(_xlfn.XLOOKUP(TRIM($E7),TRIM('Año 2026'!$E$3:$E$66),'Año 2026'!$O$3:$O$66),"")} | AO7: {=IFERROR(_xlfn.XLOOKUP(TRIM($E7),TRIM('Año 2026'!$E$3:$E$66),'Año 2026'!$P$3:$P$66),"")} | AP7: {=IFERROR(_xlfn.XLOOKUP(TRIM($E7),TRIM('Año 2026'!$E$3:$E$66),'Año 2026'!$Q$3:$Q$66),"")} | AQ7: {=IFERROR(_xlfn.XLOOKUP(TRIM($E7),TRIM('Año 2026'!$E$3:$E$66),'Año 2026'!$R$3:$R$66),"")} | AR7: {=IFERROR(_xlfn.XLOOKUP(TRIM($E7),TRIM('Año 2026'!$E$3:$E$66),'Año 2026'!$S$3:$S$66),"")} | AS7: {=IFERROR(_xlfn.XLOOKUP(TRIM($E7),TRIM('Año 2026'!$E$3:$E$66),'Año 2026'!$T$3:$T$66),"")} | AT7: {=IFERROR(_xlfn.XLOOKUP(TRIM($E7),TRIM('Año 2026'!$E$3:$E$66),'Año 2026'!$U$3:$U$66),"")} | AU7: {=IFERROR(_xlfn.XLOOKUP(TRIM($E7),TRIM('Año 2026'!$E$3:$E$66),'Año 2026'!$V$3:$V$66),"")} | AV7: {=IFERROR(_xlfn.XLOOKUP(TRIM($E7),TRIM('Año 2026'!$E$3:$E$66),'Año 2026'!$W$3:$W$66),"")} | AW7: {=IFERROR(_xlfn.XLOOKUP(TRIM($E7),TRIM('Año 2026'!$E$3:$E$66),'Año 2026'!$X$3:$X$66),"")} | AX7: {=IFERROR(_xlfn.XLOOKUP(TRIM($E7),TRIM('Año 2026'!$E$3:$E$66),'Año 2026'!$Y$3:$Y$66),"")} | AY7: {=IFERROR(_xlfn.XLOOKUP(TRIM($E7),TRIM('Año 2026'!$E$3:$E$66),'Año 2026'!$Z$3:$Z$66),"")} | AZ7: {=IFERROR(_xlfn.XLOOKUP(TRIM($E7),TRIM('Año 2026'!$E$3:$E$66),'Año 2026'!$AA$3:$AA$66),"")} | BA7: {=IFERROR(_xlfn.XLOOKUP(TRIM($E7),TRIM('Año 2026'!$E$3:$E$66),'Año 2026'!$AB$3:$AB$66),"")} | BB7: {=IFERROR(_xlfn.XLOOKUP(TRIM($E7),TRIM('Año 2026'!$E$3:$E$66),'Año 2026'!$AC$3:$AC$66),"")} | BC7: {=IFERROR(_xlfn.XLOOKUP(TRIM($E7),TRIM('Año 2026'!$E$3:$E$66),'Año 2026'!$AD$3:$AD$66),"")}
A8: 7 | B8: 2023 | C8: Accion Directa | D8: Correo electrónico | E8: AD-015-2023 | F8: Archivado | H8: 21 | I8: Pública | J8: SL01 | K8: Cusco | L8: La Convencion | M8: Santa Ana | N8: El Arenal S/N | O8: MLI | P8: III, IV, V | Q8: 19, 27, 28, 30, 33, 34, 35, 38, 40, 42, 44 | R8: Las acciones iniciarían con Oficio de abril de 2023 que comunica la "supervisión orientativa" para el seguimiento y cumplimiento de las 20 recomendaciones realizadas mediante el Informe de Resultados N° 0025- 2023-SUNEDU/02-13 del 17 de febrero de 2023, el cual fue producto de una supervisión programada realizada previamente. Dichas recomendaciones están relaciionadas con CBC I (gestión de calidad), CBC IV (investigación), CBC V (docentes), VI (servicios complementarios) y adiconalmente refieren a CBC III (ejecución presupuestal de sus proyectos de inversión y de mantenimiento). | S8: ALTA | T8: 2 | U8: Visita de inspección realizada en oct2025, a la espera del envío de información solicitada a la Universidad. | V8: 45946 | W8: Conforme a la inspección, se identificó ausencia de ambientes y afectación de CBC´s, lo cual requeriría de análisis de las mallas de los programas ofertados y del estado de los proyectos de inversión. A la fecha la Universidad no ha presentado la información solicitada en la VI de octubre de 2025. | Y8: Pendiente enviar primer reiterativo de información IR Antecedentes Barzen Manrique CBC III Carla La Torre 04.05.26 al 22.05.26 CBC IV y V - Liz (Por confirmar fechas) Priorizada para ser cerrada en mayo 2026. | Z8: Sí | AA8: 46164 | AB8: =IF(AA8<TODAY(),"VENCIDO","POR VENCER") -> VENCIDO | AC8: 46171 | AD8: COMPLETADO | AE8: Se archivó porque escaló a una SNP | AF8: {=IFERROR(_xlfn.XLOOKUP(TRIM($E8),TRIM('Año 2026'!$E$3:$E$66),'Año 2026'!$G$3:$G$66),"")} | AG8: {=IFERROR(_xlfn.XLOOKUP(TRIM($E8),TRIM('Año 2026'!$E$3:$E$66),'Año 2026'!$H$3:$H$66),"")} | AH8: {=IFERROR(_xlfn.XLOOKUP(TRIM($E8),TRIM('Año 2026'!$E$3:$E$66),'Año 2026'!$I$3:$I$66),"")} | AI8: {=IFERROR(_xlfn.XLOOKUP(TRIM($E8),TRIM('Año 2026'!$E$3:$E$66),'Año 2026'!$J$3:$J$66),"")} | AJ8: {=IFERROR(_xlfn.XLOOKUP(TRIM($E8),TRIM('Año 2026'!$E$3:$E$66),'Año 2026'!$K$3:$K$66),"")} | AK8: {=IFERROR(_xlfn.XLOOKUP(TRIM($E8),TRIM('Año 2026'!$E$3:$E$66),'Año 2026'!$L$3:$L$66),"")} | AL8: {=IFERROR(_xlfn.XLOOKUP(TRIM($E8),TRIM('Año 2026'!$E$3:$E$66),'Año 2026'!$M$3:$M$66),"")} | AM8: {=IFERROR(_xlfn.XLOOKUP(TRIM($E8),TRIM('Año 2026'!$E$3:$E$66),'Año 2026'!$N$3:$N$66),"")} | AN8: {=IFERROR(_xlfn.XLOOKUP(TRIM($E8),TRIM('Año 2026'!$E$3:$E$66),'Año 2026'!$O$3:$O$66),"")} | AO8: {=IFERROR(_xlfn.XLOOKUP(TRIM($E8),TRIM('Año 2026'!$E$3:$E$66),'Año 2026'!$P$3:$P$66),"")} | AP8: {=IFERROR(_xlfn.XLOOKUP(TRIM($E8),TRIM('Año 2026'!$E$3:$E$66),'Año 2026'!$Q$3:$Q$66),"")} | AQ8: {=IFERROR(_xlfn.XLOOKUP(TRIM($E8),TRIM('Año 2026'!$E$3:$E$66),'Año 2026'!$R$3:$R$66),"")} | AR8: {=IFERROR(_xlfn.XLOOKUP(TRIM($E8),TRIM('Año 2026'!$E$3:$E$66),'Año 2026'!$S$3:$S$66),"")} | AS8: {=IFERROR(_xlfn.XLOOKUP(TRIM($E8),TRIM('Año 2026'!$E$3:$E$66),'Año 2026'!$T$3:$T$66),"")} | AT8: {=IFERROR(_xlfn.XLOOKUP(TRIM($E8),TRIM('Año 2026'!$E$3:$E$66),'Año 2026'!$U$3:$U$66),"")} | AU8: {=IFERROR(_xlfn.XLOOKUP(TRIM($E8),TRIM('Año 2026'!$E$3:$E$66),'Año 2026'!$V$3:$V$66),"")} | AV8: {=IFERROR(_xlfn.XLOOKUP(TRIM($E8),TRIM('Año 2026'!$E$3:$E$66),'Año 2026'!$W$3:$W$66),"")} | AW8: {=IFERROR(_xlfn.XLOOKUP(TRIM($E8),TRIM('Año 2026'!$E$3:$E$66),'Año 2026'!$X$3:$X$66),"")} | AX8: {=IFERROR(_xlfn.XLOOKUP(TRIM($E8),TRIM('Año 2026'!$E$3:$E$66),'Año 2026'!$Y$3:$Y$66),"")} | AY8: {=IFERROR(_xlfn.XLOOKUP(TRIM($E8),TRIM('Año 2026'!$E$3:$E$66),'Año 2026'!$Z$3:$Z$66),"")} | AZ8: {=IFERROR(_xlfn.XLOOKUP(TRIM($E8),TRIM('Año 2026'!$E$3:$E$66),'Año 2026'!$AA$3:$AA$66),"")} | BA8: {=IFERROR(_xlfn.XLOOKUP(TRIM($E8),TRIM('Año 2026'!$E$3:$E$66),'Año 2026'!$AB$3:$AB$66),"")} | BB8: {=IFERROR(_xlfn.XLOOKUP(TRIM($E8),TRIM('Año 2026'!$E$3:$E$66),'Año 2026'!$AC$3:$AC$66),"")} | BC8: {=IFERROR(_xlfn.XLOOKUP(TRIM($E8),TRIM('Año 2026'!$E$3:$E$66),'Año 2026'!$AD$3:$AD$66),"")}
A9: 8 | B9: 2023 | C9: SNP | D9: No programada - oficio | E9: 00222-2023-SUNEDU/02-13 | F9: En trámite | H9: 49 | I9: Pública | J9: F04L01 | K9: Cusco | L9: Espinar | M9: Yauri | N9: Calle 21 de junio, sector Magisterial | O9: MLI | P9: III, V, VI | Q9: 19, 20, 21, 27, 28, 30, 39, 40, 41, 50 | R9: Denuncia trasladada por la congresista Ruth Luque Ibarra, referida a presuntas deficiencias en la infraestructura, equipamiento y condiciones de seguridad de las escuelas profesionales de Medicina Veterinaria y Educación, ubicadas en la filial Espinar (local F04L01) de la Universidad Nacional de San Antonio Abad del Cusco, consistentes en la inexistencia de un ambiente exclusivo para biblioteca y material bibliográfico insuficiente, insuficiencia de docentes para el dictado de clases, carencias en el centro de cómputo, riesgos eléctricos y deficiencias en las instalaciones sanitarias, así como daños en cielos rasos por filtraciones pluviales. Asimismo, se reporta que los establos y galpones (laboratorios) habrían sido construidos de manera inadecuada, generando riesgo de colapso o fallas estructurales. | S9: ALTA | U9: Respuesta por parte de la Universidad a los requerimientos realizados en el Acta de Supervisión, mediante Oficio N° 598-OGC-2025-UNSAAC del 31.12.25 | V9: 46022 | W9: Se realizó visita de inspección y se realizó requerimiento de información, estaría pendiente la revisión remitida por parte de la Universidad y determinar si es necesario un requerimiento complementario o se procede a elaborar el IR. | X9: JENNY MENDEZ | Y9: OS CBC III Jenny Mendez (Feb-26) CBC V y VI Ysella Arguedas (Feb-26) Priorizada para ser cerrada en mayo 2026. | Z9: Sí | AA9: 46129 | AB9: =IF(AA9<TODAY(),"VENCIDO","POR VENCER") -> VENCIDO | AC9: 46136 | AD9: EN PROCESO | AE9: Informe de Resultados | AF9: {=IFERROR(_xlfn.XLOOKUP(TRIM($E9),TRIM('Año 2026'!$E$3:$E$66),'Año 2026'!$G$3:$G$66),"")} | AG9: {=IFERROR(_xlfn.XLOOKUP(TRIM($E9),TRIM('Año 2026'!$E$3:$E$66),'Año 2026'!$H$3:$H$66),"")} | AH9: {=IFERROR(_xlfn.XLOOKUP(TRIM($E9),TRIM('Año 2026'!$E$3:$E$66),'Año 2026'!$I$3:$I$66),"")} | AI9: {=IFERROR(_xlfn.XLOOKUP(TRIM($E9),TRIM('Año 2026'!$E$3:$E$66),'Año 2026'!$J$3:$J$66),"")} | AJ9: {=IFERROR(_xlfn.XLOOKUP(TRIM($E9),TRIM('Año 2026'!$E$3:$E$66),'Año 2026'!$K$3:$K$66),"")} | AK9: {=IFERROR(_xlfn.XLOOKUP(TRIM($E9),TRIM('Año 2026'!$E$3:$E$66),'Año 2026'!$L$3:$L$66),"")} | AL9: {=IFERROR(_xlfn.XLOOKUP(TRIM($E9),TRIM('Año 2026'!$E$3:$E$66),'Año 2026'!$M$3:$M$66),"")} | AM9: {=IFERROR(_xlfn.XLOOKUP(TRIM($E9),TRIM('Año 2026'!$E$3:$E$66),'Año 2026'!$N$3:$N$66),"")} | AN9: {=IFERROR(_xlfn.XLOOKUP(TRIM($E9),TRIM('Año 2026'!$E$3:$E$66),'Año 2026'!$O$3:$O$66),"")} | AO9: {=IFERROR(_xlfn.XLOOKUP(TRIM($E9),TRIM('Año 2026'!$E$3:$E$66),'Año 2026'!$P$3:$P$66),"")} | AP9: {=IFERROR(_xlfn.XLOOKUP(TRIM($E9),TRIM('Año 2026'!$E$3:$E$66),'Año 2026'!$Q$3:$Q$66),"")} | AQ9: {=IFERROR(_xlfn.XLOOKUP(TRIM($E9),TRIM('Año 2026'!$E$3:$E$66),'Año 2026'!$R$3:$R$66),"")} | AR9: {=IFERROR(_xlfn.XLOOKUP(TRIM($E9),TRIM('Año 2026'!$E$3:$E$66),'Año 2026'!$S$3:$S$66),"")} | AS9: {=IFERROR(_xlfn.XLOOKUP(TRIM($E9),TRIM('Año 2026'!$E$3:$E$66),'Año 2026'!$T$3:$T$66),"")} | AT9: {=IFERROR(_xlfn.XLOOKUP(TRIM($E9),TRIM('Año 2026'!$E$3:$E$66),'Año 2026'!$U$3:$U$66),"")} | AU9: {=IFERROR(_xlfn.XLOOKUP(TRIM($E9),TRIM('Año 2026'!$E$3:$E$66),'Año 2026'!$V$3:$V$66),"")} | AV9: {=IFERROR(_xlfn.XLOOKUP(TRIM($E9),TRIM('Año 2026'!$E$3:$E$66),'Año 2026'!$W$3:$W$66),"")} | AW9: {=IFERROR(_xlfn.XLOOKUP(TRIM($E9),TRIM('Año 2026'!$E$3:$E$66),'Año 2026'!$X$3:$X$66),"")} | AX9: {=IFERROR(_xlfn.XLOOKUP(TRIM($E9),TRIM('Año 2026'!$E$3:$E$66),'Año 2026'!$Y$3:$Y$66),"")} | AY9: {=IFERROR(_xlfn.XLOOKUP(TRIM($E9),TRIM('Año 2026'!$E$3:$E$66),'Año 2026'!$Z$3:$Z$66),"")} | AZ9: {=IFERROR(_xlfn.XLOOKUP(TRIM($E9),TRIM('Año 2026'!$E$3:$E$66),'Año 2026'!$AA$3:$AA$66),"")} | BA9: {=IFERROR(_xlfn.XLOOKUP(TRIM($E9),TRIM('Año 2026'!$E$3:$E$66),'Año 2026'!$AB$3:$AB$66),"")} | BB9: {=IFERROR(_xlfn.XLOOKUP(TRIM($E9),TRIM('Año 2026'!$E$3:$E$66),'Año 2026'!$AC$3:$AC$66),"")} | BC9: {=IFERROR(_xlfn.XLOOKUP(TRIM($E9),TRIM('Año 2026'!$E$3:$E$66),'Año 2026'!$AD$3:$AD$66),"")}
A10: 9 | B10: 2024 | C10: Denuncia | D10: Web | E10: 02805-2024-SUNEDU/02-13 | F10: En trámite | G10: 2024EXT0000048324-SUNEDU | H10: 44 | I10: Pública | K10: Lima | L10: Barranca | M10: Barranca | N10: Avenida Toribio Luzuriaga N° 376, Mz. J - Urbanización La Florida | O10: MLI | P10: IV | R10: Solicita se designe a una nueva vicepresidenta de investigación, debido a que en el transcurso del presente año, la universidad no vendría financiando proyectos de tesis, investigaciones de docentes, emprendimientos empresariales, ni grupos de investigación; con lo cual, se estaría incumpliendo las condiciones básicas de calidad. | S10: BAJA | T10: 1 | U10: La Universidad remitió información solicitada mediante Oficio N° 551-2025-UNAB-CO/ | V10: 45988 | W10: Por lo tanto se sugiere sea derivado a el especialista de Investigacion. Pendiente elaboración de Oficio de Requerimiento Inicial Se cuenta con un Informe N° ​2 – Orden de servicio N° 2036-2025​ de Maria Alejandra Fuentes Diestra, sobre la denuncia de Investigacion, donde considera informacion del Oficio N° 551-2025-UNAB-CO/P, donde se encuentran los enlaces de Investigación. | Y10: Pendiente revisión por Isabel Astete Desde el 04.02.26 al 20.02.26 Priorizada para ser cerrada en febrero 2026. | Z10: Sí | AA10: 46073 | AB10: =IF(AA10<TODAY(),"VENCIDO","POR VENCER") -> VENCIDO | AC10: 46080 | AD10: EN PROCESO | AE10: Carta y/o Oficio | AF10: {=IFERROR(_xlfn.XLOOKUP(TRIM($E10),TRIM('Año 2026'!$E$3:$E$66),'Año 2026'!$G$3:$G$66),"")} | AG10: {=IFERROR(_xlfn.XLOOKUP(TRIM($E10),TRIM('Año 2026'!$E$3:$E$66),'Año 2026'!$H$3:$H$66),"")} | AH10: {=IFERROR(_xlfn.XLOOKUP(TRIM($E10),TRIM('Año 2026'!$E$3:$E$66),'Año 2026'!$I$3:$I$66),"")} | AI10: {=IFERROR(_xlfn.XLOOKUP(TRIM($E10),TRIM('Año 2026'!$E$3:$E$66),'Año 2026'!$J$3:$J$66),"")} | AJ10: {=IFERROR(_xlfn.XLOOKUP(TRIM($E10),TRIM('Año 2026'!$E$3:$E$66),'Año 2026'!$K$3:$K$66),"")} | AK10: {=IFERROR(_xlfn.XLOOKUP(TRIM($E10),TRIM('Año 2026'!$E$3:$E$66),'Año 2026'!$L$3:$L$66),"")} | AL10: {=IFERROR(_xlfn.XLOOKUP(TRIM($E10),TRIM('Año 2026'!$E$3:$E$66),'Año 2026'!$M$3:$M$66),"")} | AM10: {=IFERROR(_xlfn.XLOOKUP(TRIM($E10),TRIM('Año 2026'!$E$3:$E$66),'Año 2026'!$N$3:$N$66),"")} | AN10: {=IFERROR(_xlfn.XLOOKUP(TRIM($E10),TRIM('Año 2026'!$E$3:$E$66),'Año 2026'!$O$3:$O$66),"")} | AO10: {=IFERROR(_xlfn.XLOOKUP(TRIM($E10),TRIM('Año 2026'!$E$3:$E$66),'Año 2026'!$P$3:$P$66),"")} | AP10: {=IFERROR(_xlfn.XLOOKUP(TRIM($E10),TRIM('Año 2026'!$E$3:$E$66),'Año 2026'!$Q$3:$Q$66),"")} | AQ10: {=IFERROR(_xlfn.XLOOKUP(TRIM($E10),TRIM('Año 2026'!$E$3:$E$66),'Año 2026'!$R$3:$R$66),"")} | AR10: {=IFERROR(_xlfn.XLOOKUP(TRIM($E10),TRIM('Año 2026'!$E$3:$E$66),'Año 2026'!$S$3:$S$66),"")} | AS10: {=IFERROR(_xlfn.XLOOKUP(TRIM($E10),TRIM('Año 2026'!$E$3:$E$66),'Año 2026'!$T$3:$T$66),"")} | AT10: {=IFERROR(_xlfn.XLOOKUP(TRIM($E10),TRIM('Año 2026'!$E$3:$E$66),'Año 2026'!$U$3:$U$66),"")} | AU10: {=IFERROR(_xlfn.XLOOKUP(TRIM($E10),TRIM('Año 2026'!$E$3:$E$66),'Año 2026'!$V$3:$V$66),"")} | AV10: {=IFERROR(_xlfn.XLOOKUP(TRIM($E10),TRIM('Año 2026'!$E$3:$E$66),'Año 2026'!$W$3:$W$66),"")} | AW10: {=IFERROR(_xlfn.XLOOKUP(TRIM($E10),TRIM('Año 2026'!$E$3:$E$66),'Año 2026'!$X$3:$X$66),"")} | AX10: {=IFERROR(_xlfn.XLOOKUP(TRIM($E10),TRIM('Año 2026'!$E$3:$E$66),'Año 2026'!$Y$3:$Y$66),"")} | AY10: {=IFERROR(_xlfn.XLOOKUP(TRIM($E10),TRIM('Año 2026'!$E$3:$E$66),'Año 2026'!$Z$3:$Z$66),"")} | AZ10: {=IFERROR(_xlfn.XLOOKUP(TRIM($E10),TRIM('Año 2026'!$E$3:$E$66),'Año 2026'!$AA$3:$AA$66),"")} | BA10: {=IFERROR(_xlfn.XLOOKUP(TRIM($E10),TRIM('Año 2026'!$E$3:$E$66),'Año 2026'!$AB$3:$AB$66),"")} | BB10: {=IFERROR(_xlfn.XLOOKUP(TRIM($E10),TRIM('Año 2026'!$E$3:$E$66),'Año 2026'!$AC$3:$AC$66),"")} | BC10: {=IFERROR(_xlfn.XLOOKUP(TRIM($E10),TRIM('Año 2026'!$E$3:$E$66),'Año 2026'!$AD$3:$AD$66),"")}
A11: 10 | B11: 2023 | C11: SNP | D11: No programada - oficio | E11: 00052-2023-SUNEDU/02-13 | F11: En trámite | H11: 30 | I11: Pública | J11: SL03, SL04, F01L01 | K11: SL03, SL04: Ayacucho | F01L01: Cusco | L11: SL03, SL04: Huamanga | F01L01: La Convención | M11: SL03, SL04: Ayacucho | F01L01: Pichari | N11: SL03 | SL04 | F01L01 | O11: MLI | P11: III, V, VI | Q11: 17, 19, 20, 21, 22, 27, 28, 30, 39, 40, 43, 44, 48 | R11: Caso referido a presuntas deficiencias en la infraestructura, equipamiento y servicios complementarios de la Universidad Nacional de San Cristóbal de Huamanga, tanto en la sede principal como en la filial La Convención – Pichari (local F01L01), consistentes en condiciones de inhabitabilidad de ambientes académicos, deficiencias de seguridad en instalaciones (luminarias deterioradas, conexiones expuestas y falta de ventilación), carencias en los servicios de salud universitarios, limitaciones en la operatividad del comedor universitario y de la residencia estudiantil, así como la ausencia de cerco perimétrico adecuado en la filial. Asimismo, se reporta insuficiencia de personal docente en determinados programas académicos y la falta de acreditación vigente del derecho de uso del local F01L01. | S11: ALTA | T11: 2 | U11: Respuesta por parte de la Universidad a los requerimientos realizados en el Acta de Supervisión, mediante Oficio N° 542-2025-UNSCH-R del 11.12.25 | V11: 46002 | W11: Está pendiente la elaboración del Informe de Resultados, ya que se recopiló información en el 2023 y en el 2025. | Y11: IR Antecedentes Barzen Manrique CBC III Carla La Torre 01.04.26 al 15.04.26 CBC V y VI 02.03.26 al 13.03.26 Priorizada para ser cerrada en abril 2026 | Z11: Sí | AA11: 46129 | AB11: =IF(AA11<TODAY(),"VENCIDO","POR VENCER") -> VENCIDO | AC11: 46136 | AD11: EN PROCESO | AE11: Informe de Resultados | AF11: {=IFERROR(_xlfn.XLOOKUP(TRIM($E11),TRIM('Año 2026'!$E$3:$E$66),'Año 2026'!$G$3:$G$66),"")} | AG11: {=IFERROR(_xlfn.XLOOKUP(TRIM($E11),TRIM('Año 2026'!$E$3:$E$66),'Año 2026'!$H$3:$H$66),"")} | AH11: {=IFERROR(_xlfn.XLOOKUP(TRIM($E11),TRIM('Año 2026'!$E$3:$E$66),'Año 2026'!$I$3:$I$66),"")} | AI11: {=IFERROR(_xlfn.XLOOKUP(TRIM($E11),TRIM('Año 2026'!$E$3:$E$66),'Año 2026'!$J$3:$J$66),"")} | AJ11: {=IFERROR(_xlfn.XLOOKUP(TRIM($E11),TRIM('Año 2026'!$E$3:$E$66),'Año 2026'!$K$3:$K$66),"")} | AK11: {=IFERROR(_xlfn.XLOOKUP(TRIM($E11),TRIM('Año 2026'!$E$3:$E$66),'Año 2026'!$L$3:$L$66),"")} | AL11: {=IFERROR(_xlfn.XLOOKUP(TRIM($E11),TRIM('Año 2026'!$E$3:$E$66),'Año 2026'!$M$3:$M$66),"")} | AM11: {=IFERROR(_xlfn.XLOOKUP(TRIM($E11),TRIM('Año 2026'!$E$3:$E$66),'Año 2026'!$N$3:$N$66),"")} | AN11: {=IFERROR(_xlfn.XLOOKUP(TRIM($E11),TRIM('Año 2026'!$E$3:$E$66),'Año 2026'!$O$3:$O$66),"")} | AO11: {=IFERROR(_xlfn.XLOOKUP(TRIM($E11),TRIM('Año 2026'!$E$3:$E$66),'Año 2026'!$P$3:$P$66),"")} | AP11: {=IFERROR(_xlfn.XLOOKUP(TRIM($E11),TRIM('Año 2026'!$E$3:$E$66),'Año 2026'!$Q$3:$Q$66),"")} | AQ11: {=IFERROR(_xlfn.XLOOKUP(TRIM($E11),TRIM('Año 2026'!$E$3:$E$66),'Año 2026'!$R$3:$R$66),"")} | AR11: {=IFERROR(_xlfn.XLOOKUP(TRIM($E11),TRIM('Año 2026'!$E$3:$E$66),'Año 2026'!$S$3:$S$66),"")} | AS11: {=IFERROR(_xlfn.XLOOKUP(TRIM($E11),TRIM('Año 2026'!$E$3:$E$66),'Año 2026'!$T$3:$T$66),"")} | AT11: {=IFERROR(_xlfn.XLOOKUP(TRIM($E11),TRIM('Año 2026'!$E$3:$E$66),'Año 2026'!$U$3:$U$66),"")} | AU11: {=IFERROR(_xlfn.XLOOKUP(TRIM($E11),TRIM('Año 2026'!$E$3:$E$66),'Año 2026'!$V$3:$V$66),"")} | AV11: {=IFERROR(_xlfn.XLOOKUP(TRIM($E11),TRIM('Año 2026'!$E$3:$E$66),'Año 2026'!$W$3:$W$66),"")} | AW11: {=IFERROR(_xlfn.XLOOKUP(TRIM($E11),TRIM('Año 2026'!$E$3:$E$66),'Año 2026'!$X$3:$X$66),"")} | AX11: {=IFERROR(_xlfn.XLOOKUP(TRIM($E11),TRIM('Año 2026'!$E$3:$E$66),'Año 2026'!$Y$3:$Y$66),"")} | AY11: {=IFERROR(_xlfn.XLOOKUP(TRIM($E11),TRIM('Año 2026'!$E$3:$E$66),'Año 2026'!$Z$3:$Z$66),"")} | AZ11: {=IFERROR(_xlfn.XLOOKUP(TRIM($E11),TRIM('Año 2026'!$E$3:$E$66),'Año 2026'!$AA$3:$AA$66),"")} | BA11: {=IFERROR(_xlfn.XLOOKUP(TRIM($E11),TRIM('Año 2026'!$E$3:$E$66),'Año 2026'!$AB$3:$AB$66),"")} | BB11: {=IFERROR(_xlfn.XLOOKUP(TRIM($E11),TRIM('Año 2026'!$E$3:$E$66),'Año 2026'!$AC$3:$AC$66),"")} | BC11: {=IFERROR(_xlfn.XLOOKUP(TRIM($E11),TRIM('Año 2026'!$E$3:$E$66),'Año 2026'!$AD$3:$AD$66),"")}
A12: 11 | B12: 2024 | C12: Denuncia | D12: Correo electrónico | E12: 01773-2024-SUNEDU/02-13 | F12: En trámite | G12: 2024EXT0000025963-SUNEDU | H12: 41 | I12: Pública | J12: SL01, SL02, SL03, SL04 | K12: La Libertad | L12: Sanchez Carrion | M12: Huamachuco | N12: Local SL01 Ramiro Priale N°540 Huamachuco (conducente a grado academico) | Local SL02 Garcilaso de la Vega N°905- Huamachuco. (conducente a grado academico) | Local SL03 ubicado en el centro de la ciudad de Huamachuco, cuyo uso es para fines administrativos | Local SL04, Av. Los Sauces, predio Unidad Catastral N°31527 denominado “Tantapusha”, ubicado al sur de la ciudad de Huamachuco, a | aproximadamente 5.3 km del local SL01. En dicho local, la Universidad construirá su nuevo campus universitario. | O12: MLI | P12: III, IV | Q12: 19, 27 | R12: El Sindicato de Trabajadores CAS de la Universidad Nacional Ciro Alegría, pone en conocimiento irregularidades a la oferta del servicio educativo: Sindicato de trabajadores de la UNCA solicitan la reconformacion de la comision organizadora por las siguientes razones: requerimientos mejora continua en instalaciones puesta en marcha de grupos electrogenos, ejecucion de proyectos CUI N°2471427, CUI:2509818, CUI:2511627 y CUI:2513857 en el local SL04 , evidencias de la implementacion de la infraestructura, maquinaria y equipos para el comedor universitario en el local SL04. (La denuncia refiere a los requerimientos que no han presentado la Universidad) | S12: ALTA | T12: 2 | U12: La Universidad presentó información con Oficio N° 0498-2025-UNCA/P-CO en respuesta al OFICIO N° 03963-2025-SUNEDU-DS-DIRESESU-UVE | V12: 45905 | W12: En la carpta Z se encuentra el OFICIO N° 03497-2025-SUNEDU-DS-DIRESESU-UVE (08.09.25), con el que se requirió información para 4 expedientes (01773-2024-SUNEDU/02-13, 01020-2025-SUNEDU/02-13, 01186-2025-SUNEDU/02-13 y 02160-2025-SUNEDU/02-13) y comunica que se realizará Visita de Inspección los dias 15 al 19 de setiembre a 5 locales. Isabel comenzó con la evaluación de la CBC IV el 10.02.26. | X12: MANUEL HURTADO | Y12: OS Antecedentes Barzen (Feb-26) CBC III Manuel Hurtado (Feb-26) CBC IV Liz (pendiente definir fechas) Priorizada para ser cerrada en julio 2026. | Z12: Sí | AA12: 46227 | AB12: =IF(AA12<TODAY(),"VENCIDO","POR VENCER") -> POR VENCER | AC12: 46234 | AD12: EN PROCESO | AE12: Carta y/o Oficio | AF12: {=IFERROR(_xlfn.XLOOKUP(TRIM($E12),TRIM('Año 2026'!$E$3:$E$66),'Año 2026'!$G$3:$G$66),"")} | AG12: {=IFERROR(_xlfn.XLOOKUP(TRIM($E12),TRIM('Año 2026'!$E$3:$E$66),'Año 2026'!$H$3:$H$66),"")} | AH12: {=IFERROR(_xlfn.XLOOKUP(TRIM($E12),TRIM('Año 2026'!$E$3:$E$66),'Año 2026'!$I$3:$I$66),"")} | AI12: {=IFERROR(_xlfn.XLOOKUP(TRIM($E12),TRIM('Año 2026'!$E$3:$E$66),'Año 2026'!$J$3:$J$66),"")} | AJ12: {=IFERROR(_xlfn.XLOOKUP(TRIM($E12),TRIM('Año 2026'!$E$3:$E$66),'Año 2026'!$K$3:$K$66),"")} | AK12: {=IFERROR(_xlfn.XLOOKUP(TRIM($E12),TRIM('Año 2026'!$E$3:$E$66),'Año 2026'!$L$3:$L$66),"")} | AL12: {=IFERROR(_xlfn.XLOOKUP(TRIM($E12),TRIM('Año 2026'!$E$3:$E$66),'Año 2026'!$M$3:$M$66),"")} | AM12: {=IFERROR(_xlfn.XLOOKUP(TRIM($E12),TRIM('Año 2026'!$E$3:$E$66),'Año 2026'!$N$3:$N$66),"")} | AN12: {=IFERROR(_xlfn.XLOOKUP(TRIM($E12),TRIM('Año 2026'!$E$3:$E$66),'Año 2026'!$O$3:$O$66),"")} | AO12: {=IFERROR(_xlfn.XLOOKUP(TRIM($E12),TRIM('Año 2026'!$E$3:$E$66),'Año 2026'!$P$3:$P$66),"")} | AP12: {=IFERROR(_xlfn.XLOOKUP(TRIM($E12),TRIM('Año 2026'!$E$3:$E$66),'Año 2026'!$Q$3:$Q$66),"")} | AQ12: {=IFERROR(_xlfn.XLOOKUP(TRIM($E12),TRIM('Año 2026'!$E$3:$E$66),'Año 2026'!$R$3:$R$66),"")} | AR12: {=IFERROR(_xlfn.XLOOKUP(TRIM($E12),TRIM('Año 2026'!$E$3:$E$66),'Año 2026'!$S$3:$S$66),"")} | AS12: {=IFERROR(_xlfn.XLOOKUP(TRIM($E12),TRIM('Año 2026'!$E$3:$E$66),'Año 2026'!$T$3:$T$66),"")} | AT12: {=IFERROR(_xlfn.XLOOKUP(TRIM($E12),TRIM('Año 2026'!$E$3:$E$66),'Año 2026'!$U$3:$U$66),"")} | AU12: {=IFERROR(_xlfn.XLOOKUP(TRIM($E12),TRIM('Año 2026'!$E$3:$E$66),'Año 2026'!$V$3:$V$66),"")} | AV12: {=IFERROR(_xlfn.XLOOKUP(TRIM($E12),TRIM('Año 2026'!$E$3:$E$66),'Año 2026'!$W$3:$W$66),"")} | AW12: {=IFERROR(_xlfn.XLOOKUP(TRIM($E12),TRIM('Año 2026'!$E$3:$E$66),'Año 2026'!$X$3:$X$66),"")} | AX12: {=IFERROR(_xlfn.XLOOKUP(TRIM($E12),TRIM('Año 2026'!$E$3:$E$66),'Año 2026'!$Y$3:$Y$66),"")} | AY12: {=IFERROR(_xlfn.XLOOKUP(TRIM($E12),TRIM('Año 2026'!$E$3:$E$66),'Año 2026'!$Z$3:$Z$66),"")} | AZ12: {=IFERROR(_xlfn.XLOOKUP(TRIM($E12),TRIM('Año 2026'!$E$3:$E$66),'Año 2026'!$AA$3:$AA$66),"")} | BA12: {=IFERROR(_xlfn.XLOOKUP(TRIM($E12),TRIM('Año 2026'!$E$3:$E$66),'Año 2026'!$AB$3:$AB$66),"")} | BB12: {=IFERROR(_xlfn.XLOOKUP(TRIM($E12),TRIM('Año 2026'!$E$3:$E$66),'Año 2026'!$AC$3:$AC$66),"")} | BC12: {=IFERROR(_xlfn.XLOOKUP(TRIM($E12),TRIM('Año 2026'!$E$3:$E$66),'Año 2026'!$AD$3:$AD$66),"")}
A13: 12 | B13: 2024 | C13: Denuncia | D13: Web | E13: 01155-2024-SUNEDU/02-13 | F13: En trámite | G13: 2024EXT0000015663-SUNEDU, 2024EXT0000038187-SUNEDU | H13: 2 | I13: Pública | J13: SL02, SL08 | K13: Lima | L13: Lima | M13: Lima | N13: 1.-Av. Nicolas de Pierola N° 262 / Cañete 710, Lima | 2.-Jr. Iquique N°127, 129, distrito de Breña, Lima | O13: MLI | P13: III | Q13: 19, 27, 28, 29 | R13: Manifiesta que habría sido víctima de engaño por parte de la universidad antes de su postulación, ya que le habrían indicado que las clases de la carrera de Contabilidad y Economía iban a ser dictadas en la nueva sede Oquendo; sin embargo, tras haber ingresado le indicarían que las clases continuarían dictándose en la sede ubicada en la Avenida Nicolás de Piérola. Estan vinculados dos (2)denuncias: 1.-Irregularidades en la Av Nicolas de Pierola 2024EXT0000015663-SUNEDU, del 03/05/2024 (las carreras de Contabilidad y Economía, este año se hizo de manera oficial por sus redes y por el prospecto, entonces muchos gracias a ello postularon a dichas carreras con el fin de llevar sus clases en la sede Oquendo de la UNFV por temas de distancia y/o infraestructura moderna. Pero ahora al ser ingresantes se informa desde la facultad que las clases aún seguirán siendo en la antigua sede (Av. Nicolás de Piérola 262, Lima 15001) 2.- Irregularidades sede Iquique 2024EXT0000038187-SUNEDU, del 23/09/2024 ( 1. El espacio es demasiado pequeno para la cantidad de estudiantes que somos, y nuestra facultad en los 3 ultimos procesos de admision amplio las vacantes de manera significativa por lo cual ahora somos demasiado e incluso por ello tomamos clases en otras sedes como la de odontologia sede pueblo libre. Se nos dice desde hace tiempo, que hay una sede en construccion (Oquendo) pero hasta ahora no hay avances.) | S13: MEDIA | T13: 1 | U13: Mediante la Carta Nº 01239-2024-SUNEDU-DS-DIRESESU-UVE, la SUNEDU comunica al denunciante de las acciones que se han venido tomando. Mediante OFICIO Nº 00789-2024-SUNEDU-DS-DIRESESU-UVE del 11/11/24 se remite a la Muni de Breña el caso en cuanto a los pasos de escaleras | V13: 45614 | W13: Se le responde al denunciante que el local ubicado en Av. Néstor Gambeta Dpto. Mz. 85, Ventanilla, Callao, solicitó modificación de licencia el 1 de abril de 2024 | Y13: Pendiente visita del 18.02.26 al 20.02.26 por Carla La Torre + Néstor Ticse+ Víctor dela Cruz+ Abogada Falta programar producto Priorizada para ser cerrada en diciembre 2026. | AA13: 46374 | AB13: =IF(AA13<TODAY(),"VENCIDO","POR VENCER") -> POR VENCER | AC13: 46379 | AD13: EN PROCESO | AE13: Carta y/o Oficio | AF13: {=IFERROR(_xlfn.XLOOKUP(TRIM($E13),TRIM('Año 2026'!$E$3:$E$66),'Año 2026'!$G$3:$G$66),"")} -> OFICIO Nº 02249-2026-SUNEDU-DS-DIRESESU-UVE | AG13: {=IFERROR(_xlfn.XLOOKUP(TRIM($E13),TRIM('Año 2026'!$E$3:$E$66),'Año 2026'!$H$3:$H$66),"")} -> 0 | AH13: {=IFERROR(_xlfn.XLOOKUP(TRIM($E13),TRIM('Año 2026'!$E$3:$E$66),'Año 2026'!$I$3:$I$66),"")} -> 0 | AI13: {=IFERROR(_xlfn.XLOOKUP(TRIM($E13),TRIM('Año 2026'!$E$3:$E$66),'Año 2026'!$J$3:$J$66),"")} -> 0 | AJ13: {=IFERROR(_xlfn.XLOOKUP(TRIM($E13),TRIM('Año 2026'!$E$3:$E$66),'Año 2026'!$K$3:$K$66),"")} -> 0 | AK13: {=IFERROR(_xlfn.XLOOKUP(TRIM($E13),TRIM('Año 2026'!$E$3:$E$66),'Año 2026'!$L$3:$L$66),"")} -> 0 | AL13: {=IFERROR(_xlfn.XLOOKUP(TRIM($E13),TRIM('Año 2026'!$E$3:$E$66),'Año 2026'!$M$3:$M$66),"")} -> 0 | AM13: {=IFERROR(_xlfn.XLOOKUP(TRIM($E13),TRIM('Año 2026'!$E$3:$E$66),'Año 2026'!$N$3:$N$66),"")} -> 0 | AN13: {=IFERROR(_xlfn.XLOOKUP(TRIM($E13),TRIM('Año 2026'!$E$3:$E$66),'Año 2026'!$O$3:$O$66),"")} -> 0 | AO13: {=IFERROR(_xlfn.XLOOKUP(TRIM($E13),TRIM('Año 2026'!$E$3:$E$66),'Año 2026'!$P$3:$P$66),"")} -> 0 | AP13: {=IFERROR(_xlfn.XLOOKUP(TRIM($E13),TRIM('Año 2026'!$E$3:$E$66),'Año 2026'!$Q$3:$Q$66),"")} -> 0 | AQ13: {=IFERROR(_xlfn.XLOOKUP(TRIM($E13),TRIM('Año 2026'!$E$3:$E$66),'Año 2026'!$R$3:$R$66),"")} -> 0 | AR13: {=IFERROR(_xlfn.XLOOKUP(TRIM($E13),TRIM('Año 2026'!$E$3:$E$66),'Año 2026'!$S$3:$S$66),"")} -> 0 | AS13: {=IFERROR(_xlfn.XLOOKUP(TRIM($E13),TRIM('Año 2026'!$E$3:$E$66),'Año 2026'!$T$3:$T$66),"")} -> 0 | AT13: {=IFERROR(_xlfn.XLOOKUP(TRIM($E13),TRIM('Año 2026'!$E$3:$E$66),'Año 2026'!$U$3:$U$66),"")} -> 0 | AU13: {=IFERROR(_xlfn.XLOOKUP(TRIM($E13),TRIM('Año 2026'!$E$3:$E$66),'Año 2026'!$V$3:$V$66),"")} -> 0 | AV13: {=IFERROR(_xlfn.XLOOKUP(TRIM($E13),TRIM('Año 2026'!$E$3:$E$66),'Año 2026'!$W$3:$W$66),"")} -> 0 | AW13: {=IFERROR(_xlfn.XLOOKUP(TRIM($E13),TRIM('Año 2026'!$E$3:$E$66),'Año 2026'!$X$3:$X$66),"")} -> 0 | AX13: {=IFERROR(_xlfn.XLOOKUP(TRIM($E13),TRIM('Año 2026'!$E$3:$E$66),'Año 2026'!$Y$3:$Y$66),"")} -> 0 | AY13: {=IFERROR(_xlfn.XLOOKUP(TRIM($E13),TRIM('Año 2026'!$E$3:$E$66),'Año 2026'!$Z$3:$Z$66),"")} -> 0 | AZ13: {=IFERROR(_xlfn.XLOOKUP(TRIM($E13),TRIM('Año 2026'!$E$3:$E$66),'Año 2026'!$AA$3:$AA$66),"")} -> 0 | BA13: {=IFERROR(_xlfn.XLOOKUP(TRIM($E13),TRIM('Año 2026'!$E$3:$E$66),'Año 2026'!$AB$3:$AB$66),"")} -> 0 | BB13: {=IFERROR(_xlfn.XLOOKUP(TRIM($E13),TRIM('Año 2026'!$E$3:$E$66),'Año 2026'!$AC$3:$AC$66),"")} -> 0 | BC13: {=IFERROR(_xlfn.XLOOKUP(TRIM($E13),TRIM('Año 2026'!$E$3:$E$66),'Año 2026'!$AD$3:$AD$66),"")} -> 0
A14: 13 | B14: 2024 | C14: SNP | D14: No programada - oficio | E14: 00548-2024-SUNEDU/02-13 | F14: En trámite | H14: 36 | I14: Pública | J14: F04L01 | K14: Cajamarca | L14: Chota | M14: Chota | N14: Av. Agricultura 144 | O14: MLI | P14: III | Q14: 17 | R14: Caso referido a la vigencia del derecho de uso del local F04L01 de la Universidad Nacional de Cajamarca, ubicado en la filial Chota, debido a que el contrato de arrendamiento que sustentó el licenciamiento institucional habría vencido al 31 de diciembre de 2018, sin que se haya identificado documentación vigente que acredite el derecho de uso a favor de la universidad. Esta situación fue advertida en el marco de acciones de supervisión, al verificarse que el local continúa siendo utilizado para la prestación del servicio educativo sin contar con sustento registral actualizado. | S14: BAJA | T14: 1 | U14: Se emitió el segundo reiterativo de información, mediante Oficio N.° 01381-2025-SUNEDU-DS-DIRESESU-UVE del 24.04.25 | V14: 45771 | W14: La Universidad no ha remtido la información solicitada, el oficio fue elaborado por Isabel. Al buscar en Google, se indica que el local está "permanentemente cerrado"; sin embargo, se ha identificado en las redes sociales que ha habido actividad hasta noviembre de 2025. | Y14: Pendiente enviar tercer reiterativo de información Pendiente visita en abril 2 personas. Priorizada para ser cerrada en junio 2026. | Z14: Sí | AA14: 46192 | AB14: =IF(AA14<TODAY(),"VENCIDO","POR VENCER") -> POR VENCER | AC14: 46199 | AD14: EN PROCESO | AE14: Informe de Resultados | AF14: {=IFERROR(_xlfn.XLOOKUP(TRIM($E14),TRIM('Año 2026'!$E$3:$E$66),'Año 2026'!$G$3:$G$66),"")} | AG14: {=IFERROR(_xlfn.XLOOKUP(TRIM($E14),TRIM('Año 2026'!$E$3:$E$66),'Año 2026'!$H$3:$H$66),"")} | AH14: {=IFERROR(_xlfn.XLOOKUP(TRIM($E14),TRIM('Año 2026'!$E$3:$E$66),'Año 2026'!$I$3:$I$66),"")} | AI14: {=IFERROR(_xlfn.XLOOKUP(TRIM($E14),TRIM('Año 2026'!$E$3:$E$66),'Año 2026'!$J$3:$J$66),"")} | AJ14: {=IFERROR(_xlfn.XLOOKUP(TRIM($E14),TRIM('Año 2026'!$E$3:$E$66),'Año 2026'!$K$3:$K$66),"")} | AK14: {=IFERROR(_xlfn.XLOOKUP(TRIM($E14),TRIM('Año 2026'!$E$3:$E$66),'Año 2026'!$L$3:$L$66),"")} | AL14: {=IFERROR(_xlfn.XLOOKUP(TRIM($E14),TRIM('Año 2026'!$E$3:$E$66),'Año 2026'!$M$3:$M$66),"")} | AM14: {=IFERROR(_xlfn.XLOOKUP(TRIM($E14),TRIM('Año 2026'!$E$3:$E$66),'Año 2026'!$N$3:$N$66),"")} | AN14: {=IFERROR(_xlfn.XLOOKUP(TRIM($E14),TRIM('Año 2026'!$E$3:$E$66),'Año 2026'!$O$3:$O$66),"")} | AO14: {=IFERROR(_xlfn.XLOOKUP(TRIM($E14),TRIM('Año 2026'!$E$3:$E$66),'Año 2026'!$P$3:$P$66),"")} | AP14: {=IFERROR(_xlfn.XLOOKUP(TRIM($E14),TRIM('Año 2026'!$E$3:$E$66),'Año 2026'!$Q$3:$Q$66),"")} | AQ14: {=IFERROR(_xlfn.XLOOKUP(TRIM($E14),TRIM('Año 2026'!$E$3:$E$66),'Año 2026'!$R$3:$R$66),"")} | AR14: {=IFERROR(_xlfn.XLOOKUP(TRIM($E14),TRIM('Año 2026'!$E$3:$E$66),'Año 2026'!$S$3:$S$66),"")} | AS14: {=IFERROR(_xlfn.XLOOKUP(TRIM($E14),TRIM('Año 2026'!$E$3:$E$66),'Año 2026'!$T$3:$T$66),"")} | AT14: {=IFERROR(_xlfn.XLOOKUP(TRIM($E14),TRIM('Año 2026'!$E$3:$E$66),'Año 2026'!$U$3:$U$66),"")} | AU14: {=IFERROR(_xlfn.XLOOKUP(TRIM($E14),TRIM('Año 2026'!$E$3:$E$66),'Año 2026'!$V$3:$V$66),"")} | AV14: {=IFERROR(_xlfn.XLOOKUP(TRIM($E14),TRIM('Año 2026'!$E$3:$E$66),'Año 2026'!$W$3:$W$66),"")} | AW14: {=IFERROR(_xlfn.XLOOKUP(TRIM($E14),TRIM('Año 2026'!$E$3:$E$66),'Año 2026'!$X$3:$X$66),"")} | AX14: {=IFERROR(_xlfn.XLOOKUP(TRIM($E14),TRIM('Año 2026'!$E$3:$E$66),'Año 2026'!$Y$3:$Y$66),"")} | AY14: {=IFERROR(_xlfn.XLOOKUP(TRIM($E14),TRIM('Año 2026'!$E$3:$E$66),'Año 2026'!$Z$3:$Z$66),"")} | AZ14: {=IFERROR(_xlfn.XLOOKUP(TRIM($E14),TRIM('Año 2026'!$E$3:$E$66),'Año 2026'!$AA$3:$AA$66),"")} | BA14: {=IFERROR(_xlfn.XLOOKUP(TRIM($E14),TRIM('Año 2026'!$E$3:$E$66),'Año 2026'!$AB$3:$AB$66),"")} | BB14: {=IFERROR(_xlfn.XLOOKUP(TRIM($E14),TRIM('Año 2026'!$E$3:$E$66),'Año 2026'!$AC$3:$AC$66),"")} | BC14: {=IFERROR(_xlfn.XLOOKUP(TRIM($E14),TRIM('Año 2026'!$E$3:$E$66),'Año 2026'!$AD$3:$AD$66),"")}
A15: 14 | B15: 2024 | C15: Denuncia | D15: Correo electrónico | E15: 02873-2024-SUNEDU/02-13 | F15: Atendido | G15: 2024EXT0000048933-SUNEDU | H15: 2 | I15: Pública | J15: SL10 | K15: Lima | L15: Lima | M15: El Agustino | N15: Jirón Chepén - Av. Atarjea - Urb. Villa Hermosa | O15: MLI | P15: III | Q15: 27 | R15: Hace de conocimiento destrucción del Laboratorio de Investigación de Técnica Quirúrgica y Cirugía Experimental, inaugurado el 14 de julio de 1999. | S15: MEDIA | T15: 2 | U15: Requerimiento de información elaborado. Pendiente de notificación,se estaría a la espera de información. | V15: 45994 | W15: Oficio de notificación pendiente de firma de la Ejecutiva. | Y15: Pendiente realizar primer reiterativo OS Antecedentes Barzen Manrique (Mar-26) CBC III Víctor de la Cruz (Mar-26) Priorizada para ser cerrada en agosto 2026. | Z15: Sí | AA15: 46255 | AB15: =IF(AA15<TODAY(),"VENCIDO","POR VENCER") -> POR VENCER | AC15: 46262 | AD15: COMPLETADO | AE15: Se atendió con la Carta N° 01915-2026-SUNEDU-DS-DIRESESU-UVE y del Oficio N° 02658-2026-SUNEDU-DS-DIRESESU-UVE. | AF15: {=IFERROR(_xlfn.XLOOKUP(TRIM($E15),TRIM('Año 2026'!$E$3:$E$66),'Año 2026'!$G$3:$G$66),"")} | AG15: {=IFERROR(_xlfn.XLOOKUP(TRIM($E15),TRIM('Año 2026'!$E$3:$E$66),'Año 2026'!$H$3:$H$66),"")} | AH15: {=IFERROR(_xlfn.XLOOKUP(TRIM($E15),TRIM('Año 2026'!$E$3:$E$66),'Año 2026'!$I$3:$I$66),"")} | AI15: {=IFERROR(_xlfn.XLOOKUP(TRIM($E15),TRIM('Año 2026'!$E$3:$E$66),'Año 2026'!$J$3:$J$66),"")} | AJ15: {=IFERROR(_xlfn.XLOOKUP(TRIM($E15),TRIM('Año 2026'!$E$3:$E$66),'Año 2026'!$K$3:$K$66),"")} | AK15: {=IFERROR(_xlfn.XLOOKUP(TRIM($E15),TRIM('Año 2026'!$E$3:$E$66),'Año 2026'!$L$3:$L$66),"")} | AL15: {=IFERROR(_xlfn.XLOOKUP(TRIM($E15),TRIM('Año 2026'!$E$3:$E$66),'Año 2026'!$M$3:$M$66),"")} | AM15: {=IFERROR(_xlfn.XLOOKUP(TRIM($E15),TRIM('Año 2026'!$E$3:$E$66),'Año 2026'!$N$3:$N$66),"")} | AN15: {=IFERROR(_xlfn.XLOOKUP(TRIM($E15),TRIM('Año 2026'!$E$3:$E$66),'Año 2026'!$O$3:$O$66),"")} | AO15: {=IFERROR(_xlfn.XLOOKUP(TRIM($E15),TRIM('Año 2026'!$E$3:$E$66),'Año 2026'!$P$3:$P$66),"")} | AP15: {=IFERROR(_xlfn.XLOOKUP(TRIM($E15),TRIM('Año 2026'!$E$3:$E$66),'Año 2026'!$Q$3:$Q$66),"")} | AQ15: {=IFERROR(_xlfn.XLOOKUP(TRIM($E15),TRIM('Año 2026'!$E$3:$E$66),'Año 2026'!$R$3:$R$66),"")} | AR15: {=IFERROR(_xlfn.XLOOKUP(TRIM($E15),TRIM('Año 2026'!$E$3:$E$66),'Año 2026'!$S$3:$S$66),"")} | AS15: {=IFERROR(_xlfn.XLOOKUP(TRIM($E15),TRIM('Año 2026'!$E$3:$E$66),'Año 2026'!$T$3:$T$66),"")} | AT15: {=IFERROR(_xlfn.XLOOKUP(TRIM($E15),TRIM('Año 2026'!$E$3:$E$66),'Año 2026'!$U$3:$U$66),"")} | AU15: {=IFERROR(_xlfn.XLOOKUP(TRIM($E15),TRIM('Año 2026'!$E$3:$E$66),'Año 2026'!$V$3:$V$66),"")} | AV15: {=IFERROR(_xlfn.XLOOKUP(TRIM($E15),TRIM('Año 2026'!$E$3:$E$66),'Año 2026'!$W$3:$W$66),"")} | AW15: {=IFERROR(_xlfn.XLOOKUP(TRIM($E15),TRIM('Año 2026'!$E$3:$E$66),'Año 2026'!$X$3:$X$66),"")} | AX15: {=IFERROR(_xlfn.XLOOKUP(TRIM($E15),TRIM('Año 2026'!$E$3:$E$66),'Año 2026'!$Y$3:$Y$66),"")} | AY15: {=IFERROR(_xlfn.XLOOKUP(TRIM($E15),TRIM('Año 2026'!$E$3:$E$66),'Año 2026'!$Z$3:$Z$66),"")} | AZ15: {=IFERROR(_xlfn.XLOOKUP(TRIM($E15),TRIM('Año 2026'!$E$3:$E$66),'Año 2026'!$AA$3:$AA$66),"")} | BA15: {=IFERROR(_xlfn.XLOOKUP(TRIM($E15),TRIM('Año 2026'!$E$3:$E$66),'Año 2026'!$AB$3:$AB$66),"")} | BB15: {=IFERROR(_xlfn.XLOOKUP(TRIM($E15),TRIM('Año 2026'!$E$3:$E$66),'Año 2026'!$AC$3:$AC$66),"")} | BC15: {=IFERROR(_xlfn.XLOOKUP(TRIM($E15),TRIM('Año 2026'!$E$3:$E$66),'Año 2026'!$AD$3:$AD$66),"")}
A16: 15 | B16: 2024 | C16: Accion Directa | D16: Correo electrónico | E16: AD-034-2024 | F16: En trámite | H16: 52 | I16: Pública | J16: SL01 | K16: Piura | L16: Sullana | M16: Sullana | N16: Av. San Hilarión N° 101, Zona de expansión urbana de Sullana, margen izquierda, entre la urbanización popular Villa Perú Canadá | O16: MLI | P16: III | Q16: 27, 28 | R16: Las acciones indagatorias iniciarion por falta de implementación de laboratorios y mobiliario en algunas carreras profesionales, lo que involucrarIa una posible afectación al mantenimiento de la CBC. | S16: MEDIA | T16: 1 | U16: Visita de inspección realizada en mayo 2025, al respecto la Universidad presentó información y se cuenta con 1 IR elaborado pendiente de revisión final. | V16: 45806 | W16: Este expediente tiene pendiente una revisión final del IR, en el cual se precisen aspectos de la implrementación de ambientes (equipamiento y mobiliairio), y se realice el cruce de mallas respecto a los ambientes requeridos y de la ejecución de los proyectos de inversión y sus fechas. | Y16: Antecedentes Barzen Manrique CBC III Carla La Torre 01.06.26 al 19.06.26 Priorizada para ser cerrada en junio 2026. | Z16: Sí | AA16: 46192 | AB16: =IF(AA16<TODAY(),"VENCIDO","POR VENCER") -> POR VENCER | AC16: 46199 | AD16: EN PROCESO | AE16: Informe y/o Requerimiento de información | AF16: {=IFERROR(_xlfn.XLOOKUP(TRIM($E16),TRIM('Año 2026'!$E$3:$E$66),'Año 2026'!$G$3:$G$66),"")} | AG16: {=IFERROR(_xlfn.XLOOKUP(TRIM($E16),TRIM('Año 2026'!$E$3:$E$66),'Año 2026'!$H$3:$H$66),"")} | AH16: {=IFERROR(_xlfn.XLOOKUP(TRIM($E16),TRIM('Año 2026'!$E$3:$E$66),'Año 2026'!$I$3:$I$66),"")} | AI16: {=IFERROR(_xlfn.XLOOKUP(TRIM($E16),TRIM('Año 2026'!$E$3:$E$66),'Año 2026'!$J$3:$J$66),"")} | AJ16: {=IFERROR(_xlfn.XLOOKUP(TRIM($E16),TRIM('Año 2026'!$E$3:$E$66),'Año 2026'!$K$3:$K$66),"")} | AK16: {=IFERROR(_xlfn.XLOOKUP(TRIM($E16),TRIM('Año 2026'!$E$3:$E$66),'Año 2026'!$L$3:$L$66),"")} | AL16: {=IFERROR(_xlfn.XLOOKUP(TRIM($E16),TRIM('Año 2026'!$E$3:$E$66),'Año 2026'!$M$3:$M$66),"")} | AM16: {=IFERROR(_xlfn.XLOOKUP(TRIM($E16),TRIM('Año 2026'!$E$3:$E$66),'Año 2026'!$N$3:$N$66),"")} | AN16: {=IFERROR(_xlfn.XLOOKUP(TRIM($E16),TRIM('Año 2026'!$E$3:$E$66),'Año 2026'!$O$3:$O$66),"")} | AO16: {=IFERROR(_xlfn.XLOOKUP(TRIM($E16),TRIM('Año 2026'!$E$3:$E$66),'Año 2026'!$P$3:$P$66),"")} | AP16: {=IFERROR(_xlfn.XLOOKUP(TRIM($E16),TRIM('Año 2026'!$E$3:$E$66),'Año 2026'!$Q$3:$Q$66),"")} | AQ16: {=IFERROR(_xlfn.XLOOKUP(TRIM($E16),TRIM('Año 2026'!$E$3:$E$66),'Año 2026'!$R$3:$R$66),"")} | AR16: {=IFERROR(_xlfn.XLOOKUP(TRIM($E16),TRIM('Año 2026'!$E$3:$E$66),'Año 2026'!$S$3:$S$66),"")} | AS16: {=IFERROR(_xlfn.XLOOKUP(TRIM($E16),TRIM('Año 2026'!$E$3:$E$66),'Año 2026'!$T$3:$T$66),"")} | AT16: {=IFERROR(_xlfn.XLOOKUP(TRIM($E16),TRIM('Año 2026'!$E$3:$E$66),'Año 2026'!$U$3:$U$66),"")} | AU16: {=IFERROR(_xlfn.XLOOKUP(TRIM($E16),TRIM('Año 2026'!$E$3:$E$66),'Año 2026'!$V$3:$V$66),"")} | AV16: {=IFERROR(_xlfn.XLOOKUP(TRIM($E16),TRIM('Año 2026'!$E$3:$E$66),'Año 2026'!$W$3:$W$66),"")} | AW16: {=IFERROR(_xlfn.XLOOKUP(TRIM($E16),TRIM('Año 2026'!$E$3:$E$66),'Año 2026'!$X$3:$X$66),"")} | AX16: {=IFERROR(_xlfn.XLOOKUP(TRIM($E16),TRIM('Año 2026'!$E$3:$E$66),'Año 2026'!$Y$3:$Y$66),"")} | AY16: {=IFERROR(_xlfn.XLOOKUP(TRIM($E16),TRIM('Año 2026'!$E$3:$E$66),'Año 2026'!$Z$3:$Z$66),"")} | AZ16: {=IFERROR(_xlfn.XLOOKUP(TRIM($E16),TRIM('Año 2026'!$E$3:$E$66),'Año 2026'!$AA$3:$AA$66),"")} | BA16: {=IFERROR(_xlfn.XLOOKUP(TRIM($E16),TRIM('Año 2026'!$E$3:$E$66),'Año 2026'!$AB$3:$AB$66),"")} | BB16: {=IFERROR(_xlfn.XLOOKUP(TRIM($E16),TRIM('Año 2026'!$E$3:$E$66),'Año 2026'!$AC$3:$AC$66),"")} | BC16: {=IFERROR(_xlfn.XLOOKUP(TRIM($E16),TRIM('Año 2026'!$E$3:$E$66),'Año 2026'!$AD$3:$AD$66),"")}
A17: 16 | B17: 2024 | C17: Denuncia | D17: Web | E17: 02878-2024-SUNEDU/02-13 | F17: Archivado | G17: 2024EXT0000049748-SUNEDU | H17: 45 | I17: Privada | J17: SL01 | K17: Junin | L17: Huancayo | M17: Huancayo | N17: Av. Mártires del Periodismo N° 2008-2040-2060-2080, Jr. Ciro Alegria N°215, Calle Las Estrellas N° 105-115, Calle Neptuno N°100-150 y Calle Los Andes N°125 | O17: MLI | P17: III | Q17: 21 | R17: Denuncia que en el campus chorrillos de la universidad no se contaría con los servicios básicos como el agua potable. | S17: BAJA | T17: 1 | U17: Mediante Oficio Digital Nº 01160-2025-R-UPLA, presentó recibos de pagos y numeros de suministros y cuentan con un informe de cierre | V17: 45810 | W17: Cuenta con siete (7) N° Suministros: 1057597,1026467, 1089967, 1057179 entre otros | X17: GIGI NASSI | Y17: Levantamiento Oficio de Cierre por parte de Gigi el 09.02.26 Priorizada para ser cerrada en febrero 2026. | Z17: Sí | AA17: 46073 | AB17: =IF(AA17<TODAY(),"VENCIDO","POR VENCER") -> VENCIDO | AC17: 46080 | AD17: COMPLETADO | AE17: Carta N° 00523-2026-SUNEDU-DS-DIRESESU-UVE del 23 de febrero de 2026 | AF17: {=IFERROR(_xlfn.XLOOKUP(TRIM($E17),TRIM('Año 2026'!$E$3:$E$66),'Año 2026'!$G$3:$G$66),"")} | AG17: {=IFERROR(_xlfn.XLOOKUP(TRIM($E17),TRIM('Año 2026'!$E$3:$E$66),'Año 2026'!$H$3:$H$66),"")} | AH17: {=IFERROR(_xlfn.XLOOKUP(TRIM($E17),TRIM('Año 2026'!$E$3:$E$66),'Año 2026'!$I$3:$I$66),"")} | AI17: {=IFERROR(_xlfn.XLOOKUP(TRIM($E17),TRIM('Año 2026'!$E$3:$E$66),'Año 2026'!$J$3:$J$66),"")} | AJ17: {=IFERROR(_xlfn.XLOOKUP(TRIM($E17),TRIM('Año 2026'!$E$3:$E$66),'Año 2026'!$K$3:$K$66),"")} | AK17: {=IFERROR(_xlfn.XLOOKUP(TRIM($E17),TRIM('Año 2026'!$E$3:$E$66),'Año 2026'!$L$3:$L$66),"")} | AL17: {=IFERROR(_xlfn.XLOOKUP(TRIM($E17),TRIM('Año 2026'!$E$3:$E$66),'Año 2026'!$M$3:$M$66),"")} | AM17: {=IFERROR(_xlfn.XLOOKUP(TRIM($E17),TRIM('Año 2026'!$E$3:$E$66),'Año 2026'!$N$3:$N$66),"")} | AN17: {=IFERROR(_xlfn.XLOOKUP(TRIM($E17),TRIM('Año 2026'!$E$3:$E$66),'Año 2026'!$O$3:$O$66),"")} | AO17: {=IFERROR(_xlfn.XLOOKUP(TRIM($E17),TRIM('Año 2026'!$E$3:$E$66),'Año 2026'!$P$3:$P$66),"")} | AP17: {=IFERROR(_xlfn.XLOOKUP(TRIM($E17),TRIM('Año 2026'!$E$3:$E$66),'Año 2026'!$Q$3:$Q$66),"")} | AQ17: {=IFERROR(_xlfn.XLOOKUP(TRIM($E17),TRIM('Año 2026'!$E$3:$E$66),'Año 2026'!$R$3:$R$66),"")} | AR17: {=IFERROR(_xlfn.XLOOKUP(TRIM($E17),TRIM('Año 2026'!$E$3:$E$66),'Año 2026'!$S$3:$S$66),"")} | AS17: {=IFERROR(_xlfn.XLOOKUP(TRIM($E17),TRIM('Año 2026'!$E$3:$E$66),'Año 2026'!$T$3:$T$66),"")} | AT17: {=IFERROR(_xlfn.XLOOKUP(TRIM($E17),TRIM('Año 2026'!$E$3:$E$66),'Año 2026'!$U$3:$U$66),"")} | AU17: {=IFERROR(_xlfn.XLOOKUP(TRIM($E17),TRIM('Año 2026'!$E$3:$E$66),'Año 2026'!$V$3:$V$66),"")} | AV17: {=IFERROR(_xlfn.XLOOKUP(TRIM($E17),TRIM('Año 2026'!$E$3:$E$66),'Año 2026'!$W$3:$W$66),"")} | AW17: {=IFERROR(_xlfn.XLOOKUP(TRIM($E17),TRIM('Año 2026'!$E$3:$E$66),'Año 2026'!$X$3:$X$66),"")} | AX17: {=IFERROR(_xlfn.XLOOKUP(TRIM($E17),TRIM('Año 2026'!$E$3:$E$66),'Año 2026'!$Y$3:$Y$66),"")} | AY17: {=IFERROR(_xlfn.XLOOKUP(TRIM($E17),TRIM('Año 2026'!$E$3:$E$66),'Año 2026'!$Z$3:$Z$66),"")} | AZ17: {=IFERROR(_xlfn.XLOOKUP(TRIM($E17),TRIM('Año 2026'!$E$3:$E$66),'Año 2026'!$AA$3:$AA$66),"")} | BA17: {=IFERROR(_xlfn.XLOOKUP(TRIM($E17),TRIM('Año 2026'!$E$3:$E$66),'Año 2026'!$AB$3:$AB$66),"")} | BB17: {=IFERROR(_xlfn.XLOOKUP(TRIM($E17),TRIM('Año 2026'!$E$3:$E$66),'Año 2026'!$AC$3:$AC$66),"")} | BC17: {=IFERROR(_xlfn.XLOOKUP(TRIM($E17),TRIM('Año 2026'!$E$3:$E$66),'Año 2026'!$AD$3:$AD$66),"")}
A18: 17 | B18: 2024 | C18: Denuncia | D18: Web | E18: 02299-2024-SUNEDU/02-13 | F18: En trámite | G18: 2024EXT0000035994-SUNEDU | H18: 5 | I18: Privada | J18: Nuevo local, distrito de Miraflores | K18: Lima | L18: Lima | M18: Miraflores | N18: Calle Dos de Mayo No. 152 | O18: MLI | P18: I, III | Q18: 1, 17 | R18: Hace de conocimiento presuntas irregularidades en los indicadores de las condiciones básicas de calidad: (I) presunta ilegalidad sobre la adecuación de los estatutos a las disposiciones establecidas a la ley universitaria. (II) la universidad no habría registrado un inmueble adquirido en el 2010 por las autoridades universitarias, ubicado en la Calle Dos de Mayo No. 152. Miraflores | S18: BAJA | T18: 2 | U18: Formato único de denuncia | V18: 45544 | W18: No ha sido atendida | Y18: Pendiente visita del 25.02.26 por Carla La Torre + Susana Varas CBC I y CBC III Susana Varas 02.03.26 al 20.03.26 Priorizada para ser cerrada en marzo 2026. | Z18: Sí | AB18: Sin fecha | AD18: EN PROCESO | AE18: Carta y/o Oficio | AF18: {=IFERROR(_xlfn.XLOOKUP(TRIM($E18),TRIM('Año 2026'!$E$3:$E$66),'Año 2026'!$G$3:$G$66),"")} -> OFICIO Nº 00931-2026-SUNEDU-DS-DIRESESU-UVE | AG18: {=IFERROR(_xlfn.XLOOKUP(TRIM($E18),TRIM('Año 2026'!$E$3:$E$66),'Año 2026'!$H$3:$H$66),"")} -> 0 | AH18: {=IFERROR(_xlfn.XLOOKUP(TRIM($E18),TRIM('Año 2026'!$E$3:$E$66),'Año 2026'!$I$3:$I$66),"")} -> 0 | AI18: {=IFERROR(_xlfn.XLOOKUP(TRIM($E18),TRIM('Año 2026'!$E$3:$E$66),'Año 2026'!$J$3:$J$66),"")} -> 0 | AJ18: {=IFERROR(_xlfn.XLOOKUP(TRIM($E18),TRIM('Año 2026'!$E$3:$E$66),'Año 2026'!$K$3:$K$66),"")} -> 0 | AK18: {=IFERROR(_xlfn.XLOOKUP(TRIM($E18),TRIM('Año 2026'!$E$3:$E$66),'Año 2026'!$L$3:$L$66),"")} -> 0 | AL18: {=IFERROR(_xlfn.XLOOKUP(TRIM($E18),TRIM('Año 2026'!$E$3:$E$66),'Año 2026'!$M$3:$M$66),"")} -> 0 | AM18: {=IFERROR(_xlfn.XLOOKUP(TRIM($E18),TRIM('Año 2026'!$E$3:$E$66),'Año 2026'!$N$3:$N$66),"")} -> 0 | AN18: {=IFERROR(_xlfn.XLOOKUP(TRIM($E18),TRIM('Año 2026'!$E$3:$E$66),'Año 2026'!$O$3:$O$66),"")} -> 0 | AO18: {=IFERROR(_xlfn.XLOOKUP(TRIM($E18),TRIM('Año 2026'!$E$3:$E$66),'Año 2026'!$P$3:$P$66),"")} -> 0 | AP18: {=IFERROR(_xlfn.XLOOKUP(TRIM($E18),TRIM('Año 2026'!$E$3:$E$66),'Año 2026'!$Q$3:$Q$66),"")} -> 0 | AQ18: {=IFERROR(_xlfn.XLOOKUP(TRIM($E18),TRIM('Año 2026'!$E$3:$E$66),'Año 2026'!$R$3:$R$66),"")} -> 0 | AR18: {=IFERROR(_xlfn.XLOOKUP(TRIM($E18),TRIM('Año 2026'!$E$3:$E$66),'Año 2026'!$S$3:$S$66),"")} -> 0 | AS18: {=IFERROR(_xlfn.XLOOKUP(TRIM($E18),TRIM('Año 2026'!$E$3:$E$66),'Año 2026'!$T$3:$T$66),"")} -> 0 | AT18: {=IFERROR(_xlfn.XLOOKUP(TRIM($E18),TRIM('Año 2026'!$E$3:$E$66),'Año 2026'!$U$3:$U$66),"")} -> 0 | AU18: {=IFERROR(_xlfn.XLOOKUP(TRIM($E18),TRIM('Año 2026'!$E$3:$E$66),'Año 2026'!$V$3:$V$66),"")} -> 0 | AV18: {=IFERROR(_xlfn.XLOOKUP(TRIM($E18),TRIM('Año 2026'!$E$3:$E$66),'Año 2026'!$W$3:$W$66),"")} -> 0 | AW18: {=IFERROR(_xlfn.XLOOKUP(TRIM($E18),TRIM('Año 2026'!$E$3:$E$66),'Año 2026'!$X$3:$X$66),"")} -> 0 | AX18: {=IFERROR(_xlfn.XLOOKUP(TRIM($E18),TRIM('Año 2026'!$E$3:$E$66),'Año 2026'!$Y$3:$Y$66),"")} -> 0 | AY18: {=IFERROR(_xlfn.XLOOKUP(TRIM($E18),TRIM('Año 2026'!$E$3:$E$66),'Año 2026'!$Z$3:$Z$66),"")} -> 0 | AZ18: {=IFERROR(_xlfn.XLOOKUP(TRIM($E18),TRIM('Año 2026'!$E$3:$E$66),'Año 2026'!$AA$3:$AA$66),"")} -> 0 | BA18: {=IFERROR(_xlfn.XLOOKUP(TRIM($E18),TRIM('Año 2026'!$E$3:$E$66),'Año 2026'!$AB$3:$AB$66),"")} -> 0 | BB18: {=IFERROR(_xlfn.XLOOKUP(TRIM($E18),TRIM('Año 2026'!$E$3:$E$66),'Año 2026'!$AC$3:$AC$66),"")} -> 0 | BC18: {=IFERROR(_xlfn.XLOOKUP(TRIM($E18),TRIM('Año 2026'!$E$3:$E$66),'Año 2026'!$AD$3:$AD$66),"")} -> 0
A19: 18 | B19: 2024 | C19: Accion Directa | D19: Correo electrónico | E19: AD-041-2024 | F19: Atendido | H19: 49 | I19: Pública | J19: SL01 | K19: Cusco | L19: Cusco | M19: Cusco | N19: Av. de la Cultura N° 733 | O19: MLI | P19: VI | Q19: 44 | R19: Las acciones de indagación se iniciaron debido a que se advirtió (en medios públicos) irregularidades en la reserva de cupos en el comedor universitario del local SL01 de la Universidad Nacional de San Antonio Abad del Cusco. Este hecho estaría vinculado con el mantenimiento de la CBC VI del Modelo de Licenciamiento. | S19: MEDIA | T19: 1 | U19: La Universidad remitió información en dic2025 ante el pedido del oficio de requerimiento de información de nov2025. | V19: 45993 | W19: En este caso no se realizó visita de inspección. El tema a tratar es CBC VI respecto el servicio de comedor, se podría culminar con un Oficio e Informe de Cierre, debido a que se cuenta con información remitida ante los pedidos realizados. | X19: ERNESTO ALZA CLAUDIA MECHAN | Y19: Pendiente revisión porIsabel Astete Desde el 09.02.26 al 20.02.26 Priorizada para ser cerrada en marzo 2026. Ernetso | Z19: Sí | AA19: 46101 | AB19: =IF(AA19<TODAY(),"VENCIDO","POR VENCER") -> VENCIDO | AC19: 46108 | AD19: COMPLETADO | AE19: Atendido con el Informe N° 00292-2026-SUNEDU-DS-DIRESESU-UVE, notificado mediante el Oficio N° 01319-2026-SUNEDU-DS-DIRESESU-UVE del 1 de abril de 2026. | AF19: {=IFERROR(_xlfn.XLOOKUP(TRIM($E19),TRIM('Año 2026'!$E$3:$E$66),'Año 2026'!$G$3:$G$66),"")} | AG19: {=IFERROR(_xlfn.XLOOKUP(TRIM($E19),TRIM('Año 2026'!$E$3:$E$66),'Año 2026'!$H$3:$H$66),"")} | AH19: {=IFERROR(_xlfn.XLOOKUP(TRIM($E19),TRIM('Año 2026'!$E$3:$E$66),'Año 2026'!$I$3:$I$66),"")} | AI19: {=IFERROR(_xlfn.XLOOKUP(TRIM($E19),TRIM('Año 2026'!$E$3:$E$66),'Año 2026'!$J$3:$J$66),"")} | AJ19: {=IFERROR(_xlfn.XLOOKUP(TRIM($E19),TRIM('Año 2026'!$E$3:$E$66),'Año 2026'!$K$3:$K$66),"")} | AK19: {=IFERROR(_xlfn.XLOOKUP(TRIM($E19),TRIM('Año 2026'!$E$3:$E$66),'Año 2026'!$L$3:$L$66),"")} | AL19: {=IFERROR(_xlfn.XLOOKUP(TRIM($E19),TRIM('Año 2026'!$E$3:$E$66),'Año 2026'!$M$3:$M$66),"")} | AM19: {=IFERROR(_xlfn.XLOOKUP(TRIM($E19),TRIM('Año 2026'!$E$3:$E$66),'Año 2026'!$N$3:$N$66),"")} | AN19: {=IFERROR(_xlfn.XLOOKUP(TRIM($E19),TRIM('Año 2026'!$E$3:$E$66),'Año 2026'!$O$3:$O$66),"")} | AO19: {=IFERROR(_xlfn.XLOOKUP(TRIM($E19),TRIM('Año 2026'!$E$3:$E$66),'Año 2026'!$P$3:$P$66),"")} | AP19: {=IFERROR(_xlfn.XLOOKUP(TRIM($E19),TRIM('Año 2026'!$E$3:$E$66),'Año 2026'!$Q$3:$Q$66),"")} | AQ19: {=IFERROR(_xlfn.XLOOKUP(TRIM($E19),TRIM('Año 2026'!$E$3:$E$66),'Año 2026'!$R$3:$R$66),"")} | AR19: {=IFERROR(_xlfn.XLOOKUP(TRIM($E19),TRIM('Año 2026'!$E$3:$E$66),'Año 2026'!$S$3:$S$66),"")} | AS19: {=IFERROR(_xlfn.XLOOKUP(TRIM($E19),TRIM('Año 2026'!$E$3:$E$66),'Año 2026'!$T$3:$T$66),"")} | AT19: {=IFERROR(_xlfn.XLOOKUP(TRIM($E19),TRIM('Año 2026'!$E$3:$E$66),'Año 2026'!$U$3:$U$66),"")} | AU19: {=IFERROR(_xlfn.XLOOKUP(TRIM($E19),TRIM('Año 2026'!$E$3:$E$66),'Año 2026'!$V$3:$V$66),"")} | AV19: {=IFERROR(_xlfn.XLOOKUP(TRIM($E19),TRIM('Año 2026'!$E$3:$E$66),'Año 2026'!$W$3:$W$66),"")} | AW19: {=IFERROR(_xlfn.XLOOKUP(TRIM($E19),TRIM('Año 2026'!$E$3:$E$66),'Año 2026'!$X$3:$X$66),"")} | AX19: {=IFERROR(_xlfn.XLOOKUP(TRIM($E19),TRIM('Año 2026'!$E$3:$E$66),'Año 2026'!$Y$3:$Y$66),"")} | AY19: {=IFERROR(_xlfn.XLOOKUP(TRIM($E19),TRIM('Año 2026'!$E$3:$E$66),'Año 2026'!$Z$3:$Z$66),"")} | AZ19: {=IFERROR(_xlfn.XLOOKUP(TRIM($E19),TRIM('Año 2026'!$E$3:$E$66),'Año 2026'!$AA$3:$AA$66),"")} | BA19: {=IFERROR(_xlfn.XLOOKUP(TRIM($E19),TRIM('Año 2026'!$E$3:$E$66),'Año 2026'!$AB$3:$AB$66),"")} | BB19: {=IFERROR(_xlfn.XLOOKUP(TRIM($E19),TRIM('Año 2026'!$E$3:$E$66),'Año 2026'!$AC$3:$AC$66),"")} | BC19: {=IFERROR(_xlfn.XLOOKUP(TRIM($E19),TRIM('Año 2026'!$E$3:$E$66),'Año 2026'!$AD$3:$AD$66),"")}
A20: 19 | B20: 2024 | C20: Denuncia | D20: Web | E20: 02628-2024-SUNEDU/02-13 | F20: Archivado | G20: 2024EXT0000043718-SUNEDU | H20: 35 | I20: Privada | K20: Lima | L20: Lima | M20: Santa Anita | N20: Av. Alameda del Corregidor 1517-1531, Urb. Sirius – III Etapa – La Molina | O20: MLI | P20: VI | Q20: 44 | R20: Hace de conocimiento que se habría clausurado el comedor de la de la Facultad de Medicina de la universidad tras una fiscalización realizada por la municipalidad a la concesionaria que operaba en dicho espacio, lo cual estaría afectando a los alumnos ya que no tendrían un lugar donde almorzar. | S20: BAJA | U20: Formato único de denuncia | V20: 45588 | W20: En la carpeta en Z no hay informacion se requiere solicitar informacion. Se cuenta con informacion de la VI realizada para el PILOTO del PLAN 2025. Donde verificaron que si funcionaba y habia dejado de atender un tiempo por mantenimiento de las instalacion. (Pablo tiene fotos) | X20: NÉSTOR TICSE | Y20: Falta IR u Oficio para cierre Priorizada para ser cerrada en febrero 2026. Néstor | Z20: Sí | AA20: 46132 | AB20: =IF(AA20<TODAY(),"VENCIDO","POR VENCER") -> VENCIDO | AC20: 46139 | AD20: COMPLETADO | AE20: Carta N° 01451-2026-SUNEDU-DS-DIRESESU-UVE y Oficio Nº 01850-2026-SUNEDU-DS-DIRESESU-UVE | AF20: {=IFERROR(_xlfn.XLOOKUP(TRIM($E20),TRIM('Año 2026'!$E$3:$E$66),'Año 2026'!$G$3:$G$66),"")} | AG20: {=IFERROR(_xlfn.XLOOKUP(TRIM($E20),TRIM('Año 2026'!$E$3:$E$66),'Año 2026'!$H$3:$H$66),"")} | AH20: {=IFERROR(_xlfn.XLOOKUP(TRIM($E20),TRIM('Año 2026'!$E$3:$E$66),'Año 2026'!$I$3:$I$66),"")} | AI20: {=IFERROR(_xlfn.XLOOKUP(TRIM($E20),TRIM('Año 2026'!$E$3:$E$66),'Año 2026'!$J$3:$J$66),"")} | AJ20: {=IFERROR(_xlfn.XLOOKUP(TRIM($E20),TRIM('Año 2026'!$E$3:$E$66),'Año 2026'!$K$3:$K$66),"")} | AK20: {=IFERROR(_xlfn.XLOOKUP(TRIM($E20),TRIM('Año 2026'!$E$3:$E$66),'Año 2026'!$L$3:$L$66),"")} | AL20: {=IFERROR(_xlfn.XLOOKUP(TRIM($E20),TRIM('Año 2026'!$E$3:$E$66),'Año 2026'!$M$3:$M$66),"")} | AM20: {=IFERROR(_xlfn.XLOOKUP(TRIM($E20),TRIM('Año 2026'!$E$3:$E$66),'Año 2026'!$N$3:$N$66),"")} | AN20: {=IFERROR(_xlfn.XLOOKUP(TRIM($E20),TRIM('Año 2026'!$E$3:$E$66),'Año 2026'!$O$3:$O$66),"")} | AO20: {=IFERROR(_xlfn.XLOOKUP(TRIM($E20),TRIM('Año 2026'!$E$3:$E$66),'Año 2026'!$P$3:$P$66),"")} | AP20: {=IFERROR(_xlfn.XLOOKUP(TRIM($E20),TRIM('Año 2026'!$E$3:$E$66),'Año 2026'!$Q$3:$Q$66),"")} | AQ20: {=IFERROR(_xlfn.XLOOKUP(TRIM($E20),TRIM('Año 2026'!$E$3:$E$66),'Año 2026'!$R$3:$R$66),"")} | AR20: {=IFERROR(_xlfn.XLOOKUP(TRIM($E20),TRIM('Año 2026'!$E$3:$E$66),'Año 2026'!$S$3:$S$66),"")} | AS20: {=IFERROR(_xlfn.XLOOKUP(TRIM($E20),TRIM('Año 2026'!$E$3:$E$66),'Año 2026'!$T$3:$T$66),"")} | AT20: {=IFERROR(_xlfn.XLOOKUP(TRIM($E20),TRIM('Año 2026'!$E$3:$E$66),'Año 2026'!$U$3:$U$66),"")} | AU20: {=IFERROR(_xlfn.XLOOKUP(TRIM($E20),TRIM('Año 2026'!$E$3:$E$66),'Año 2026'!$V$3:$V$66),"")} | AV20: {=IFERROR(_xlfn.XLOOKUP(TRIM($E20),TRIM('Año 2026'!$E$3:$E$66),'Año 2026'!$W$3:$W$66),"")} | AW20: {=IFERROR(_xlfn.XLOOKUP(TRIM($E20),TRIM('Año 2026'!$E$3:$E$66),'Año 2026'!$X$3:$X$66),"")} | AX20: {=IFERROR(_xlfn.XLOOKUP(TRIM($E20),TRIM('Año 2026'!$E$3:$E$66),'Año 2026'!$Y$3:$Y$66),"")} | AY20: {=IFERROR(_xlfn.XLOOKUP(TRIM($E20),TRIM('Año 2026'!$E$3:$E$66),'Año 2026'!$Z$3:$Z$66),"")} | AZ20: {=IFERROR(_xlfn.XLOOKUP(TRIM($E20),TRIM('Año 2026'!$E$3:$E$66),'Año 2026'!$AA$3:$AA$66),"")} | BA20: {=IFERROR(_xlfn.XLOOKUP(TRIM($E20),TRIM('Año 2026'!$E$3:$E$66),'Año 2026'!$AB$3:$AB$66),"")} | BB20: {=IFERROR(_xlfn.XLOOKUP(TRIM($E20),TRIM('Año 2026'!$E$3:$E$66),'Año 2026'!$AC$3:$AC$66),"")} | BC20: {=IFERROR(_xlfn.XLOOKUP(TRIM($E20),TRIM('Año 2026'!$E$3:$E$66),'Año 2026'!$AD$3:$AD$66),"")}
A21: 20 | B21: 2025 | C21: Denuncia | D21: MP | E21: 02373-2025-SUNEDU/02-13 | F21: Archivado | G21: 2025EXT0000044435-SUNEDU, 2025EXT0000048042-SUNEDU | H21: 12 | I21: Privada | J21: SL02 | K21: Arequipa | L21: Arequipa | M21: Arequipa | N21: Calle Samuel Velarde N° 320 – Umacollo | O21: MLI | P21: III | Q21: 17, 24, 27, 28, 29, 30 | R21: Denuncia que la universidad habría cometido un incumplimiento contractual respecto a una deuda que la universidad mantendría con la empresa "Go Media Films E.I.R.L." quien implemento en el edificio "Torre Santa María" infraestructura tecnológica, domótica, mobiliario y sistemas audiovisuales. | S21: MEDIA | U21: Oficio Nº 3012-AL-2025 de respuesta a requerimiento de información | V21: 45939 | W21: ARCHIVADO. Pendiente actualizar la carpeta del Z, incluyendo el oficio que archiva la denuncia. | Y21: Falta atender | AB21: SIN FECHA | AD21: EN PROCESO | AE21: Carta y/o Oficio | AF21: {=IFERROR(_xlfn.XLOOKUP(TRIM($E21),TRIM('Año 2026'!$E$3:$E$66),'Año 2026'!$G$3:$G$66),"")} | AG21: {=IFERROR(_xlfn.XLOOKUP(TRIM($E21),TRIM('Año 2026'!$E$3:$E$66),'Año 2026'!$H$3:$H$66),"")} | AH21: {=IFERROR(_xlfn.XLOOKUP(TRIM($E21),TRIM('Año 2026'!$E$3:$E$66),'Año 2026'!$I$3:$I$66),"")} | AI21: {=IFERROR(_xlfn.XLOOKUP(TRIM($E21),TRIM('Año 2026'!$E$3:$E$66),'Año 2026'!$J$3:$J$66),"")} | AJ21: {=IFERROR(_xlfn.XLOOKUP(TRIM($E21),TRIM('Año 2026'!$E$3:$E$66),'Año 2026'!$K$3:$K$66),"")} | AK21: {=IFERROR(_xlfn.XLOOKUP(TRIM($E21),TRIM('Año 2026'!$E$3:$E$66),'Año 2026'!$L$3:$L$66),"")} | AL21: {=IFERROR(_xlfn.XLOOKUP(TRIM($E21),TRIM('Año 2026'!$E$3:$E$66),'Año 2026'!$M$3:$M$66),"")} | AM21: {=IFERROR(_xlfn.XLOOKUP(TRIM($E21),TRIM('Año 2026'!$E$3:$E$66),'Año 2026'!$N$3:$N$66),"")} | AN21: {=IFERROR(_xlfn.XLOOKUP(TRIM($E21),TRIM('Año 2026'!$E$3:$E$66),'Año 2026'!$O$3:$O$66),"")} | AO21: {=IFERROR(_xlfn.XLOOKUP(TRIM($E21),TRIM('Año 2026'!$E$3:$E$66),'Año 2026'!$P$3:$P$66),"")} | AP21: {=IFERROR(_xlfn.XLOOKUP(TRIM($E21),TRIM('Año 2026'!$E$3:$E$66),'Año 2026'!$Q$3:$Q$66),"")} | AQ21: {=IFERROR(_xlfn.XLOOKUP(TRIM($E21),TRIM('Año 2026'!$E$3:$E$66),'Año 2026'!$R$3:$R$66),"")} | AR21: {=IFERROR(_xlfn.XLOOKUP(TRIM($E21),TRIM('Año 2026'!$E$3:$E$66),'Año 2026'!$S$3:$S$66),"")} | AS21: {=IFERROR(_xlfn.XLOOKUP(TRIM($E21),TRIM('Año 2026'!$E$3:$E$66),'Año 2026'!$T$3:$T$66),"")} | AT21: {=IFERROR(_xlfn.XLOOKUP(TRIM($E21),TRIM('Año 2026'!$E$3:$E$66),'Año 2026'!$U$3:$U$66),"")} | AU21: {=IFERROR(_xlfn.XLOOKUP(TRIM($E21),TRIM('Año 2026'!$E$3:$E$66),'Año 2026'!$V$3:$V$66),"")} | AV21: {=IFERROR(_xlfn.XLOOKUP(TRIM($E21),TRIM('Año 2026'!$E$3:$E$66),'Año 2026'!$W$3:$W$66),"")} | AW21: {=IFERROR(_xlfn.XLOOKUP(TRIM($E21),TRIM('Año 2026'!$E$3:$E$66),'Año 2026'!$X$3:$X$66),"")} | AX21: {=IFERROR(_xlfn.XLOOKUP(TRIM($E21),TRIM('Año 2026'!$E$3:$E$66),'Año 2026'!$Y$3:$Y$66),"")} | AY21: {=IFERROR(_xlfn.XLOOKUP(TRIM($E21),TRIM('Año 2026'!$E$3:$E$66),'Año 2026'!$Z$3:$Z$66),"")} | AZ21: {=IFERROR(_xlfn.XLOOKUP(TRIM($E21),TRIM('Año 2026'!$E$3:$E$66),'Año 2026'!$AA$3:$AA$66),"")} | BA21: {=IFERROR(_xlfn.XLOOKUP(TRIM($E21),TRIM('Año 2026'!$E$3:$E$66),'Año 2026'!$AB$3:$AB$66),"")} | BB21: {=IFERROR(_xlfn.XLOOKUP(TRIM($E21),TRIM('Año 2026'!$E$3:$E$66),'Año 2026'!$AC$3:$AC$66),"")} | BC21: {=IFERROR(_xlfn.XLOOKUP(TRIM($E21),TRIM('Año 2026'!$E$3:$E$66),'Año 2026'!$AD$3:$AD$66),"")}
A22: 21 | B22: 2025 | C22: SNP | D22: Web | E22: 00506-2025-SUNEDU/02-13 | F22: Atendido | G22: 2025EXT0000015628-SUNEDU | H22: 11 | I22: Privada | J22: F03L01 | K22: Madre de Dios | L22: Tambopata | M22: Tambopata | N22: Av. Dos de Mayo y Av. Ernesto Rivera Mza. 1-H Lote 9-10, | O22: MLI | P22: III | Q22: 19, 20, 27, 28, 30 | R22: Denuncia referida a la presunta falta de implementación del programa de Enfermería de la Universidad Andina del Cusco en el local F03L01, pese a encontrarse en funcionamiento desde aproximadamente dos años, consistente en la carencia de implementos básicos para las prácticas académicas (como maniquíes para procedimientos), la existencia de un laboratorio de Enfermería de dimensiones reducidas, aulas con ventilación insuficiente y deficiencias en los servicios higiénicos, tales como baños en mal estado, puertas que no cierran y piletas averiadas. | S22: ALTA | T22: 1 | U22: La Universidad remitió información complementaria mediante Oficio N° 0455-2025-R-UAC del 20.11.25 | V22: 45981 | W22: El informe ya se encontraba culminado y parcialmente revisado; estaría pendiente complementar con la última información remitida por la Universidad. | X22: GIGI NASSI | Y22: CBC III Gigi Nassi 09.02.26 al 16.02.26 Priorizada para ser cerrada en marzo 2026. Rev RL | Z22: Sí | AA22: 46073 | AB22: =IF(AA22<TODAY(),"VENCIDO","POR VENCER") -> VENCIDO | AC22: 46080 | AD22: COMPLETADO | AE22: Informe de Resultados N° 00035-2026-SUNEDU-DS-DIRESESU-UVE del 28 de febrero de 2026 | AF22: {=IFERROR(_xlfn.XLOOKUP(TRIM($E22),TRIM('Año 2026'!$E$3:$E$66),'Año 2026'!$G$3:$G$66),"")} | AG22: {=IFERROR(_xlfn.XLOOKUP(TRIM($E22),TRIM('Año 2026'!$E$3:$E$66),'Año 2026'!$H$3:$H$66),"")} | AH22: {=IFERROR(_xlfn.XLOOKUP(TRIM($E22),TRIM('Año 2026'!$E$3:$E$66),'Año 2026'!$I$3:$I$66),"")} | AI22: {=IFERROR(_xlfn.XLOOKUP(TRIM($E22),TRIM('Año 2026'!$E$3:$E$66),'Año 2026'!$J$3:$J$66),"")} | AJ22: {=IFERROR(_xlfn.XLOOKUP(TRIM($E22),TRIM('Año 2026'!$E$3:$E$66),'Año 2026'!$K$3:$K$66),"")} | AK22: {=IFERROR(_xlfn.XLOOKUP(TRIM($E22),TRIM('Año 2026'!$E$3:$E$66),'Año 2026'!$L$3:$L$66),"")} | AL22: {=IFERROR(_xlfn.XLOOKUP(TRIM($E22),TRIM('Año 2026'!$E$3:$E$66),'Año 2026'!$M$3:$M$66),"")} | AM22: {=IFERROR(_xlfn.XLOOKUP(TRIM($E22),TRIM('Año 2026'!$E$3:$E$66),'Año 2026'!$N$3:$N$66),"")} | AN22: {=IFERROR(_xlfn.XLOOKUP(TRIM($E22),TRIM('Año 2026'!$E$3:$E$66),'Año 2026'!$O$3:$O$66),"")} | AO22: {=IFERROR(_xlfn.XLOOKUP(TRIM($E22),TRIM('Año 2026'!$E$3:$E$66),'Año 2026'!$P$3:$P$66),"")} | AP22: {=IFERROR(_xlfn.XLOOKUP(TRIM($E22),TRIM('Año 2026'!$E$3:$E$66),'Año 2026'!$Q$3:$Q$66),"")} | AQ22: {=IFERROR(_xlfn.XLOOKUP(TRIM($E22),TRIM('Año 2026'!$E$3:$E$66),'Año 2026'!$R$3:$R$66),"")} | AR22: {=IFERROR(_xlfn.XLOOKUP(TRIM($E22),TRIM('Año 2026'!$E$3:$E$66),'Año 2026'!$S$3:$S$66),"")} | AS22: {=IFERROR(_xlfn.XLOOKUP(TRIM($E22),TRIM('Año 2026'!$E$3:$E$66),'Año 2026'!$T$3:$T$66),"")} | AT22: {=IFERROR(_xlfn.XLOOKUP(TRIM($E22),TRIM('Año 2026'!$E$3:$E$66),'Año 2026'!$U$3:$U$66),"")} | AU22: {=IFERROR(_xlfn.XLOOKUP(TRIM($E22),TRIM('Año 2026'!$E$3:$E$66),'Año 2026'!$V$3:$V$66),"")} | AV22: {=IFERROR(_xlfn.XLOOKUP(TRIM($E22),TRIM('Año 2026'!$E$3:$E$66),'Año 2026'!$W$3:$W$66),"")} | AW22: {=IFERROR(_xlfn.XLOOKUP(TRIM($E22),TRIM('Año 2026'!$E$3:$E$66),'Año 2026'!$X$3:$X$66),"")} | AX22: {=IFERROR(_xlfn.XLOOKUP(TRIM($E22),TRIM('Año 2026'!$E$3:$E$66),'Año 2026'!$Y$3:$Y$66),"")} | AY22: {=IFERROR(_xlfn.XLOOKUP(TRIM($E22),TRIM('Año 2026'!$E$3:$E$66),'Año 2026'!$Z$3:$Z$66),"")} | AZ22: {=IFERROR(_xlfn.XLOOKUP(TRIM($E22),TRIM('Año 2026'!$E$3:$E$66),'Año 2026'!$AA$3:$AA$66),"")} | BA22: {=IFERROR(_xlfn.XLOOKUP(TRIM($E22),TRIM('Año 2026'!$E$3:$E$66),'Año 2026'!$AB$3:$AB$66),"")} | BB22: {=IFERROR(_xlfn.XLOOKUP(TRIM($E22),TRIM('Año 2026'!$E$3:$E$66),'Año 2026'!$AC$3:$AC$66),"")} | BC22: {=IFERROR(_xlfn.XLOOKUP(TRIM($E22),TRIM('Año 2026'!$E$3:$E$66),'Año 2026'!$AD$3:$AD$66),"")}
A23: 22 | B23: 2025 | C23: Denuncia | D23: Web | E23: 02562-2025-SUNEDU/02-13 | F23: Archivado | G23: 2025EXT0000048337-SUNEDU | H23: 141 | I23: Privada | J23: SL01 | K23: Lima | L23: Lima | M23: San Juan de Lurigancho | N23: Avenida Canto Bello N° 431, Urbanización Canto Bello | O23: MLI | P23: III | Q23: 19, 27 | R23: Denuncia que la universidad no contaría con ambientes adecuados para brindar algunas carreras profesionales, ya que la práctica es virtual. Agrega que cuando el estudiante va a reclamar sobre su derecho a una buena educación, ellos se excusan con que las instalaciones están sobre pobladas. | S23: ALTA | U23: Carta N° 03562-2025-SUNEDU-DS-DIRESESU-UVE, mediante el cual se solicita información para la subsanación a la denuncia presentada contra la Universidad. | V23: 45968 | W23: Presentan un audio en el que indican que, en su SLI, las aulas eran amplias; mientras que, ahora la Universidad las redujo en tamaño. Podrían presentar riesgos de seguridad por atrapamiento y caídas en caso de evacuación. También podría presentar insuficientes ambientes (aulas, laboratorios y/o talleres) para la oferta de los programas autorizados. | Y23: Se reemplazó por UNAB | AA23: 46073 | AB23: =IF(AA23<TODAY(),"VENCIDO","POR VENCER") -> VENCIDO | AC23: 46080 | AD23: COMPLETADO | AE23: Carta N° 00626-2026-SUNEDU-DS-DIRESESU-UVE del 27 de febrero de 2026 | AF23: {=IFERROR(_xlfn.XLOOKUP(TRIM($E23),TRIM('Año 2026'!$E$3:$E$66),'Año 2026'!$G$3:$G$66),"")} | AG23: {=IFERROR(_xlfn.XLOOKUP(TRIM($E23),TRIM('Año 2026'!$E$3:$E$66),'Año 2026'!$H$3:$H$66),"")} | AH23: {=IFERROR(_xlfn.XLOOKUP(TRIM($E23),TRIM('Año 2026'!$E$3:$E$66),'Año 2026'!$I$3:$I$66),"")} | AI23: {=IFERROR(_xlfn.XLOOKUP(TRIM($E23),TRIM('Año 2026'!$E$3:$E$66),'Año 2026'!$J$3:$J$66),"")} | AJ23: {=IFERROR(_xlfn.XLOOKUP(TRIM($E23),TRIM('Año 2026'!$E$3:$E$66),'Año 2026'!$K$3:$K$66),"")} | AK23: {=IFERROR(_xlfn.XLOOKUP(TRIM($E23),TRIM('Año 2026'!$E$3:$E$66),'Año 2026'!$L$3:$L$66),"")} | AL23: {=IFERROR(_xlfn.XLOOKUP(TRIM($E23),TRIM('Año 2026'!$E$3:$E$66),'Año 2026'!$M$3:$M$66),"")} | AM23: {=IFERROR(_xlfn.XLOOKUP(TRIM($E23),TRIM('Año 2026'!$E$3:$E$66),'Año 2026'!$N$3:$N$66),"")} | AN23: {=IFERROR(_xlfn.XLOOKUP(TRIM($E23),TRIM('Año 2026'!$E$3:$E$66),'Año 2026'!$O$3:$O$66),"")} | AO23: {=IFERROR(_xlfn.XLOOKUP(TRIM($E23),TRIM('Año 2026'!$E$3:$E$66),'Año 2026'!$P$3:$P$66),"")} | AP23: {=IFERROR(_xlfn.XLOOKUP(TRIM($E23),TRIM('Año 2026'!$E$3:$E$66),'Año 2026'!$Q$3:$Q$66),"")} | AQ23: {=IFERROR(_xlfn.XLOOKUP(TRIM($E23),TRIM('Año 2026'!$E$3:$E$66),'Año 2026'!$R$3:$R$66),"")} | AR23: {=IFERROR(_xlfn.XLOOKUP(TRIM($E23),TRIM('Año 2026'!$E$3:$E$66),'Año 2026'!$S$3:$S$66),"")} | AS23: {=IFERROR(_xlfn.XLOOKUP(TRIM($E23),TRIM('Año 2026'!$E$3:$E$66),'Año 2026'!$T$3:$T$66),"")} | AT23: {=IFERROR(_xlfn.XLOOKUP(TRIM($E23),TRIM('Año 2026'!$E$3:$E$66),'Año 2026'!$U$3:$U$66),"")} | AU23: {=IFERROR(_xlfn.XLOOKUP(TRIM($E23),TRIM('Año 2026'!$E$3:$E$66),'Año 2026'!$V$3:$V$66),"")} | AV23: {=IFERROR(_xlfn.XLOOKUP(TRIM($E23),TRIM('Año 2026'!$E$3:$E$66),'Año 2026'!$W$3:$W$66),"")} | AW23: {=IFERROR(_xlfn.XLOOKUP(TRIM($E23),TRIM('Año 2026'!$E$3:$E$66),'Año 2026'!$X$3:$X$66),"")} | AX23: {=IFERROR(_xlfn.XLOOKUP(TRIM($E23),TRIM('Año 2026'!$E$3:$E$66),'Año 2026'!$Y$3:$Y$66),"")} | AY23: {=IFERROR(_xlfn.XLOOKUP(TRIM($E23),TRIM('Año 2026'!$E$3:$E$66),'Año 2026'!$Z$3:$Z$66),"")} | AZ23: {=IFERROR(_xlfn.XLOOKUP(TRIM($E23),TRIM('Año 2026'!$E$3:$E$66),'Año 2026'!$AA$3:$AA$66),"")} | BA23: {=IFERROR(_xlfn.XLOOKUP(TRIM($E23),TRIM('Año 2026'!$E$3:$E$66),'Año 2026'!$AB$3:$AB$66),"")} | BB23: {=IFERROR(_xlfn.XLOOKUP(TRIM($E23),TRIM('Año 2026'!$E$3:$E$66),'Año 2026'!$AC$3:$AC$66),"")} | BC23: {=IFERROR(_xlfn.XLOOKUP(TRIM($E23),TRIM('Año 2026'!$E$3:$E$66),'Año 2026'!$AD$3:$AD$66),"")}
A24: 23 | B24: 2025 | C24: Accion Directa | D24: Correo electrónico | E24: AD-009-2025 | F24: Atendido | H24: 13 | I24: Privada | J24: F05L01 | K24: Lima | L24: Lima | M24: Los Olivos | N24: Av. Alfredo Mendiola N° 6232, Urbanización lotización industrial Molitalia | O24: MLI | P24: VI | Q24: 45 | R24: Sobre el fallecimiento de una estudiante en el local de Los Olivos (F05L01) de la Universidad César Vallejo S.A.C. Este hecho estaría vinculado con el mantenimiento de la CBC VI, indicador 48 del Modelo de Licenciamiento. | S24: BAJA | T24: 1 | U24: Visita de inspección realizada en jun2025. Al respecto la Universidad presentó la información solicitada. Se cuenta con 1 IR elaborado pendiente de revisión final. | V24: 45818 | W24: IR elaborado por Paola, pendiente de revisión final. | Y24: Pendiente revisión final por parte de Herbert en abril 2026 | Z24: Sí | AA24: 46073 | AB24: =IF(AA24<TODAY(),"VENCIDO","POR VENCER") -> VENCIDO | AC24: 46136 | AD24: COMPLETADO | AE24: Atendido con el Informe N° 00126-2026-SUNEDU-DS-DIRESESU-UVE y notificado mediante el Oficio N° 00620-2026-SUNEDU-DS-DIRESESU-UVE, ambos del 24 de febrero de 2026. | AF24: {=IFERROR(_xlfn.XLOOKUP(TRIM($E24),TRIM('Año 2026'!$E$3:$E$66),'Año 2026'!$G$3:$G$66),"")} | AG24: {=IFERROR(_xlfn.XLOOKUP(TRIM($E24),TRIM('Año 2026'!$E$3:$E$66),'Año 2026'!$H$3:$H$66),"")} | AH24: {=IFERROR(_xlfn.XLOOKUP(TRIM($E24),TRIM('Año 2026'!$E$3:$E$66),'Año 2026'!$I$3:$I$66),"")} | AI24: {=IFERROR(_xlfn.XLOOKUP(TRIM($E24),TRIM('Año 2026'!$E$3:$E$66),'Año 2026'!$J$3:$J$66),"")} | AJ24: {=IFERROR(_xlfn.XLOOKUP(TRIM($E24),TRIM('Año 2026'!$E$3:$E$66),'Año 2026'!$K$3:$K$66),"")} | AK24: {=IFERROR(_xlfn.XLOOKUP(TRIM($E24),TRIM('Año 2026'!$E$3:$E$66),'Año 2026'!$L$3:$L$66),"")} | AL24: {=IFERROR(_xlfn.XLOOKUP(TRIM($E24),TRIM('Año 2026'!$E$3:$E$66),'Año 2026'!$M$3:$M$66),"")} | AM24: {=IFERROR(_xlfn.XLOOKUP(TRIM($E24),TRIM('Año 2026'!$E$3:$E$66),'Año 2026'!$N$3:$N$66),"")} | AN24: {=IFERROR(_xlfn.XLOOKUP(TRIM($E24),TRIM('Año 2026'!$E$3:$E$66),'Año 2026'!$O$3:$O$66),"")} | AO24: {=IFERROR(_xlfn.XLOOKUP(TRIM($E24),TRIM('Año 2026'!$E$3:$E$66),'Año 2026'!$P$3:$P$66),"")} | AP24: {=IFERROR(_xlfn.XLOOKUP(TRIM($E24),TRIM('Año 2026'!$E$3:$E$66),'Año 2026'!$Q$3:$Q$66),"")} | AQ24: {=IFERROR(_xlfn.XLOOKUP(TRIM($E24),TRIM('Año 2026'!$E$3:$E$66),'Año 2026'!$R$3:$R$66),"")} | AR24: {=IFERROR(_xlfn.XLOOKUP(TRIM($E24),TRIM('Año 2026'!$E$3:$E$66),'Año 2026'!$S$3:$S$66),"")} | AS24: {=IFERROR(_xlfn.XLOOKUP(TRIM($E24),TRIM('Año 2026'!$E$3:$E$66),'Año 2026'!$T$3:$T$66),"")} | AT24: {=IFERROR(_xlfn.XLOOKUP(TRIM($E24),TRIM('Año 2026'!$E$3:$E$66),'Año 2026'!$U$3:$U$66),"")} | AU24: {=IFERROR(_xlfn.XLOOKUP(TRIM($E24),TRIM('Año 2026'!$E$3:$E$66),'Año 2026'!$V$3:$V$66),"")} | AV24: {=IFERROR(_xlfn.XLOOKUP(TRIM($E24),TRIM('Año 2026'!$E$3:$E$66),'Año 2026'!$W$3:$W$66),"")} | AW24: {=IFERROR(_xlfn.XLOOKUP(TRIM($E24),TRIM('Año 2026'!$E$3:$E$66),'Año 2026'!$X$3:$X$66),"")} | AX24: {=IFERROR(_xlfn.XLOOKUP(TRIM($E24),TRIM('Año 2026'!$E$3:$E$66),'Año 2026'!$Y$3:$Y$66),"")} | AY24: {=IFERROR(_xlfn.XLOOKUP(TRIM($E24),TRIM('Año 2026'!$E$3:$E$66),'Año 2026'!$Z$3:$Z$66),"")} | AZ24: {=IFERROR(_xlfn.XLOOKUP(TRIM($E24),TRIM('Año 2026'!$E$3:$E$66),'Año 2026'!$AA$3:$AA$66),"")} | BA24: {=IFERROR(_xlfn.XLOOKUP(TRIM($E24),TRIM('Año 2026'!$E$3:$E$66),'Año 2026'!$AB$3:$AB$66),"")} | BB24: {=IFERROR(_xlfn.XLOOKUP(TRIM($E24),TRIM('Año 2026'!$E$3:$E$66),'Año 2026'!$AC$3:$AC$66),"")} | BC24: {=IFERROR(_xlfn.XLOOKUP(TRIM($E24),TRIM('Año 2026'!$E$3:$E$66),'Año 2026'!$AD$3:$AD$66),"")}
A25: 24 | B25: 2025 | C25: Accion Directa | D25: Correo electrónico | E25: AD-014-2025 | F25: Cerrada | H25: 36 | I25: Pública | J25: SL01 | K25: Cajamarca | L25: Cajamarca | M25: Cajamarca | N25: Av. Atahualpa 1050 | O25: MLI | P25: IV | Q25: 34 | R25: El programa Medicina Veterinaria (P21) de la Facultad de Ciencias Veterinarias de la Universidad habría permitido el uso arbitrario de canes protegidos por la Ley N° 30407, Ley de Protección y Bienestar Animal. Se vincula con el mantenimiento de la CBC IV, indicador 34 del Modelo de Licenciamiento. | S25: BAJA | W25: La denuncia continua como SNP, se cierra la AD. | Y25: Falta atender | AB25: SIN FECHA | AD25: EN PROCESO | AE25: Informe y/o Requerimiento de información | AF25: {=IFERROR(_xlfn.XLOOKUP(TRIM($E25),TRIM('Año 2026'!$E$3:$E$66),'Año 2026'!$G$3:$G$66),"")} | AG25: {=IFERROR(_xlfn.XLOOKUP(TRIM($E25),TRIM('Año 2026'!$E$3:$E$66),'Año 2026'!$H$3:$H$66),"")} | AH25: {=IFERROR(_xlfn.XLOOKUP(TRIM($E25),TRIM('Año 2026'!$E$3:$E$66),'Año 2026'!$I$3:$I$66),"")} | AI25: {=IFERROR(_xlfn.XLOOKUP(TRIM($E25),TRIM('Año 2026'!$E$3:$E$66),'Año 2026'!$J$3:$J$66),"")} | AJ25: {=IFERROR(_xlfn.XLOOKUP(TRIM($E25),TRIM('Año 2026'!$E$3:$E$66),'Año 2026'!$K$3:$K$66),"")} | AK25: {=IFERROR(_xlfn.XLOOKUP(TRIM($E25),TRIM('Año 2026'!$E$3:$E$66),'Año 2026'!$L$3:$L$66),"")} | AL25: {=IFERROR(_xlfn.XLOOKUP(TRIM($E25),TRIM('Año 2026'!$E$3:$E$66),'Año 2026'!$M$3:$M$66),"")} | AM25: {=IFERROR(_xlfn.XLOOKUP(TRIM($E25),TRIM('Año 2026'!$E$3:$E$66),'Año 2026'!$N$3:$N$66),"")} | AN25: {=IFERROR(_xlfn.XLOOKUP(TRIM($E25),TRIM('Año 2026'!$E$3:$E$66),'Año 2026'!$O$3:$O$66),"")} | AO25: {=IFERROR(_xlfn.XLOOKUP(TRIM($E25),TRIM('Año 2026'!$E$3:$E$66),'Año 2026'!$P$3:$P$66),"")} | AP25: {=IFERROR(_xlfn.XLOOKUP(TRIM($E25),TRIM('Año 2026'!$E$3:$E$66),'Año 2026'!$Q$3:$Q$66),"")} | AQ25: {=IFERROR(_xlfn.XLOOKUP(TRIM($E25),TRIM('Año 2026'!$E$3:$E$66),'Año 2026'!$R$3:$R$66),"")} | AR25: {=IFERROR(_xlfn.XLOOKUP(TRIM($E25),TRIM('Año 2026'!$E$3:$E$66),'Año 2026'!$S$3:$S$66),"")} | AS25: {=IFERROR(_xlfn.XLOOKUP(TRIM($E25),TRIM('Año 2026'!$E$3:$E$66),'Año 2026'!$T$3:$T$66),"")} | AT25: {=IFERROR(_xlfn.XLOOKUP(TRIM($E25),TRIM('Año 2026'!$E$3:$E$66),'Año 2026'!$U$3:$U$66),"")} | AU25: {=IFERROR(_xlfn.XLOOKUP(TRIM($E25),TRIM('Año 2026'!$E$3:$E$66),'Año 2026'!$V$3:$V$66),"")} | AV25: {=IFERROR(_xlfn.XLOOKUP(TRIM($E25),TRIM('Año 2026'!$E$3:$E$66),'Año 2026'!$W$3:$W$66),"")} | AW25: {=IFERROR(_xlfn.XLOOKUP(TRIM($E25),TRIM('Año 2026'!$E$3:$E$66),'Año 2026'!$X$3:$X$66),"")} | AX25: {=IFERROR(_xlfn.XLOOKUP(TRIM($E25),TRIM('Año 2026'!$E$3:$E$66),'Año 2026'!$Y$3:$Y$66),"")} | AY25: {=IFERROR(_xlfn.XLOOKUP(TRIM($E25),TRIM('Año 2026'!$E$3:$E$66),'Año 2026'!$Z$3:$Z$66),"")} | AZ25: {=IFERROR(_xlfn.XLOOKUP(TRIM($E25),TRIM('Año 2026'!$E$3:$E$66),'Año 2026'!$AA$3:$AA$66),"")} | BA25: {=IFERROR(_xlfn.XLOOKUP(TRIM($E25),TRIM('Año 2026'!$E$3:$E$66),'Año 2026'!$AB$3:$AB$66),"")} | BB25: {=IFERROR(_xlfn.XLOOKUP(TRIM($E25),TRIM('Año 2026'!$E$3:$E$66),'Año 2026'!$AC$3:$AC$66),"")} | BC25: {=IFERROR(_xlfn.XLOOKUP(TRIM($E25),TRIM('Año 2026'!$E$3:$E$66),'Año 2026'!$AD$3:$AD$66),"")}
A26: 25 | B26: 2025 | C26: Accion Directa | D26: Correo electrónico | E26: AD-031-2025 | F26: En trámite | H26: 13 | I26: Privada | J26: F05L01 | K26: Lima | L26: Lima | M26: Los Olivos | N26: Av. Alfredo Mendiola N° 6232, Urbanización lotización industrial Molitalia | O26: MLI | P26: III | Q26: 19, 30 | R26: Se tomó conocimiento de que, en el local F05L01 de la Universidad César Vallejo, el lunes 16 de junio del presente año se suspendieron las clases con el propósito de realizar una revisión preventiva de la infraestructura, tras la actividad sísmica registrada el domingo 15 de junio. | S26: MEDIA | U26: Registro de denuncia (Acta de registro de información) a partir de infografía de redes sociales. | V26: 45834 | W26: Se podría cerrar el informe con una visita de inspección breve que registre el estado de los ambientes y/o infraestructura que en su momento fue identificada como afectada por el movimiento sísimico de jun2025. | Y26: Falta atender | AB26: SIN FECHA | AD26: EN PROCESO | AE26: Informe y/o Requerimiento de información | AF26: {=IFERROR(_xlfn.XLOOKUP(TRIM($E26),TRIM('Año 2026'!$E$3:$E$66),'Año 2026'!$G$3:$G$66),"")} -> 0 | AG26: {=IFERROR(_xlfn.XLOOKUP(TRIM($E26),TRIM('Año 2026'!$E$3:$E$66),'Año 2026'!$H$3:$H$66),"")} -> 0 | AH26: {=IFERROR(_xlfn.XLOOKUP(TRIM($E26),TRIM('Año 2026'!$E$3:$E$66),'Año 2026'!$I$3:$I$66),"")} -> 0 | AI26: {=IFERROR(_xlfn.XLOOKUP(TRIM($E26),TRIM('Año 2026'!$E$3:$E$66),'Año 2026'!$J$3:$J$66),"")} -> 0 | AJ26: {=IFERROR(_xlfn.XLOOKUP(TRIM($E26),TRIM('Año 2026'!$E$3:$E$66),'Año 2026'!$K$3:$K$66),"")} -> -46192 | AK26: {=IFERROR(_xlfn.XLOOKUP(TRIM($E26),TRIM('Año 2026'!$E$3:$E$66),'Año 2026'!$L$3:$L$66),"")} -> 🚨 VENCIDO | AL26: {=IFERROR(_xlfn.XLOOKUP(TRIM($E26),TRIM('Año 2026'!$E$3:$E$66),'Año 2026'!$M$3:$M$66),"")} -> ❌ Vencido por 46192 días | AM26: {=IFERROR(_xlfn.XLOOKUP(TRIM($E26),TRIM('Año 2026'!$E$3:$E$66),'Año 2026'!$N$3:$N$66),"")} -> 0 | AN26: {=IFERROR(_xlfn.XLOOKUP(TRIM($E26),TRIM('Año 2026'!$E$3:$E$66),'Año 2026'!$O$3:$O$66),"")} -> 0 | AO26: {=IFERROR(_xlfn.XLOOKUP(TRIM($E26),TRIM('Año 2026'!$E$3:$E$66),'Año 2026'!$P$3:$P$66),"")} -> 0 | AP26: {=IFERROR(_xlfn.XLOOKUP(TRIM($E26),TRIM('Año 2026'!$E$3:$E$66),'Año 2026'!$Q$3:$Q$66),"")} -> 0 | AQ26: {=IFERROR(_xlfn.XLOOKUP(TRIM($E26),TRIM('Año 2026'!$E$3:$E$66),'Año 2026'!$R$3:$R$66),"")} -> 0 | AR26: {=IFERROR(_xlfn.XLOOKUP(TRIM($E26),TRIM('Año 2026'!$E$3:$E$66),'Año 2026'!$S$3:$S$66),"")} -> 0 | AS26: {=IFERROR(_xlfn.XLOOKUP(TRIM($E26),TRIM('Año 2026'!$E$3:$E$66),'Año 2026'!$T$3:$T$66),"")} -> 0 | AT26: {=IFERROR(_xlfn.XLOOKUP(TRIM($E26),TRIM('Año 2026'!$E$3:$E$66),'Año 2026'!$U$3:$U$66),"")} -> 0 | AU26: {=IFERROR(_xlfn.XLOOKUP(TRIM($E26),TRIM('Año 2026'!$E$3:$E$66),'Año 2026'!$V$3:$V$66),"")} -> 0 | AV26: {=IFERROR(_xlfn.XLOOKUP(TRIM($E26),TRIM('Año 2026'!$E$3:$E$66),'Año 2026'!$W$3:$W$66),"")} -> 0 | AW26: {=IFERROR(_xlfn.XLOOKUP(TRIM($E26),TRIM('Año 2026'!$E$3:$E$66),'Año 2026'!$X$3:$X$66),"")} -> 0 | AX26: {=IFERROR(_xlfn.XLOOKUP(TRIM($E26),TRIM('Año 2026'!$E$3:$E$66),'Año 2026'!$Y$3:$Y$66),"")} -> 0 | AY26: {=IFERROR(_xlfn.XLOOKUP(TRIM($E26),TRIM('Año 2026'!$E$3:$E$66),'Año 2026'!$Z$3:$Z$66),"")} -> 0 | AZ26: {=IFERROR(_xlfn.XLOOKUP(TRIM($E26),TRIM('Año 2026'!$E$3:$E$66),'Año 2026'!$AA$3:$AA$66),"")} -> 0 | BA26: {=IFERROR(_xlfn.XLOOKUP(TRIM($E26),TRIM('Año 2026'!$E$3:$E$66),'Año 2026'!$AB$3:$AB$66),"")} -> 0 | BB26: {=IFERROR(_xlfn.XLOOKUP(TRIM($E26),TRIM('Año 2026'!$E$3:$E$66),'Año 2026'!$AC$3:$AC$66),"")} -> 0 | BC26: {=IFERROR(_xlfn.XLOOKUP(TRIM($E26),TRIM('Año 2026'!$E$3:$E$66),'Año 2026'!$AD$3:$AD$66),"")} -> 0
A27: 26 | B27: 2025 | C27: Accion Directa | D27: Correo electrónico | E27: AD-037-2025 | F27: Archivado | G27: 2024EXT00015997-SUNEDU | H27: 13 | I27: Privada | J27: F04L03 | K27: Ancash | L27: Santa | M27: Nuevo Chimbote | N27: Monte de Chimbote Sub Lote 1-2, Sector Pampa Alconcillo | O27: MLI | P27: III | Q27: 19 | R27: Un sector del local nuevo en Nuevo Chimbote, ubicado en la Panamerica Norte, se utiliza como depósito de muebles, material de construcción , basura, entre otros. | S27: BAJA | U27: En dic 2015 remitió información solicitada en la visita de inspección realizada en dic 2025. | V27: 46002 | W27: En las fotografías de la visita de inspección se advierte una situación irregular que podría transgredir las condiciones de seguridad del local, se trata de la obras de 3 pisos que se ubica sobre otros 3 pisos construidos del pabellón principal del local. En dicha línea, se estaría utilizando ambientes a la par que se desarrollan obra civil en los pisos superiores. Durante la inspección la Universidad señaló que la obra se encontraría paralizada. | X27: GIGI NASSI | Y27: Falta elaborar Informe | AB27: SIN FECHA | AD27: COMPLETADO | AE27: Informe N° 00446-2026-SUNEDU-DS-DIRESESU-UVE que concluye con el archivamiento de la AD. | AF27: {=IFERROR(_xlfn.XLOOKUP(TRIM($E27),TRIM('Año 2026'!$E$3:$E$66),'Año 2026'!$G$3:$G$66),"")} | AG27: {=IFERROR(_xlfn.XLOOKUP(TRIM($E27),TRIM('Año 2026'!$E$3:$E$66),'Año 2026'!$H$3:$H$66),"")} | AH27: {=IFERROR(_xlfn.XLOOKUP(TRIM($E27),TRIM('Año 2026'!$E$3:$E$66),'Año 2026'!$I$3:$I$66),"")} | AI27: {=IFERROR(_xlfn.XLOOKUP(TRIM($E27),TRIM('Año 2026'!$E$3:$E$66),'Año 2026'!$J$3:$J$66),"")} | AJ27: {=IFERROR(_xlfn.XLOOKUP(TRIM($E27),TRIM('Año 2026'!$E$3:$E$66),'Año 2026'!$K$3:$K$66),"")} | AK27: {=IFERROR(_xlfn.XLOOKUP(TRIM($E27),TRIM('Año 2026'!$E$3:$E$66),'Año 2026'!$L$3:$L$66),"")} | AL27: {=IFERROR(_xlfn.XLOOKUP(TRIM($E27),TRIM('Año 2026'!$E$3:$E$66),'Año 2026'!$M$3:$M$66),"")} | AM27: {=IFERROR(_xlfn.XLOOKUP(TRIM($E27),TRIM('Año 2026'!$E$3:$E$66),'Año 2026'!$N$3:$N$66),"")} | AN27: {=IFERROR(_xlfn.XLOOKUP(TRIM($E27),TRIM('Año 2026'!$E$3:$E$66),'Año 2026'!$O$3:$O$66),"")} | AO27: {=IFERROR(_xlfn.XLOOKUP(TRIM($E27),TRIM('Año 2026'!$E$3:$E$66),'Año 2026'!$P$3:$P$66),"")} | AP27: {=IFERROR(_xlfn.XLOOKUP(TRIM($E27),TRIM('Año 2026'!$E$3:$E$66),'Año 2026'!$Q$3:$Q$66),"")} | AQ27: {=IFERROR(_xlfn.XLOOKUP(TRIM($E27),TRIM('Año 2026'!$E$3:$E$66),'Año 2026'!$R$3:$R$66),"")} | AR27: {=IFERROR(_xlfn.XLOOKUP(TRIM($E27),TRIM('Año 2026'!$E$3:$E$66),'Año 2026'!$S$3:$S$66),"")} | AS27: {=IFERROR(_xlfn.XLOOKUP(TRIM($E27),TRIM('Año 2026'!$E$3:$E$66),'Año 2026'!$T$3:$T$66),"")} | AT27: {=IFERROR(_xlfn.XLOOKUP(TRIM($E27),TRIM('Año 2026'!$E$3:$E$66),'Año 2026'!$U$3:$U$66),"")} | AU27: {=IFERROR(_xlfn.XLOOKUP(TRIM($E27),TRIM('Año 2026'!$E$3:$E$66),'Año 2026'!$V$3:$V$66),"")} | AV27: {=IFERROR(_xlfn.XLOOKUP(TRIM($E27),TRIM('Año 2026'!$E$3:$E$66),'Año 2026'!$W$3:$W$66),"")} | AW27: {=IFERROR(_xlfn.XLOOKUP(TRIM($E27),TRIM('Año 2026'!$E$3:$E$66),'Año 2026'!$X$3:$X$66),"")} | AX27: {=IFERROR(_xlfn.XLOOKUP(TRIM($E27),TRIM('Año 2026'!$E$3:$E$66),'Año 2026'!$Y$3:$Y$66),"")} | AY27: {=IFERROR(_xlfn.XLOOKUP(TRIM($E27),TRIM('Año 2026'!$E$3:$E$66),'Año 2026'!$Z$3:$Z$66),"")} | AZ27: {=IFERROR(_xlfn.XLOOKUP(TRIM($E27),TRIM('Año 2026'!$E$3:$E$66),'Año 2026'!$AA$3:$AA$66),"")} | BA27: {=IFERROR(_xlfn.XLOOKUP(TRIM($E27),TRIM('Año 2026'!$E$3:$E$66),'Año 2026'!$AB$3:$AB$66),"")} | BB27: {=IFERROR(_xlfn.XLOOKUP(TRIM($E27),TRIM('Año 2026'!$E$3:$E$66),'Año 2026'!$AC$3:$AC$66),"")} | BC27: {=IFERROR(_xlfn.XLOOKUP(TRIM($E27),TRIM('Año 2026'!$E$3:$E$66),'Año 2026'!$AD$3:$AD$66),"")}
A28: 27 | B28: 2025 | C28: Denuncia | D28: Web | E28: 01164-2025-SUNEDU/02-13 | F28: En trámite | G28: 2025EXT0000024112-SUNEDU | H28: 11 | I28: Privada | J28: F01L01 | K28: Cusco | L28: Canchis | M28: Sicuani | N28: Av. República de Hungría N° 1036 | O28: MLI | P28: III, VI | Q28: 17, 19, 20, 27, 28, 29, 30, 43, 44, 45, 48 | R28: Denuncia que en la página oficial de la universidad hace referencia a admisión en la carrera de Ingeniería Civil. Precisando, que actualmente esta institución no tiene los laboratorios correspondientes para ofertar esta carrera, es por ello que se esta lucrando mas sin pensar en el desarrollo de los estudiantes, por tal motivo solicita su inspección y clausura de la filial. | S28: ALTA | T28: 2 | U28: La Universidad remitió información complementaria mediante Oficio N° 0304-2025-R-UAC del 07.08.25 | V28: 45876 | W28: Pendiente escalar a SNP, mediante oficio. | Y28: Elaborar Oficio para escalar a SNP y requerimiento de info en mayo 2026. Falta programar producto | AB28: SIN FECHA | AD28: EN PROCESO | AE28: Carta y/o Oficio | AF28: {=IFERROR(_xlfn.XLOOKUP(TRIM($E28),TRIM('Año 2026'!$E$3:$E$66),'Año 2026'!$G$3:$G$66),"")} -> Oficio N° 02359-2025-SUNEDU-DS-DIRESESU-UVE | AG28: {=IFERROR(_xlfn.XLOOKUP(TRIM($E28),TRIM('Año 2026'!$E$3:$E$66),'Año 2026'!$H$3:$H$66),"")} -> 45839 | AH28: {=IFERROR(_xlfn.XLOOKUP(TRIM($E28),TRIM('Año 2026'!$E$3:$E$66),'Año 2026'!$I$3:$I$66),"")} -> 5 | AI28: {=IFERROR(_xlfn.XLOOKUP(TRIM($E28),TRIM('Año 2026'!$E$3:$E$66),'Año 2026'!$J$3:$J$66),"")} -> 45846 | AJ28: {=IFERROR(_xlfn.XLOOKUP(TRIM($E28),TRIM('Año 2026'!$E$3:$E$66),'Año 2026'!$K$3:$K$66),"")} -> -346 | AK28: {=IFERROR(_xlfn.XLOOKUP(TRIM($E28),TRIM('Año 2026'!$E$3:$E$66),'Año 2026'!$L$3:$L$66),"")} -> NUEVA FECHA | AL28: {=IFERROR(_xlfn.XLOOKUP(TRIM($E28),TRIM('Año 2026'!$E$3:$E$66),'Año 2026'!$M$3:$M$66),"")} -> NUEVA FECHA | AM28: {=IFERROR(_xlfn.XLOOKUP(TRIM($E28),TRIM('Año 2026'!$E$3:$E$66),'Año 2026'!$N$3:$N$66),"")} -> Ajustes al plazo | AN28: {=IFERROR(_xlfn.XLOOKUP(TRIM($E28),TRIM('Año 2026'!$E$3:$E$66),'Año 2026'!$O$3:$O$66),"")} -> 0 | AO28: {=IFERROR(_xlfn.XLOOKUP(TRIM($E28),TRIM('Año 2026'!$E$3:$E$66),'Año 2026'!$P$3:$P$66),"")} -> Prórroga | AP28: {=IFERROR(_xlfn.XLOOKUP(TRIM($E28),TRIM('Año 2026'!$E$3:$E$66),'Año 2026'!$Q$3:$Q$66),"")} -> 0 | AQ28: {=IFERROR(_xlfn.XLOOKUP(TRIM($E28),TRIM('Año 2026'!$E$3:$E$66),'Año 2026'!$R$3:$R$66),"")} -> 0 | AR28: {=IFERROR(_xlfn.XLOOKUP(TRIM($E28),TRIM('Año 2026'!$E$3:$E$66),'Año 2026'!$S$3:$S$66),"")} -> 0 | AS28: {=IFERROR(_xlfn.XLOOKUP(TRIM($E28),TRIM('Año 2026'!$E$3:$E$66),'Año 2026'!$T$3:$T$66),"")} -> 0 | AT28: {=IFERROR(_xlfn.XLOOKUP(TRIM($E28),TRIM('Año 2026'!$E$3:$E$66),'Año 2026'!$U$3:$U$66),"")} -> 0 | AU28: {=IFERROR(_xlfn.XLOOKUP(TRIM($E28),TRIM('Año 2026'!$E$3:$E$66),'Año 2026'!$V$3:$V$66),"")} -> Oficio N° 02665-2025-SUNEDU-DS-DIRESESU-UVE | AV28: {=IFERROR(_xlfn.XLOOKUP(TRIM($E28),TRIM('Año 2026'!$E$3:$E$66),'Año 2026'!$W$3:$W$66),"")} -> 45855 | AW28: {=IFERROR(_xlfn.XLOOKUP(TRIM($E28),TRIM('Año 2026'!$E$3:$E$66),'Año 2026'!$X$3:$X$66),"")} -> 6 | AX28: {=IFERROR(_xlfn.XLOOKUP(TRIM($E28),TRIM('Año 2026'!$E$3:$E$66),'Año 2026'!$Y$3:$Y$66),"")} | AY28: {=IFERROR(_xlfn.XLOOKUP(TRIM($E28),TRIM('Año 2026'!$E$3:$E$66),'Año 2026'!$Z$3:$Z$66),"")} | AZ28: {=IFERROR(_xlfn.XLOOKUP(TRIM($E28),TRIM('Año 2026'!$E$3:$E$66),'Año 2026'!$AA$3:$AA$66),"")} | BA28: {=IFERROR(_xlfn.XLOOKUP(TRIM($E28),TRIM('Año 2026'!$E$3:$E$66),'Año 2026'!$AB$3:$AB$66),"")} | BB28: {=IFERROR(_xlfn.XLOOKUP(TRIM($E28),TRIM('Año 2026'!$E$3:$E$66),'Año 2026'!$AC$3:$AC$66),"")} -> Entregado | BC28: {=IFERROR(_xlfn.XLOOKUP(TRIM($E28),TRIM('Año 2026'!$E$3:$E$66),'Año 2026'!$AD$3:$AD$66),"")} -> 0
A29: 28 | B29: 2025 | C29: SNP | D29: No programada - oficio | E29: 02521-2025-SUNEDU/02-13 | F29: En trámite | G29: 2025INT0000010126-SUNEDU | H29: 4 | I29: Pública | J29: SF Azángaro, SF Chucuito | K29: Puno | L29: SF Azángaro: Azángaro | SF Chucuito: Chucuito | M29: SF Azángaro: Azángaro | SF Chucuito: Juli | N29: SF Azángaro: Jr. Lima N°627 del Barrio Cultural Puente | SF Juli: Jr. Juli N°887/ Av. Bolognesi N°389 | O29: MLI | P29: I, III, IV, V, VI | Q29: 2, 5, 6, 17, 19, 20, 21, 22, 23, 24, 27, 28, 29, 30, 33, 36, 38, 39, 40, 41, 42, 43, 44, 45, 46, 47, 48, 50 | R29: Caso referido a la creación y funcionamiento de secciones de facultad de la Universidad Nacional del Altiplano en las provincias de Juli y Azángaro, en los que se estaría brindando el servicio educativo en edificaciones que corresponderían a instituciones de educación básica, sin encontrarse registradas en el SIU. Asimismo, se identificaron presuntas deficiencias en las condiciones de seguridad y habitabilidad de los ambientes. | S29: ALTA | T29: 2 | U29: La Universidad remitió información requerida en el Acta de Supervisión, mediante Oficio N° 407-2025-R-UNA-PUNO del 28.10.25 | V29: 45989 | W29: Solo se ha realizado visita de inspección y se ha requerido información, no hay ninguna acción adicional. | Y29: OS Antecedentes Barzen Manrique (Feb-26) CBC I y IV Katherine Mideyrosz (Feb y Mar-26) CBC V y CBC VI Tatiana Canales (Feb y Mar -26) Priorizada para ser cerrada en mayo 2026. (Rev. RL) | Z29: Sí | AA29: 46164 | AB29: =IF(AA29<TODAY(),"VENCIDO","POR VENCER") -> VENCIDO | AC29: 46171 | AD29: EN PROCESO | AE29: Informe de Resultados | AF29: {=IFERROR(_xlfn.XLOOKUP(TRIM($E29),TRIM('Año 2026'!$E$3:$E$66),'Año 2026'!$G$3:$G$66),"")} -> Oficio N° 03316-2025-SUNEDU-DS-DIRESESU-UVE (03.09.25) | AG29: {=IFERROR(_xlfn.XLOOKUP(TRIM($E29),TRIM('Año 2026'!$E$3:$E$66),'Año 2026'!$H$3:$H$66),"")} -> 45904 | AH29: {=IFERROR(_xlfn.XLOOKUP(TRIM($E29),TRIM('Año 2026'!$E$3:$E$66),'Año 2026'!$I$3:$I$66),"")} -> 3 | AI29: {=IFERROR(_xlfn.XLOOKUP(TRIM($E29),TRIM('Año 2026'!$E$3:$E$66),'Año 2026'!$J$3:$J$66),"")} -> 45909 | AJ29: {=IFERROR(_xlfn.XLOOKUP(TRIM($E29),TRIM('Año 2026'!$E$3:$E$66),'Año 2026'!$K$3:$K$66),"")} -> -283 | AK29: {=IFERROR(_xlfn.XLOOKUP(TRIM($E29),TRIM('Año 2026'!$E$3:$E$66),'Año 2026'!$L$3:$L$66),"")} -> NUEVA FECHA | AL29: {=IFERROR(_xlfn.XLOOKUP(TRIM($E29),TRIM('Año 2026'!$E$3:$E$66),'Año 2026'!$M$3:$M$66),"")} -> NUEVA FECHA | AM29: {=IFERROR(_xlfn.XLOOKUP(TRIM($E29),TRIM('Año 2026'!$E$3:$E$66),'Año 2026'!$N$3:$N$66),"")} -> Ajustes al plazo | AN29: {=IFERROR(_xlfn.XLOOKUP(TRIM($E29),TRIM('Año 2026'!$E$3:$E$66),'Año 2026'!$O$3:$O$66),"")} -> 0 | AO29: {=IFERROR(_xlfn.XLOOKUP(TRIM($E29),TRIM('Año 2026'!$E$3:$E$66),'Año 2026'!$P$3:$P$66),"")} -> Prórroga | AP29: {=IFERROR(_xlfn.XLOOKUP(TRIM($E29),TRIM('Año 2026'!$E$3:$E$66),'Año 2026'!$Q$3:$Q$66),"")} -> 0 | AQ29: {=IFERROR(_xlfn.XLOOKUP(TRIM($E29),TRIM('Año 2026'!$E$3:$E$66),'Año 2026'!$R$3:$R$66),"")} -> 0 | AR29: {=IFERROR(_xlfn.XLOOKUP(TRIM($E29),TRIM('Año 2026'!$E$3:$E$66),'Año 2026'!$S$3:$S$66),"")} -> 0 | AS29: {=IFERROR(_xlfn.XLOOKUP(TRIM($E29),TRIM('Año 2026'!$E$3:$E$66),'Año 2026'!$T$3:$T$66),"")} -> 0 | AT29: {=IFERROR(_xlfn.XLOOKUP(TRIM($E29),TRIM('Año 2026'!$E$3:$E$66),'Año 2026'!$U$3:$U$66),"")} -> 0 | AU29: {=IFERROR(_xlfn.XLOOKUP(TRIM($E29),TRIM('Año 2026'!$E$3:$E$66),'Año 2026'!$V$3:$V$66),"")} -> Oficio N° 04129-2025-SUNEDU-DS-DIRESESU-UVE | AV29: {=IFERROR(_xlfn.XLOOKUP(TRIM($E29),TRIM('Año 2026'!$E$3:$E$66),'Año 2026'!$W$3:$W$66),"")} -> 45945 | AW29: {=IFERROR(_xlfn.XLOOKUP(TRIM($E29),TRIM('Año 2026'!$E$3:$E$66),'Año 2026'!$X$3:$X$66),"")} -> 10 | AX29: {=IFERROR(_xlfn.XLOOKUP(TRIM($E29),TRIM('Año 2026'!$E$3:$E$66),'Año 2026'!$Y$3:$Y$66),"")} | AY29: {=IFERROR(_xlfn.XLOOKUP(TRIM($E29),TRIM('Año 2026'!$E$3:$E$66),'Año 2026'!$Z$3:$Z$66),"")} | AZ29: {=IFERROR(_xlfn.XLOOKUP(TRIM($E29),TRIM('Año 2026'!$E$3:$E$66),'Año 2026'!$AA$3:$AA$66),"")} | BA29: {=IFERROR(_xlfn.XLOOKUP(TRIM($E29),TRIM('Año 2026'!$E$3:$E$66),'Año 2026'!$AB$3:$AB$66),"")} | BB29: {=IFERROR(_xlfn.XLOOKUP(TRIM($E29),TRIM('Año 2026'!$E$3:$E$66),'Año 2026'!$AC$3:$AC$66),"")} -> Entregado | BC29: {=IFERROR(_xlfn.XLOOKUP(TRIM($E29),TRIM('Año 2026'!$E$3:$E$66),'Año 2026'!$AD$3:$AD$66),"")} -> 0
A30: 29 | B30: 2025 | C30: Denuncia | D30: Web | E30: 03188-2025-SUNEDU/02-13 | F30: Cerrada | G30: 2025EXT0000062629-SUNEDU | H30: 16 | I30: Pública | J30: SL03, SL04 | K30: Junin | L30: Tarma | M30: Acobamba | N30: SL03: Ubic. Rur. Sector Huancucro, AcobambaTarma-Junín | SL04: Predio denominado Huancucro | Acobamba-Tarma-Junín | O30: MLI | P30: III | Q30: 19, 27, 28, 30 | R30: Denuncia refiere que los alumnos se encontrarían estudiando en situación precaria, siendo que la Universidad no estaría utilizando todo su presupuesto. | S30: ALTA | T30: 1 | U30: Denuncia recibida | V30: 45987 | W30: Se requiere indagar previamente el estado de los proyectos de inversión, programas licenciados y programas de NOA, y posterior a ello constatar a través de una visita de inspección el estado de la infraestura de la Universidad. | Y30: Pendiente visita del 10.02.26 al 12.02.26 por Stephanie Recabarren + Susana Varas CBC III Carla La Torre Priorizada para ser cerrada en setiembre 2026. | Z30: Sí | AA30: 46283 | AB30: =IF(AA30<TODAY(),"VENCIDO","POR VENCER") -> POR VENCER | AC30: 46290 | AD30: COMPLETADO | AE30: Se archiva por inicio de SNP oficio N° 00423-2026-SUNEDU-DS-DIRESESU-UVE | AF30: {=IFERROR(_xlfn.XLOOKUP(TRIM($E30),TRIM('Año 2026'!$E$3:$E$66),'Año 2026'!$G$3:$G$66),"")} -> Oficio N° 00423-2026-SUNEDU-DS-DIRESESU-UVE (02.02.26) | AG30: {=IFERROR(_xlfn.XLOOKUP(TRIM($E30),TRIM('Año 2026'!$E$3:$E$66),'Año 2026'!$H$3:$H$66),"")} -> 46057 | AH30: {=IFERROR(_xlfn.XLOOKUP(TRIM($E30),TRIM('Año 2026'!$E$3:$E$66),'Año 2026'!$I$3:$I$66),"")} -> 2 | AI30: {=IFERROR(_xlfn.XLOOKUP(TRIM($E30),TRIM('Año 2026'!$E$3:$E$66),'Año 2026'!$J$3:$J$66),"")} -> 46094 | AJ30: {=IFERROR(_xlfn.XLOOKUP(TRIM($E30),TRIM('Año 2026'!$E$3:$E$66),'Año 2026'!$K$3:$K$66),"")} -> -98 | AK30: {=IFERROR(_xlfn.XLOOKUP(TRIM($E30),TRIM('Año 2026'!$E$3:$E$66),'Año 2026'!$L$3:$L$66),"")} -> NUEVA FECHA | AL30: {=IFERROR(_xlfn.XLOOKUP(TRIM($E30),TRIM('Año 2026'!$E$3:$E$66),'Año 2026'!$M$3:$M$66),"")} -> NUEVA FECHA | AM30: {=IFERROR(_xlfn.XLOOKUP(TRIM($E30),TRIM('Año 2026'!$E$3:$E$66),'Año 2026'!$N$3:$N$66),"")} -> Ajustes al plazo | AN30: {=IFERROR(_xlfn.XLOOKUP(TRIM($E30),TRIM('Año 2026'!$E$3:$E$66),'Año 2026'!$O$3:$O$66),"")} -> 0 | AO30: {=IFERROR(_xlfn.XLOOKUP(TRIM($E30),TRIM('Año 2026'!$E$3:$E$66),'Año 2026'!$P$3:$P$66),"")} -> Prórroga | AP30: {=IFERROR(_xlfn.XLOOKUP(TRIM($E30),TRIM('Año 2026'!$E$3:$E$66),'Año 2026'!$Q$3:$Q$66),"")} -> 0 | AQ30: {=IFERROR(_xlfn.XLOOKUP(TRIM($E30),TRIM('Año 2026'!$E$3:$E$66),'Año 2026'!$R$3:$R$66),"")} -> 0 | AR30: {=IFERROR(_xlfn.XLOOKUP(TRIM($E30),TRIM('Año 2026'!$E$3:$E$66),'Año 2026'!$S$3:$S$66),"")} -> 0 | AS30: {=IFERROR(_xlfn.XLOOKUP(TRIM($E30),TRIM('Año 2026'!$E$3:$E$66),'Año 2026'!$T$3:$T$66),"")} -> 0 | AT30: {=IFERROR(_xlfn.XLOOKUP(TRIM($E30),TRIM('Año 2026'!$E$3:$E$66),'Año 2026'!$U$3:$U$66),"")} -> 0 | AU30: {=IFERROR(_xlfn.XLOOKUP(TRIM($E30),TRIM('Año 2026'!$E$3:$E$66),'Año 2026'!$V$3:$V$66),"")} -> Oficio N° 00820-2026-SUNEDU-DS-DIRESESU-UVE (09.03.26) | AV30: {=IFERROR(_xlfn.XLOOKUP(TRIM($E30),TRIM('Año 2026'!$E$3:$E$66),'Año 2026'!$W$3:$W$66),"")} -> 46090 | AW30: {=IFERROR(_xlfn.XLOOKUP(TRIM($E30),TRIM('Año 2026'!$E$3:$E$66),'Año 2026'!$X$3:$X$66),"")} -> 10 | AX30: {=IFERROR(_xlfn.XLOOKUP(TRIM($E30),TRIM('Año 2026'!$E$3:$E$66),'Año 2026'!$Y$3:$Y$66),"")} | AY30: {=IFERROR(_xlfn.XLOOKUP(TRIM($E30),TRIM('Año 2026'!$E$3:$E$66),'Año 2026'!$Z$3:$Z$66),"")} | AZ30: {=IFERROR(_xlfn.XLOOKUP(TRIM($E30),TRIM('Año 2026'!$E$3:$E$66),'Año 2026'!$AA$3:$AA$66),"")} | BA30: {=IFERROR(_xlfn.XLOOKUP(TRIM($E30),TRIM('Año 2026'!$E$3:$E$66),'Año 2026'!$AB$3:$AB$66),"")} | BB30: {=IFERROR(_xlfn.XLOOKUP(TRIM($E30),TRIM('Año 2026'!$E$3:$E$66),'Año 2026'!$AC$3:$AC$66),"")} -> Entregado | BC30: {=IFERROR(_xlfn.XLOOKUP(TRIM($E30),TRIM('Año 2026'!$E$3:$E$66),'Año 2026'!$AD$3:$AD$66),"")} -> 0
A31: 30 | B31: 2025 | C31: SNP | D31: Web | E31: 03190-2025-SUNEDU/02-13 (Vinculado 03188-2025-SUNEDU/02-13) | F31: En trámite | G31: 2025EXT0000062679-SUNEDU, 2025EXT0000063005-SUNEDU | H31: 16 | I31: Pública | J31: SL03, SL04 | K31: Junin | L31: Tarma | M31: Acobamba | N31: SL03: Ubic. Rur. Sector Huancucro, AcobambaTarma-Junín | SL04: Predio denominado Huancucro | Acobamba-Tarma-Junín | O31: MLI | R31: Denuncia refiere a la comisión organizadora de la Universidad, respecto de la cual se señala que estaría conformada por personal que tendría denuncias de acoso sexual y malversación de presupuesto. | S31: MEDIA | T31: 1 | U31: Denuncia recibida | V31: 45987 | W31: Por el criterio de sostenibilidad financiera se podría realizar las acciones indagatorias de esta denuncia. Se podría sumar a las acciones de la denuncia que refiere a infraestructura precaria, y que ameritaría una visita de inspección. | Y31: Se acumula con 03188-2025-SUNEDU/02-13 | AB31: SIN FECHA | AD31: EN PROCESO | AE31: Se recomienda acumular la atención al Expediente más antiguo al ser afines | AF31: {=IFERROR(_xlfn.XLOOKUP(TRIM($E31),TRIM('Año 2026'!$E$3:$E$66),'Año 2026'!$G$3:$G$66),"")} | AG31: {=IFERROR(_xlfn.XLOOKUP(TRIM($E31),TRIM('Año 2026'!$E$3:$E$66),'Año 2026'!$H$3:$H$66),"")} | AH31: {=IFERROR(_xlfn.XLOOKUP(TRIM($E31),TRIM('Año 2026'!$E$3:$E$66),'Año 2026'!$I$3:$I$66),"")} | AI31: {=IFERROR(_xlfn.XLOOKUP(TRIM($E31),TRIM('Año 2026'!$E$3:$E$66),'Año 2026'!$J$3:$J$66),"")} | AJ31: {=IFERROR(_xlfn.XLOOKUP(TRIM($E31),TRIM('Año 2026'!$E$3:$E$66),'Año 2026'!$K$3:$K$66),"")} | AK31: {=IFERROR(_xlfn.XLOOKUP(TRIM($E31),TRIM('Año 2026'!$E$3:$E$66),'Año 2026'!$L$3:$L$66),"")} | AL31: {=IFERROR(_xlfn.XLOOKUP(TRIM($E31),TRIM('Año 2026'!$E$3:$E$66),'Año 2026'!$M$3:$M$66),"")} | AM31: {=IFERROR(_xlfn.XLOOKUP(TRIM($E31),TRIM('Año 2026'!$E$3:$E$66),'Año 2026'!$N$3:$N$66),"")} | AN31: {=IFERROR(_xlfn.XLOOKUP(TRIM($E31),TRIM('Año 2026'!$E$3:$E$66),'Año 2026'!$O$3:$O$66),"")} | AO31: {=IFERROR(_xlfn.XLOOKUP(TRIM($E31),TRIM('Año 2026'!$E$3:$E$66),'Año 2026'!$P$3:$P$66),"")} | AP31: {=IFERROR(_xlfn.XLOOKUP(TRIM($E31),TRIM('Año 2026'!$E$3:$E$66),'Año 2026'!$Q$3:$Q$66),"")} | AQ31: {=IFERROR(_xlfn.XLOOKUP(TRIM($E31),TRIM('Año 2026'!$E$3:$E$66),'Año 2026'!$R$3:$R$66),"")} | AR31: {=IFERROR(_xlfn.XLOOKUP(TRIM($E31),TRIM('Año 2026'!$E$3:$E$66),'Año 2026'!$S$3:$S$66),"")} | AS31: {=IFERROR(_xlfn.XLOOKUP(TRIM($E31),TRIM('Año 2026'!$E$3:$E$66),'Año 2026'!$T$3:$T$66),"")} | AT31: {=IFERROR(_xlfn.XLOOKUP(TRIM($E31),TRIM('Año 2026'!$E$3:$E$66),'Año 2026'!$U$3:$U$66),"")} | AU31: {=IFERROR(_xlfn.XLOOKUP(TRIM($E31),TRIM('Año 2026'!$E$3:$E$66),'Año 2026'!$V$3:$V$66),"")} | AV31: {=IFERROR(_xlfn.XLOOKUP(TRIM($E31),TRIM('Año 2026'!$E$3:$E$66),'Año 2026'!$W$3:$W$66),"")} | AW31: {=IFERROR(_xlfn.XLOOKUP(TRIM($E31),TRIM('Año 2026'!$E$3:$E$66),'Año 2026'!$X$3:$X$66),"")} | AX31: {=IFERROR(_xlfn.XLOOKUP(TRIM($E31),TRIM('Año 2026'!$E$3:$E$66),'Año 2026'!$Y$3:$Y$66),"")} | AY31: {=IFERROR(_xlfn.XLOOKUP(TRIM($E31),TRIM('Año 2026'!$E$3:$E$66),'Año 2026'!$Z$3:$Z$66),"")} | AZ31: {=IFERROR(_xlfn.XLOOKUP(TRIM($E31),TRIM('Año 2026'!$E$3:$E$66),'Año 2026'!$AA$3:$AA$66),"")} | BA31: {=IFERROR(_xlfn.XLOOKUP(TRIM($E31),TRIM('Año 2026'!$E$3:$E$66),'Año 2026'!$AB$3:$AB$66),"")} | BB31: {=IFERROR(_xlfn.XLOOKUP(TRIM($E31),TRIM('Año 2026'!$E$3:$E$66),'Año 2026'!$AC$3:$AC$66),"")} | BC31: {=IFERROR(_xlfn.XLOOKUP(TRIM($E31),TRIM('Año 2026'!$E$3:$E$66),'Año 2026'!$AD$3:$AD$66),"")}
A32: 31 | B32: 2025 | C32: Denuncia | D32: MP | E32: 01927-2025-SUNEDU/02-13 | F32: Cerrada | G32: 2025EXT0000038971-SUNEDU, 2024INT0000002755-SUNEDU | H32: 31 | I32: Pública | J32: SL01 | K32: Pasco | L32: Pasco | M32: Yanacancha | N32: Programa de vivienda Urbanización San Juan Pampa, Mz Q, Lote 1, Sector Centro Comercial | O32: MLI | P32: III | Q32: 27, 28 | R32: Denuncia referida a la presunta falta de implementación del programa de Ingeniería Metalúrgica de la Universidad Nacional Daniel Alcides Carrión, consistente en la inexistencia y/o insuficiencia de laboratorios, talleres, reactivos, materiales y equipamiento necesario para el desarrollo de prácticas académicas, lo que habría limitado la formación de competencias profesionales de los estudiantes. Asimismo, se reporta la falta de asignación de ambientes adecuados para los laboratorios pedagógicos, la inoperatividad de equipos especializados —como el equipo de absorción atómica— por ausencia de personal capacitado, así como deficiencias en la dotación de insumos básicos para el inicio del semestre académico. Adicionalmente, se advierten presuntas deficiencias en la gestión administrativa vinculadas a la demora en la entrega de ambientes, falta de atención a reclamos formales presentados por estudiantes y egresados, y ausencia de acciones oportunas para garantizar condiciones mínimas de infraestructura y equipamiento. | S32: ALTA | U32: Se escala a SNP | V32: 45853 | W32: La denuncia continua como SNP, se cierra la AD. | AB32: SIN FECHA | AD32: EN PROCESO | AE32: Carta y/o Oficio | AF32: {=IFERROR(_xlfn.XLOOKUP(TRIM($E32),TRIM('Año 2026'!$E$3:$E$66),'Año 2026'!$G$3:$G$66),"")} -> 05589-2025-SUNEDU-DS-DIRESESU-UVE | AG32: {=IFERROR(_xlfn.XLOOKUP(TRIM($E32),TRIM('Año 2026'!$E$3:$E$66),'Año 2026'!$H$3:$H$66),"")} -> 46029 | AH32: {=IFERROR(_xlfn.XLOOKUP(TRIM($E32),TRIM('Año 2026'!$E$3:$E$66),'Año 2026'!$I$3:$I$66),"")} -> 5 | AI32: {=IFERROR(_xlfn.XLOOKUP(TRIM($E32),TRIM('Año 2026'!$E$3:$E$66),'Año 2026'!$J$3:$J$66),"")} -> 46094 | AJ32: {=IFERROR(_xlfn.XLOOKUP(TRIM($E32),TRIM('Año 2026'!$E$3:$E$66),'Año 2026'!$K$3:$K$66),"")} -> -98 | AK32: {=IFERROR(_xlfn.XLOOKUP(TRIM($E32),TRIM('Año 2026'!$E$3:$E$66),'Año 2026'!$L$3:$L$66),"")} -> NUEVA FECHA | AL32: {=IFERROR(_xlfn.XLOOKUP(TRIM($E32),TRIM('Año 2026'!$E$3:$E$66),'Año 2026'!$M$3:$M$66),"")} -> NUEVA FECHA | AM32: {=IFERROR(_xlfn.XLOOKUP(TRIM($E32),TRIM('Año 2026'!$E$3:$E$66),'Año 2026'!$N$3:$N$66),"")} -> Ajustes al plazo | AN32: {=IFERROR(_xlfn.XLOOKUP(TRIM($E32),TRIM('Año 2026'!$E$3:$E$66),'Año 2026'!$O$3:$O$66),"")} -> 0 | AO32: {=IFERROR(_xlfn.XLOOKUP(TRIM($E32),TRIM('Año 2026'!$E$3:$E$66),'Año 2026'!$P$3:$P$66),"")} -> Prórroga | AP32: {=IFERROR(_xlfn.XLOOKUP(TRIM($E32),TRIM('Año 2026'!$E$3:$E$66),'Año 2026'!$Q$3:$Q$66),"")} -> 0 | AQ32: {=IFERROR(_xlfn.XLOOKUP(TRIM($E32),TRIM('Año 2026'!$E$3:$E$66),'Año 2026'!$R$3:$R$66),"")} -> 0 | AR32: {=IFERROR(_xlfn.XLOOKUP(TRIM($E32),TRIM('Año 2026'!$E$3:$E$66),'Año 2026'!$S$3:$S$66),"")} -> 0 | AS32: {=IFERROR(_xlfn.XLOOKUP(TRIM($E32),TRIM('Año 2026'!$E$3:$E$66),'Año 2026'!$T$3:$T$66),"")} -> 0 | AT32: {=IFERROR(_xlfn.XLOOKUP(TRIM($E32),TRIM('Año 2026'!$E$3:$E$66),'Año 2026'!$U$3:$U$66),"")} -> 0 | AU32: {=IFERROR(_xlfn.XLOOKUP(TRIM($E32),TRIM('Año 2026'!$E$3:$E$66),'Año 2026'!$V$3:$V$66),"")} -> 0 | AV32: {=IFERROR(_xlfn.XLOOKUP(TRIM($E32),TRIM('Año 2026'!$E$3:$E$66),'Año 2026'!$W$3:$W$66),"")} -> 0 | AW32: {=IFERROR(_xlfn.XLOOKUP(TRIM($E32),TRIM('Año 2026'!$E$3:$E$66),'Año 2026'!$X$3:$X$66),"")} -> 0 | AX32: {=IFERROR(_xlfn.XLOOKUP(TRIM($E32),TRIM('Año 2026'!$E$3:$E$66),'Año 2026'!$Y$3:$Y$66),"")} -> 0 | AY32: {=IFERROR(_xlfn.XLOOKUP(TRIM($E32),TRIM('Año 2026'!$E$3:$E$66),'Año 2026'!$Z$3:$Z$66),"")} -> 0 | AZ32: {=IFERROR(_xlfn.XLOOKUP(TRIM($E32),TRIM('Año 2026'!$E$3:$E$66),'Año 2026'!$AA$3:$AA$66),"")} -> 0 | BA32: {=IFERROR(_xlfn.XLOOKUP(TRIM($E32),TRIM('Año 2026'!$E$3:$E$66),'Año 2026'!$AB$3:$AB$66),"")} -> 0 | BB32: {=IFERROR(_xlfn.XLOOKUP(TRIM($E32),TRIM('Año 2026'!$E$3:$E$66),'Año 2026'!$AC$3:$AC$66),"")} -> Entregado | BC32: {=IFERROR(_xlfn.XLOOKUP(TRIM($E32),TRIM('Año 2026'!$E$3:$E$66),'Año 2026'!$AD$3:$AD$66),"")} -> No se atendió la prórroga
A33: 32 | B33: 2025 | C33: SNP | D33: Web | E33: 03200-2025-SUNEDU/02-13) (Vinculado 03188-2025-SUNEDU/02-13) | F33: En trámite | G33: 2025EXT0000063141-SUNEDU | H33: 16 | I33: Pública | J33: SL03, SL04 | K33: Junin | L33: Tarma | M33: Acobamba | N33: SL03: Ubic. Rur. Sector Huancucro, AcobambaTarma-Junín | SL04: Predio denominado Huancucro | Acobamba-Tarma-Junín | O33: MLI | P33: III | Q33: 27, 28, 30 | R33: Denuncia refiere a la comisión organizadora, respecto de la cual señala que habría incurrido en actos de corrupción y priorizó obras que no atienden a la necesidad de la Escuela Profesional de Ingeniería Agroindustrial, carente de infraestructura, laboratorios y equipamiento, así como no se estaría promoviendo el área de investigación. También señala que las Escuelas vinculadas con las carreras profesionales de Administración y Medicina Humana presentan falencias. | S33: ALTA | T33: 1 | U33: Denuncia recibida | V33: 45988 | W33: Se requiere indagar previamente el estado de los proyectos de inversión, programas licenciados y programas de NOA, y posterior a ello constatar a través de una visita de inspección el estado de la infraestura de la Universidad. | Y33: Se acumula con 03188-2025-SUNEDU/02-13 | AB33: SIN FECHA | AD33: EN PROCESO | AE33: Se recomienda acumular la atención al Expediente más antiguo al ser afines | AF33: {=IFERROR(_xlfn.XLOOKUP(TRIM($E33),TRIM('Año 2026'!$E$3:$E$66),'Año 2026'!$G$3:$G$66),"")} | AG33: {=IFERROR(_xlfn.XLOOKUP(TRIM($E33),TRIM('Año 2026'!$E$3:$E$66),'Año 2026'!$H$3:$H$66),"")} | AH33: {=IFERROR(_xlfn.XLOOKUP(TRIM($E33),TRIM('Año 2026'!$E$3:$E$66),'Año 2026'!$I$3:$I$66),"")} | AI33: {=IFERROR(_xlfn.XLOOKUP(TRIM($E33),TRIM('Año 2026'!$E$3:$E$66),'Año 2026'!$J$3:$J$66),"")} | AJ33: {=IFERROR(_xlfn.XLOOKUP(TRIM($E33),TRIM('Año 2026'!$E$3:$E$66),'Año 2026'!$K$3:$K$66),"")} | AK33: {=IFERROR(_xlfn.XLOOKUP(TRIM($E33),TRIM('Año 2026'!$E$3:$E$66),'Año 2026'!$L$3:$L$66),"")} | AL33: {=IFERROR(_xlfn.XLOOKUP(TRIM($E33),TRIM('Año 2026'!$E$3:$E$66),'Año 2026'!$M$3:$M$66),"")} | AM33: {=IFERROR(_xlfn.XLOOKUP(TRIM($E33),TRIM('Año 2026'!$E$3:$E$66),'Año 2026'!$N$3:$N$66),"")} | AN33: {=IFERROR(_xlfn.XLOOKUP(TRIM($E33),TRIM('Año 2026'!$E$3:$E$66),'Año 2026'!$O$3:$O$66),"")} | AO33: {=IFERROR(_xlfn.XLOOKUP(TRIM($E33),TRIM('Año 2026'!$E$3:$E$66),'Año 2026'!$P$3:$P$66),"")} | AP33: {=IFERROR(_xlfn.XLOOKUP(TRIM($E33),TRIM('Año 2026'!$E$3:$E$66),'Año 2026'!$Q$3:$Q$66),"")} | AQ33: {=IFERROR(_xlfn.XLOOKUP(TRIM($E33),TRIM('Año 2026'!$E$3:$E$66),'Año 2026'!$R$3:$R$66),"")} | AR33: {=IFERROR(_xlfn.XLOOKUP(TRIM($E33),TRIM('Año 2026'!$E$3:$E$66),'Año 2026'!$S$3:$S$66),"")} | AS33: {=IFERROR(_xlfn.XLOOKUP(TRIM($E33),TRIM('Año 2026'!$E$3:$E$66),'Año 2026'!$T$3:$T$66),"")} | AT33: {=IFERROR(_xlfn.XLOOKUP(TRIM($E33),TRIM('Año 2026'!$E$3:$E$66),'Año 2026'!$U$3:$U$66),"")} | AU33: {=IFERROR(_xlfn.XLOOKUP(TRIM($E33),TRIM('Año 2026'!$E$3:$E$66),'Año 2026'!$V$3:$V$66),"")} | AV33: {=IFERROR(_xlfn.XLOOKUP(TRIM($E33),TRIM('Año 2026'!$E$3:$E$66),'Año 2026'!$W$3:$W$66),"")} | AW33: {=IFERROR(_xlfn.XLOOKUP(TRIM($E33),TRIM('Año 2026'!$E$3:$E$66),'Año 2026'!$X$3:$X$66),"")} | AX33: {=IFERROR(_xlfn.XLOOKUP(TRIM($E33),TRIM('Año 2026'!$E$3:$E$66),'Año 2026'!$Y$3:$Y$66),"")} | AY33: {=IFERROR(_xlfn.XLOOKUP(TRIM($E33),TRIM('Año 2026'!$E$3:$E$66),'Año 2026'!$Z$3:$Z$66),"")} | AZ33: {=IFERROR(_xlfn.XLOOKUP(TRIM($E33),TRIM('Año 2026'!$E$3:$E$66),'Año 2026'!$AA$3:$AA$66),"")} | BA33: {=IFERROR(_xlfn.XLOOKUP(TRIM($E33),TRIM('Año 2026'!$E$3:$E$66),'Año 2026'!$AB$3:$AB$66),"")} | BB33: {=IFERROR(_xlfn.XLOOKUP(TRIM($E33),TRIM('Año 2026'!$E$3:$E$66),'Año 2026'!$AC$3:$AC$66),"")} | BC33: {=IFERROR(_xlfn.XLOOKUP(TRIM($E33),TRIM('Año 2026'!$E$3:$E$66),'Año 2026'!$AD$3:$AD$66),"")}
A34: 33 | B34: 2025 | C34: SNP | D34: Web | E34: 03188-2025-SUNEDU/02-13 | F34: En trámite | G34: 2025EXT0000062629-SUNEDU | H34: 16 | I34: Pública | J34: SL03, SL04 | K34: Junin | L34: Tarma | M34: Acobamba | N34: SL03: Ubic. Rur. Sector Huancucro, AcobambaTarma-Junín | SL04: Predio denominado Huancucro | Acobamba-Tarma-Junín | O34: MLI | P34: III | Q34: 19, 27, 28, 30 | R34: Denuncia refiere que los alumnos se encontrarían estudiando en situación precaria, siendo que la Universidad no estaría utilizando todo su presupuesto. | Y34: Se acumula con 03188-2025-SUNEDU/02-14 | AB34: SIN FECHA | AD34: EN PROCESO | AE34: Se recomienda acumular la atención al Expediente más antiguo al ser afines | AF34: {=IFERROR(_xlfn.XLOOKUP(TRIM($E34),TRIM('Año 2026'!$E$3:$E$66),'Año 2026'!$G$3:$G$66),"")} -> Oficio N° 00423-2026-SUNEDU-DS-DIRESESU-UVE (02.02.26) | AG34: {=IFERROR(_xlfn.XLOOKUP(TRIM($E34),TRIM('Año 2026'!$E$3:$E$66),'Año 2026'!$H$3:$H$66),"")} -> 46057 | AH34: {=IFERROR(_xlfn.XLOOKUP(TRIM($E34),TRIM('Año 2026'!$E$3:$E$66),'Año 2026'!$I$3:$I$66),"")} -> 2 | AI34: {=IFERROR(_xlfn.XLOOKUP(TRIM($E34),TRIM('Año 2026'!$E$3:$E$66),'Año 2026'!$J$3:$J$66),"")} -> 46094 | AJ34: {=IFERROR(_xlfn.XLOOKUP(TRIM($E34),TRIM('Año 2026'!$E$3:$E$66),'Año 2026'!$K$3:$K$66),"")} -> -98 | AK34: {=IFERROR(_xlfn.XLOOKUP(TRIM($E34),TRIM('Año 2026'!$E$3:$E$66),'Año 2026'!$L$3:$L$66),"")} -> NUEVA FECHA | AL34: {=IFERROR(_xlfn.XLOOKUP(TRIM($E34),TRIM('Año 2026'!$E$3:$E$66),'Año 2026'!$M$3:$M$66),"")} -> NUEVA FECHA | AM34: {=IFERROR(_xlfn.XLOOKUP(TRIM($E34),TRIM('Año 2026'!$E$3:$E$66),'Año 2026'!$N$3:$N$66),"")} -> Ajustes al plazo | AN34: {=IFERROR(_xlfn.XLOOKUP(TRIM($E34),TRIM('Año 2026'!$E$3:$E$66),'Año 2026'!$O$3:$O$66),"")} -> 0 | AO34: {=IFERROR(_xlfn.XLOOKUP(TRIM($E34),TRIM('Año 2026'!$E$3:$E$66),'Año 2026'!$P$3:$P$66),"")} -> Prórroga | AP34: {=IFERROR(_xlfn.XLOOKUP(TRIM($E34),TRIM('Año 2026'!$E$3:$E$66),'Año 2026'!$Q$3:$Q$66),"")} -> 0 | AQ34: {=IFERROR(_xlfn.XLOOKUP(TRIM($E34),TRIM('Año 2026'!$E$3:$E$66),'Año 2026'!$R$3:$R$66),"")} -> 0 | AR34: {=IFERROR(_xlfn.XLOOKUP(TRIM($E34),TRIM('Año 2026'!$E$3:$E$66),'Año 2026'!$S$3:$S$66),"")} -> 0 | AS34: {=IFERROR(_xlfn.XLOOKUP(TRIM($E34),TRIM('Año 2026'!$E$3:$E$66),'Año 2026'!$T$3:$T$66),"")} -> 0 | AT34: {=IFERROR(_xlfn.XLOOKUP(TRIM($E34),TRIM('Año 2026'!$E$3:$E$66),'Año 2026'!$U$3:$U$66),"")} -> 0 | AU34: {=IFERROR(_xlfn.XLOOKUP(TRIM($E34),TRIM('Año 2026'!$E$3:$E$66),'Año 2026'!$V$3:$V$66),"")} -> Oficio N° 00820-2026-SUNEDU-DS-DIRESESU-UVE (09.03.26) | AV34: {=IFERROR(_xlfn.XLOOKUP(TRIM($E34),TRIM('Año 2026'!$E$3:$E$66),'Año 2026'!$W$3:$W$66),"")} -> 46090 | AW34: {=IFERROR(_xlfn.XLOOKUP(TRIM($E34),TRIM('Año 2026'!$E$3:$E$66),'Año 2026'!$X$3:$X$66),"")} -> 10 | AX34: {=IFERROR(_xlfn.XLOOKUP(TRIM($E34),TRIM('Año 2026'!$E$3:$E$66),'Año 2026'!$Y$3:$Y$66),"")} | AY34: {=IFERROR(_xlfn.XLOOKUP(TRIM($E34),TRIM('Año 2026'!$E$3:$E$66),'Año 2026'!$Z$3:$Z$66),"")} | AZ34: {=IFERROR(_xlfn.XLOOKUP(TRIM($E34),TRIM('Año 2026'!$E$3:$E$66),'Año 2026'!$AA$3:$AA$66),"")} | BA34: {=IFERROR(_xlfn.XLOOKUP(TRIM($E34),TRIM('Año 2026'!$E$3:$E$66),'Año 2026'!$AB$3:$AB$66),"")} | BB34: {=IFERROR(_xlfn.XLOOKUP(TRIM($E34),TRIM('Año 2026'!$E$3:$E$66),'Año 2026'!$AC$3:$AC$66),"")} -> Entregado | BC34: {=IFERROR(_xlfn.XLOOKUP(TRIM($E34),TRIM('Año 2026'!$E$3:$E$66),'Año 2026'!$AD$3:$AD$66),"")} -> 0
A35: 34 | B35: 2025 | C35: Denuncia | D35: Web | E35: 02619-2025-SUNEDU/02-13 | F35: En trámite | G35: 2025EXT0000049372-SUNEDU, 2024INT0000002755-SUNEDU | H35: 31 | I35: Pública | J35: SL01 | K35: Pasco | L35: Pasco | M35: Yanacancha | N35: Programa de vivienda Urbanización San Juan Pampa, Mz Q, Lote 1, Sector Centro Comercial | O35: MLI | P35: III | Q35: 17, 19, 20, 27, 28 | R35: Denuncia referida a la Universidad Nacional Daniel Alcides Carrión (UNDAC), consistente en la falta de infraestructura propia y adecuada para el desarrollo de las actividades académicas de la Facultad de Ciencias de la Comunicación, la utilización de aulas prestadas correspondientes a la Facultad de Educación sin contar con autorización ni implementación suficiente, así como la advertencia de un eventual desalojo de los ambientes actualmente ocupados, lo que comprometería la continuidad del servicio educativo. Asimismo, se reporta la inexistencia de ambientes adecuados para el desarrollo de la Escuela Profesional de Ciencias de la Comunicación, así como la ausencia de laboratorios y de condiciones mínimas de funcionamiento. | S35: ALTA | U35: Ingreso de Formato Único de Denuncia con fecha 10.09.25/Se escaló a SNP | V35: 45910 | W35: La denuncia continua como SNP, se cierra la AD. | AB35: SIN FECHA | AD35: EN PROCESO | AE35: Carta y/o Oficio | AF35: {=IFERROR(_xlfn.XLOOKUP(TRIM($E35),TRIM('Año 2026'!$E$3:$E$66),'Año 2026'!$G$3:$G$66),"")} -> 05589-2025-SUNEDU-DS-DIRESESU-UVE | AG35: {=IFERROR(_xlfn.XLOOKUP(TRIM($E35),TRIM('Año 2026'!$E$3:$E$66),'Año 2026'!$H$3:$H$66),"")} -> 46029 | AH35: {=IFERROR(_xlfn.XLOOKUP(TRIM($E35),TRIM('Año 2026'!$E$3:$E$66),'Año 2026'!$I$3:$I$66),"")} -> 5 | AI35: {=IFERROR(_xlfn.XLOOKUP(TRIM($E35),TRIM('Año 2026'!$E$3:$E$66),'Año 2026'!$J$3:$J$66),"")} -> 46094 | AJ35: {=IFERROR(_xlfn.XLOOKUP(TRIM($E35),TRIM('Año 2026'!$E$3:$E$66),'Año 2026'!$K$3:$K$66),"")} -> -98 | AK35: {=IFERROR(_xlfn.XLOOKUP(TRIM($E35),TRIM('Año 2026'!$E$3:$E$66),'Año 2026'!$L$3:$L$66),"")} -> NUEVA FECHA | AL35: {=IFERROR(_xlfn.XLOOKUP(TRIM($E35),TRIM('Año 2026'!$E$3:$E$66),'Año 2026'!$M$3:$M$66),"")} -> NUEVA FECHA | AM35: {=IFERROR(_xlfn.XLOOKUP(TRIM($E35),TRIM('Año 2026'!$E$3:$E$66),'Año 2026'!$N$3:$N$66),"")} -> Ajustes al plazo | AN35: {=IFERROR(_xlfn.XLOOKUP(TRIM($E35),TRIM('Año 2026'!$E$3:$E$66),'Año 2026'!$O$3:$O$66),"")} -> 0 | AO35: {=IFERROR(_xlfn.XLOOKUP(TRIM($E35),TRIM('Año 2026'!$E$3:$E$66),'Año 2026'!$P$3:$P$66),"")} -> Prórroga | AP35: {=IFERROR(_xlfn.XLOOKUP(TRIM($E35),TRIM('Año 2026'!$E$3:$E$66),'Año 2026'!$Q$3:$Q$66),"")} -> 0 | AQ35: {=IFERROR(_xlfn.XLOOKUP(TRIM($E35),TRIM('Año 2026'!$E$3:$E$66),'Año 2026'!$R$3:$R$66),"")} -> 0 | AR35: {=IFERROR(_xlfn.XLOOKUP(TRIM($E35),TRIM('Año 2026'!$E$3:$E$66),'Año 2026'!$S$3:$S$66),"")} -> 0 | AS35: {=IFERROR(_xlfn.XLOOKUP(TRIM($E35),TRIM('Año 2026'!$E$3:$E$66),'Año 2026'!$T$3:$T$66),"")} -> 0 | AT35: {=IFERROR(_xlfn.XLOOKUP(TRIM($E35),TRIM('Año 2026'!$E$3:$E$66),'Año 2026'!$U$3:$U$66),"")} -> 0 | AU35: {=IFERROR(_xlfn.XLOOKUP(TRIM($E35),TRIM('Año 2026'!$E$3:$E$66),'Año 2026'!$V$3:$V$66),"")} -> 0 | AV35: {=IFERROR(_xlfn.XLOOKUP(TRIM($E35),TRIM('Año 2026'!$E$3:$E$66),'Año 2026'!$W$3:$W$66),"")} -> 0 | AW35: {=IFERROR(_xlfn.XLOOKUP(TRIM($E35),TRIM('Año 2026'!$E$3:$E$66),'Año 2026'!$X$3:$X$66),"")} -> 0 | AX35: {=IFERROR(_xlfn.XLOOKUP(TRIM($E35),TRIM('Año 2026'!$E$3:$E$66),'Año 2026'!$Y$3:$Y$66),"")} -> 0 | AY35: {=IFERROR(_xlfn.XLOOKUP(TRIM($E35),TRIM('Año 2026'!$E$3:$E$66),'Año 2026'!$Z$3:$Z$66),"")} -> 0 | AZ35: {=IFERROR(_xlfn.XLOOKUP(TRIM($E35),TRIM('Año 2026'!$E$3:$E$66),'Año 2026'!$AA$3:$AA$66),"")} -> 0 | BA35: {=IFERROR(_xlfn.XLOOKUP(TRIM($E35),TRIM('Año 2026'!$E$3:$E$66),'Año 2026'!$AB$3:$AB$66),"")} -> 0 | BB35: {=IFERROR(_xlfn.XLOOKUP(TRIM($E35),TRIM('Año 2026'!$E$3:$E$66),'Año 2026'!$AC$3:$AC$66),"")} -> Entregado | BC35: {=IFERROR(_xlfn.XLOOKUP(TRIM($E35),TRIM('Año 2026'!$E$3:$E$66),'Año 2026'!$AD$3:$AD$66),"")} -> No se atendió la prórroga
A36: 35 | B36: 2025 | C36: SNP | D36: MP | E36: 03299-2025-SUNEDU/02-13 (Vinculado 03188-2025-SUNEDU/02-13) | F36: En trámite | G36: 2025EXT0000065562-SUNEDU | H36: 16 | I36: Pública | J36: SL03, SL04 | K36: Junín | L36: Tarma | M36: Acobamba | N36: SL03: Ubic. Rur. Sector Huancucro, AcobambaTarma-Junín | SL04: Predio denominado Huancucro | Acobamba-Tarma-Junín | O36: MLI | P36: III | Q36: 19, 27, 28 | R36: Denuncia presentada por estudiantes de la Universidad Nacional Autónoma Altoandina de Tarma, trasladada por el Congreso de la República a la SUNEDU, referida a presuntos actos de acoso sexual por parte de docentes; presunta omisión de funciones por parte de funcionarios y autoridades universitarias, incluido el rector; presunta indiferencia institucional hacia los estudiantes de las carreras de Administración, Ingeniería Agroindustrial y Medicina Humana; la inexistencia de laboratorio para el programa de Medicina Humana; problemas en las vías de acceso al campus universitario y presuntas irregularidades vinculadas a una comisión universitaria. | S36: ALTA | T36: 1 | U36: Ingreso de Formato Único de Denuncia con fecha 11.12.25 | V36: 46002 | W36: El programa de Medicina Humana formó parte de la nueva oferta académica registrada; por lo que no se habría supervisado la implementación de su infraestructura. Estaría pendiente el requerimiento inicial de información. Lo vinculado a acoso sexual y lo de la comisión universitaria, estaría siendo atendido por el equipo de Estudiantes. | Y36: Se acumula con 03188-2025-SUNEDU/02-13 | AB36: SIN FECHA | AD36: EN PROCESO | AE36: Se recomienda acumular la atención al Expediente más antiguo al ser afines. Falta enviar carta | AF36: {=IFERROR(_xlfn.XLOOKUP(TRIM($E36),TRIM('Año 2026'!$E$3:$E$66),'Año 2026'!$G$3:$G$66),"")} | AG36: {=IFERROR(_xlfn.XLOOKUP(TRIM($E36),TRIM('Año 2026'!$E$3:$E$66),'Año 2026'!$H$3:$H$66),"")} | AH36: {=IFERROR(_xlfn.XLOOKUP(TRIM($E36),TRIM('Año 2026'!$E$3:$E$66),'Año 2026'!$I$3:$I$66),"")} | AI36: {=IFERROR(_xlfn.XLOOKUP(TRIM($E36),TRIM('Año 2026'!$E$3:$E$66),'Año 2026'!$J$3:$J$66),"")} | AJ36: {=IFERROR(_xlfn.XLOOKUP(TRIM($E36),TRIM('Año 2026'!$E$3:$E$66),'Año 2026'!$K$3:$K$66),"")} | AK36: {=IFERROR(_xlfn.XLOOKUP(TRIM($E36),TRIM('Año 2026'!$E$3:$E$66),'Año 2026'!$L$3:$L$66),"")} | AL36: {=IFERROR(_xlfn.XLOOKUP(TRIM($E36),TRIM('Año 2026'!$E$3:$E$66),'Año 2026'!$M$3:$M$66),"")} | AM36: {=IFERROR(_xlfn.XLOOKUP(TRIM($E36),TRIM('Año 2026'!$E$3:$E$66),'Año 2026'!$N$3:$N$66),"")} | AN36: {=IFERROR(_xlfn.XLOOKUP(TRIM($E36),TRIM('Año 2026'!$E$3:$E$66),'Año 2026'!$O$3:$O$66),"")} | AO36: {=IFERROR(_xlfn.XLOOKUP(TRIM($E36),TRIM('Año 2026'!$E$3:$E$66),'Año 2026'!$P$3:$P$66),"")} | AP36: {=IFERROR(_xlfn.XLOOKUP(TRIM($E36),TRIM('Año 2026'!$E$3:$E$66),'Año 2026'!$Q$3:$Q$66),"")} | AQ36: {=IFERROR(_xlfn.XLOOKUP(TRIM($E36),TRIM('Año 2026'!$E$3:$E$66),'Año 2026'!$R$3:$R$66),"")} | AR36: {=IFERROR(_xlfn.XLOOKUP(TRIM($E36),TRIM('Año 2026'!$E$3:$E$66),'Año 2026'!$S$3:$S$66),"")} | AS36: {=IFERROR(_xlfn.XLOOKUP(TRIM($E36),TRIM('Año 2026'!$E$3:$E$66),'Año 2026'!$T$3:$T$66),"")} | AT36: {=IFERROR(_xlfn.XLOOKUP(TRIM($E36),TRIM('Año 2026'!$E$3:$E$66),'Año 2026'!$U$3:$U$66),"")} | AU36: {=IFERROR(_xlfn.XLOOKUP(TRIM($E36),TRIM('Año 2026'!$E$3:$E$66),'Año 2026'!$V$3:$V$66),"")} | AV36: {=IFERROR(_xlfn.XLOOKUP(TRIM($E36),TRIM('Año 2026'!$E$3:$E$66),'Año 2026'!$W$3:$W$66),"")} | AW36: {=IFERROR(_xlfn.XLOOKUP(TRIM($E36),TRIM('Año 2026'!$E$3:$E$66),'Año 2026'!$X$3:$X$66),"")} | AX36: {=IFERROR(_xlfn.XLOOKUP(TRIM($E36),TRIM('Año 2026'!$E$3:$E$66),'Año 2026'!$Y$3:$Y$66),"")} | AY36: {=IFERROR(_xlfn.XLOOKUP(TRIM($E36),TRIM('Año 2026'!$E$3:$E$66),'Año 2026'!$Z$3:$Z$66),"")} | AZ36: {=IFERROR(_xlfn.XLOOKUP(TRIM($E36),TRIM('Año 2026'!$E$3:$E$66),'Año 2026'!$AA$3:$AA$66),"")} | BA36: {=IFERROR(_xlfn.XLOOKUP(TRIM($E36),TRIM('Año 2026'!$E$3:$E$66),'Año 2026'!$AB$3:$AB$66),"")} | BB36: {=IFERROR(_xlfn.XLOOKUP(TRIM($E36),TRIM('Año 2026'!$E$3:$E$66),'Año 2026'!$AC$3:$AC$66),"")} | BC36: {=IFERROR(_xlfn.XLOOKUP(TRIM($E36),TRIM('Año 2026'!$E$3:$E$66),'Año 2026'!$AD$3:$AD$66),"")}
A37: 36 | B37: 2025 | C37: Accion Directa | D37: Correo electrónico | E37: AD-042-2025 | F37: En trámite | H37: 26 | I37: Pública | J37: SL01, SL02 | K37: Puno | L37: San Roman | M37: SL01:Juliaca | SL02: San Miguel | N37: SL01: Jr. Manco Inca s/n | SL02: Predio rural UNAJ-02 y UNAJ-04 Sector Ayabaca | O37: MLI | P37: III, VI | Q37: 19, 24, 27, 30, 44, 50 | R37: Denuncia trasladada por la Comisión de Fiscalización y Contraloría del Congreso de la República, referida a presuntas deficiencias en la infraestructura y servicios del campus de la Universidad Nacional de Juliaca, consistentes en la falta de laboratorios, bibliotecas, servicio de internet y comedor universitario; presunta vulneración de derechos laborales de una docente gestante; presunta contratación de personal administrativo sin concurso público e irregularidades en el cumplimiento de la Ley N.º 32171. | S37: ALTA | T37: 1 | U37: Visita de Inspección del 02.12.25 al 05.12.25, con cierre de acta el 11.12.25 | V37: 46002 | W37: Pendiente recibir información, al 26 de enero aún están en plazo (prorrogado) | Y37: Pendiente programar reunión orientación ocupabilidad CBC III Carla La Torre Priorizada para ser cerrada en octubre 2026 | Z37: Sí | AA37: 46318 | AB37: =IF(AA37<TODAY(),"VENCIDO","POR VENCER") -> POR VENCER | AC37: 46325 | AD37: EN PROCESO | AE37: Informe y/o Requerimiento de información | AF37: {=IFERROR(_xlfn.XLOOKUP(TRIM($E37),TRIM('Año 2026'!$E$3:$E$66),'Año 2026'!$G$3:$G$66),"")} -> Oficio N° 04289-2025-SUNEDU-DS-DIRESESU-UVE | AG37: {=IFERROR(_xlfn.XLOOKUP(TRIM($E37),TRIM('Año 2026'!$E$3:$E$66),'Año 2026'!$H$3:$H$66),"")} -> 45957 | AH37: {=IFERROR(_xlfn.XLOOKUP(TRIM($E37),TRIM('Año 2026'!$E$3:$E$66),'Año 2026'!$I$3:$I$66),"")} -> 10 | AI37: {=IFERROR(_xlfn.XLOOKUP(TRIM($E37),TRIM('Año 2026'!$E$3:$E$66),'Año 2026'!$J$3:$J$66),"")} -> 45971 | AJ37: {=IFERROR(_xlfn.XLOOKUP(TRIM($E37),TRIM('Año 2026'!$E$3:$E$66),'Año 2026'!$K$3:$K$66),"")} -> -221 | AK37: {=IFERROR(_xlfn.XLOOKUP(TRIM($E37),TRIM('Año 2026'!$E$3:$E$66),'Año 2026'!$L$3:$L$66),"")} -> NUEVA FECHA | AL37: {=IFERROR(_xlfn.XLOOKUP(TRIM($E37),TRIM('Año 2026'!$E$3:$E$66),'Año 2026'!$M$3:$M$66),"")} -> NUEVA FECHA | AM37: {=IFERROR(_xlfn.XLOOKUP(TRIM($E37),TRIM('Año 2026'!$E$3:$E$66),'Año 2026'!$N$3:$N$66),"")} -> Ajustes al plazo | AN37: {=IFERROR(_xlfn.XLOOKUP(TRIM($E37),TRIM('Año 2026'!$E$3:$E$66),'Año 2026'!$O$3:$O$66),"")} -> 0 | AO37: {=IFERROR(_xlfn.XLOOKUP(TRIM($E37),TRIM('Año 2026'!$E$3:$E$66),'Año 2026'!$P$3:$P$66),"")} -> Prórroga | AP37: {=IFERROR(_xlfn.XLOOKUP(TRIM($E37),TRIM('Año 2026'!$E$3:$E$66),'Año 2026'!$Q$3:$Q$66),"")} -> 0 | AQ37: {=IFERROR(_xlfn.XLOOKUP(TRIM($E37),TRIM('Año 2026'!$E$3:$E$66),'Año 2026'!$R$3:$R$66),"")} -> 0 | AR37: {=IFERROR(_xlfn.XLOOKUP(TRIM($E37),TRIM('Año 2026'!$E$3:$E$66),'Año 2026'!$S$3:$S$66),"")} -> 0 | AS37: {=IFERROR(_xlfn.XLOOKUP(TRIM($E37),TRIM('Año 2026'!$E$3:$E$66),'Año 2026'!$T$3:$T$66),"")} -> 0 | AT37: {=IFERROR(_xlfn.XLOOKUP(TRIM($E37),TRIM('Año 2026'!$E$3:$E$66),'Año 2026'!$U$3:$U$66),"")} -> 0 | AU37: {=IFERROR(_xlfn.XLOOKUP(TRIM($E37),TRIM('Año 2026'!$E$3:$E$66),'Año 2026'!$V$3:$V$66),"")} -> 0012-2026-SUNEDU-DS-DIRESESU-UVE | AV37: {=IFERROR(_xlfn.XLOOKUP(TRIM($E37),TRIM('Año 2026'!$E$3:$E$66),'Año 2026'!$W$3:$W$66),"")} -> 46034 | AW37: {=IFERROR(_xlfn.XLOOKUP(TRIM($E37),TRIM('Año 2026'!$E$3:$E$66),'Año 2026'!$X$3:$X$66),"")} -> 10 | AX37: {=IFERROR(_xlfn.XLOOKUP(TRIM($E37),TRIM('Año 2026'!$E$3:$E$66),'Año 2026'!$Y$3:$Y$66),"")} | AY37: {=IFERROR(_xlfn.XLOOKUP(TRIM($E37),TRIM('Año 2026'!$E$3:$E$66),'Año 2026'!$Z$3:$Z$66),"")} | AZ37: {=IFERROR(_xlfn.XLOOKUP(TRIM($E37),TRIM('Año 2026'!$E$3:$E$66),'Año 2026'!$AA$3:$AA$66),"")} | BA37: {=IFERROR(_xlfn.XLOOKUP(TRIM($E37),TRIM('Año 2026'!$E$3:$E$66),'Año 2026'!$AB$3:$AB$66),"")} | BB37: {=IFERROR(_xlfn.XLOOKUP(TRIM($E37),TRIM('Año 2026'!$E$3:$E$66),'Año 2026'!$AC$3:$AC$66),"")} -> Entregado | BC37: {=IFERROR(_xlfn.XLOOKUP(TRIM($E37),TRIM('Año 2026'!$E$3:$E$66),'Año 2026'!$AD$3:$AD$66),"")} -> 0
A38: 37 | B38: 2025 | C38: Denuncia | D38: MP | E38: 03072-2025-SUNEDU/02-13 | F38: En trámite | G38: 2025EXT0000058737-SUNEDU | H38: 44 | I38: Pública | J38: SL01 | K38: Lima | L38: Barranca | M38: Barranca | N38: Avenida | Toribio Luzuriaga N° 376, Mz. J - Urbanización La Florida | O38: MLI | P38: I, III | Q38: 2, 27, 28 | R38: Denuncia presuntas irregularidades que estarían afectando la prestación del servicio educativo superior universitario, entre las que se mencionan: errores y omisiones en el plan curricular de la carrera de Ingeniería de Sistemas e Informática; falta de laboratorios y materiales de practica de física, electrónica, redes y de cómputo; así como la falta de talleres y eventos académicos especializados, entre otros. Programa de Ingeniería de Sistemas e Informatica vinculado a la denuncia, la misma que forma parte de los programas NOA 2023. | S38: MEDIA | T38: 2 | U38: Formato único de denuncia | V38: 45971 | W38: Una vez que llegue la información, comenzar con elaboración del informe. CASO IMPACTO | Y38: PLAN 2026/ 16 al 24 de marzo de 2026 (visita) Priorizada para ser cerrada en setiembre 2026. | Z38: Sí | AA38: 46283 | AB38: =IF(AA38<TODAY(),"VENCIDO","POR VENCER") -> POR VENCER | AC38: 46290 | AD38: EN PROCESO | AE38: Carta y/o Oficio | AF38: {=IFERROR(_xlfn.XLOOKUP(TRIM($E38),TRIM('Año 2026'!$E$3:$E$66),'Año 2026'!$G$3:$G$66),"")} -> OFICIO Nº 00954-2026-SUNEDU-DS-DIRESESU-UVE | AG38: {=IFERROR(_xlfn.XLOOKUP(TRIM($E38),TRIM('Año 2026'!$E$3:$E$66),'Año 2026'!$H$3:$H$66),"")} -> 46101 | AH38: {=IFERROR(_xlfn.XLOOKUP(TRIM($E38),TRIM('Año 2026'!$E$3:$E$66),'Año 2026'!$I$3:$I$66),"")} -> 5 | AI38: {=IFERROR(_xlfn.XLOOKUP(TRIM($E38),TRIM('Año 2026'!$E$3:$E$66),'Año 2026'!$J$3:$J$66),"")} -> 46108 | AJ38: {=IFERROR(_xlfn.XLOOKUP(TRIM($E38),TRIM('Año 2026'!$E$3:$E$66),'Año 2026'!$K$3:$K$66),"")} -> -84 | AK38: {=IFERROR(_xlfn.XLOOKUP(TRIM($E38),TRIM('Año 2026'!$E$3:$E$66),'Año 2026'!$L$3:$L$66),"")} -> NUEVA FECHA | AL38: {=IFERROR(_xlfn.XLOOKUP(TRIM($E38),TRIM('Año 2026'!$E$3:$E$66),'Año 2026'!$M$3:$M$66),"")} -> NUEVA FECHA | AM38: {=IFERROR(_xlfn.XLOOKUP(TRIM($E38),TRIM('Año 2026'!$E$3:$E$66),'Año 2026'!$N$3:$N$66),"")} -> Ajustes al plazo | AN38: {=IFERROR(_xlfn.XLOOKUP(TRIM($E38),TRIM('Año 2026'!$E$3:$E$66),'Año 2026'!$O$3:$O$66),"")} -> Plazo vencido - preguntar a susana | AO38: {=IFERROR(_xlfn.XLOOKUP(TRIM($E38),TRIM('Año 2026'!$E$3:$E$66),'Año 2026'!$P$3:$P$66),"")} -> 0 | AP38: {=IFERROR(_xlfn.XLOOKUP(TRIM($E38),TRIM('Año 2026'!$E$3:$E$66),'Año 2026'!$Q$3:$Q$66),"")} -> 0 | AQ38: {=IFERROR(_xlfn.XLOOKUP(TRIM($E38),TRIM('Año 2026'!$E$3:$E$66),'Año 2026'!$R$3:$R$66),"")} -> 0 | AR38: {=IFERROR(_xlfn.XLOOKUP(TRIM($E38),TRIM('Año 2026'!$E$3:$E$66),'Año 2026'!$S$3:$S$66),"")} -> 0 | AS38: {=IFERROR(_xlfn.XLOOKUP(TRIM($E38),TRIM('Año 2026'!$E$3:$E$66),'Año 2026'!$T$3:$T$66),"")} -> 0 | AT38: {=IFERROR(_xlfn.XLOOKUP(TRIM($E38),TRIM('Año 2026'!$E$3:$E$66),'Año 2026'!$U$3:$U$66),"")} -> 0 | AU38: {=IFERROR(_xlfn.XLOOKUP(TRIM($E38),TRIM('Año 2026'!$E$3:$E$66),'Año 2026'!$V$3:$V$66),"")} -> 0 | AV38: {=IFERROR(_xlfn.XLOOKUP(TRIM($E38),TRIM('Año 2026'!$E$3:$E$66),'Año 2026'!$W$3:$W$66),"")} -> 0 | AW38: {=IFERROR(_xlfn.XLOOKUP(TRIM($E38),TRIM('Año 2026'!$E$3:$E$66),'Año 2026'!$X$3:$X$66),"")} -> 0 | AX38: {=IFERROR(_xlfn.XLOOKUP(TRIM($E38),TRIM('Año 2026'!$E$3:$E$66),'Año 2026'!$Y$3:$Y$66),"")} -> 0 | AY38: {=IFERROR(_xlfn.XLOOKUP(TRIM($E38),TRIM('Año 2026'!$E$3:$E$66),'Año 2026'!$Z$3:$Z$66),"")} -> 0 | AZ38: {=IFERROR(_xlfn.XLOOKUP(TRIM($E38),TRIM('Año 2026'!$E$3:$E$66),'Año 2026'!$AA$3:$AA$66),"")} -> 0 | BA38: {=IFERROR(_xlfn.XLOOKUP(TRIM($E38),TRIM('Año 2026'!$E$3:$E$66),'Año 2026'!$AB$3:$AB$66),"")} -> 0 | BB38: {=IFERROR(_xlfn.XLOOKUP(TRIM($E38),TRIM('Año 2026'!$E$3:$E$66),'Año 2026'!$AC$3:$AC$66),"")} -> 0 | BC38: {=IFERROR(_xlfn.XLOOKUP(TRIM($E38),TRIM('Año 2026'!$E$3:$E$66),'Año 2026'!$AD$3:$AD$66),"")} -> 0
A39: 38 | B39: 2025 | C39: Accion Directa | D39: Correo electrónico | E39: AD-010-2025 | F39: En trámite | G39: 2025INT0000000421-SUNEDU | H39: 53 | I39: Pública | J39: SL01 | K39: Apurimac | L39: Abancay | M39: Tamburco | N39: Av. Inca Garcilaso de la Vega y la Panamericana Abancay – Cusco S/N | O39: MLI | P39: III, VI | Q39: 30, 44 | R39: El comedor universitario del local SL01 de la Universidad Nacional Micaela Bastidas de Apurímac podría estar brindando el servicio en condiciones inadecuadas. Esta situación podría implicar una afectación al mantenimiento de las CBC III y VI del Modelo de Licenciamiento. En nov 2025 remitió información solicitada. | S39: MEDIA | T39: 2 | U39: IR en word elaborado por Jenny | V39: 45684 | W39: Existe IR elaborado por Jenny, se encuentra a la espra de revsión y notificación | Y39: Falta revisar Informe elaborado | AB39: SIN FECHA | AD39: EN PROCESO | AE39: Informe y/o Requerimiento de información | AF39: {=IFERROR(_xlfn.XLOOKUP(TRIM($E39),TRIM('Año 2026'!$E$3:$E$66),'Año 2026'!$G$3:$G$66),"")} -> Oficio N° 00066-2025-SUNEDU-DS-DIRESESU-UVE | AG39: {=IFERROR(_xlfn.XLOOKUP(TRIM($E39),TRIM('Año 2026'!$E$3:$E$66),'Año 2026'!$H$3:$H$66),"")} -> 45672 | AH39: {=IFERROR(_xlfn.XLOOKUP(TRIM($E39),TRIM('Año 2026'!$E$3:$E$66),'Año 2026'!$I$3:$I$66),"")} -> 5 | AI39: {=IFERROR(_xlfn.XLOOKUP(TRIM($E39),TRIM('Año 2026'!$E$3:$E$66),'Año 2026'!$J$3:$J$66),"")} -> 45679 | AJ39: {=IFERROR(_xlfn.XLOOKUP(TRIM($E39),TRIM('Año 2026'!$E$3:$E$66),'Año 2026'!$K$3:$K$66),"")} -> -513 | AK39: {=IFERROR(_xlfn.XLOOKUP(TRIM($E39),TRIM('Año 2026'!$E$3:$E$66),'Año 2026'!$L$3:$L$66),"")} -> NUEVA FECHA | AL39: {=IFERROR(_xlfn.XLOOKUP(TRIM($E39),TRIM('Año 2026'!$E$3:$E$66),'Año 2026'!$M$3:$M$66),"")} -> NUEVA FECHA | AM39: {=IFERROR(_xlfn.XLOOKUP(TRIM($E39),TRIM('Año 2026'!$E$3:$E$66),'Año 2026'!$N$3:$N$66),"")} -> Ajustes al plazo | AN39: {=IFERROR(_xlfn.XLOOKUP(TRIM($E39),TRIM('Año 2026'!$E$3:$E$66),'Año 2026'!$O$3:$O$66),"")} -> 0 | AO39: {=IFERROR(_xlfn.XLOOKUP(TRIM($E39),TRIM('Año 2026'!$E$3:$E$66),'Año 2026'!$P$3:$P$66),"")} -> Prórroga | AP39: {=IFERROR(_xlfn.XLOOKUP(TRIM($E39),TRIM('Año 2026'!$E$3:$E$66),'Año 2026'!$Q$3:$Q$66),"")} -> 0 | AQ39: {=IFERROR(_xlfn.XLOOKUP(TRIM($E39),TRIM('Año 2026'!$E$3:$E$66),'Año 2026'!$R$3:$R$66),"")} -> 0 | AR39: {=IFERROR(_xlfn.XLOOKUP(TRIM($E39),TRIM('Año 2026'!$E$3:$E$66),'Año 2026'!$S$3:$S$66),"")} -> 0 | AS39: {=IFERROR(_xlfn.XLOOKUP(TRIM($E39),TRIM('Año 2026'!$E$3:$E$66),'Año 2026'!$T$3:$T$66),"")} -> 0 | AT39: {=IFERROR(_xlfn.XLOOKUP(TRIM($E39),TRIM('Año 2026'!$E$3:$E$66),'Año 2026'!$U$3:$U$66),"")} -> 0 | AU39: {=IFERROR(_xlfn.XLOOKUP(TRIM($E39),TRIM('Año 2026'!$E$3:$E$66),'Año 2026'!$V$3:$V$66),"")} -> Oficio N° 04500-2025-SUNEDU-DS-DIRESESU-UVE | AV39: {=IFERROR(_xlfn.XLOOKUP(TRIM($E39),TRIM('Año 2026'!$E$3:$E$66),'Año 2026'!$W$3:$W$66),"")} -> 45966 | AW39: {=IFERROR(_xlfn.XLOOKUP(TRIM($E39),TRIM('Año 2026'!$E$3:$E$66),'Año 2026'!$X$3:$X$66),"")} -> 3 | AX39: {=IFERROR(_xlfn.XLOOKUP(TRIM($E39),TRIM('Año 2026'!$E$3:$E$66),'Año 2026'!$Y$3:$Y$66),"")} | AY39: {=IFERROR(_xlfn.XLOOKUP(TRIM($E39),TRIM('Año 2026'!$E$3:$E$66),'Año 2026'!$Z$3:$Z$66),"")} | AZ39: {=IFERROR(_xlfn.XLOOKUP(TRIM($E39),TRIM('Año 2026'!$E$3:$E$66),'Año 2026'!$AA$3:$AA$66),"")} | BA39: {=IFERROR(_xlfn.XLOOKUP(TRIM($E39),TRIM('Año 2026'!$E$3:$E$66),'Año 2026'!$AB$3:$AB$66),"")} | BB39: {=IFERROR(_xlfn.XLOOKUP(TRIM($E39),TRIM('Año 2026'!$E$3:$E$66),'Año 2026'!$AC$3:$AC$66),"")} -> Entregado | BC39: {=IFERROR(_xlfn.XLOOKUP(TRIM($E39),TRIM('Año 2026'!$E$3:$E$66),'Año 2026'!$AD$3:$AD$66),"")} -> 0
A40: 39 | B40: 2025 | C40: SNP | D40: No programada - oficio | E40: 01445-2025-SUNEDU/02-13 | F40: En trámite | G40: 2025EXT0000006933-SUNEDU | H40: 36 | I40: Pública | J40: SL01 | K40: Cajamarca | L40: Cajamarca | M40: Cajamarca | N40: Av. Atahualpa 1050 | O40: MLI | P40: IV | Q40: 34 | R40: El programa Medicina Veterinaria (P21) de la Facultad de Ciencias Veterinarias de la Universidad habría permitido el uso arbitrario de canes protegidos por la Ley N° 30407, Ley de Protección y Bienestar Animal. Se vincula con el mantenimiento de la CBC IV, indicador 34 del Modelo de Licenciamiento. | S40: BAJA | T40: 2 | U40: La Universidad remitió información en jun2025. Se cuenta con 1 IR elaborado pendiente de revisión final. | V40: 45832 | W40: Se tiene un IR preliminar elaborado por Cristina Anaya, pendiente de revisión final. La AD-014-2025 escaló a SNP. | Y40: Falta revisar Informe preliminar elaborado Falta programar | AB40: SIN FECHA | AD40: EN PROCESO | AE40: Informe de Resultados | AF40: {=IFERROR(_xlfn.XLOOKUP(TRIM($E40),TRIM('Año 2026'!$E$3:$E$66),'Año 2026'!$G$3:$G$66),"")} -> Oficio N° 01747-2025-SUNEDU-DS-DIRESESU-UVE (27.05.25) | AG40: {=IFERROR(_xlfn.XLOOKUP(TRIM($E40),TRIM('Año 2026'!$E$3:$E$66),'Año 2026'!$H$3:$H$66),"")} -> 45805 | AH40: {=IFERROR(_xlfn.XLOOKUP(TRIM($E40),TRIM('Año 2026'!$E$3:$E$66),'Año 2026'!$I$3:$I$66),"")} -> 5 | AI40: {=IFERROR(_xlfn.XLOOKUP(TRIM($E40),TRIM('Año 2026'!$E$3:$E$66),'Año 2026'!$J$3:$J$66),"")} -> 45812 | AJ40: {=IFERROR(_xlfn.XLOOKUP(TRIM($E40),TRIM('Año 2026'!$E$3:$E$66),'Año 2026'!$K$3:$K$66),"")} -> -380 | AK40: {=IFERROR(_xlfn.XLOOKUP(TRIM($E40),TRIM('Año 2026'!$E$3:$E$66),'Año 2026'!$L$3:$L$66),"")} -> NUEVA FECHA | AL40: {=IFERROR(_xlfn.XLOOKUP(TRIM($E40),TRIM('Año 2026'!$E$3:$E$66),'Año 2026'!$M$3:$M$66),"")} -> NUEVA FECHA | AM40: {=IFERROR(_xlfn.XLOOKUP(TRIM($E40),TRIM('Año 2026'!$E$3:$E$66),'Año 2026'!$N$3:$N$66),"")} -> Ajustes al plazo | AN40: {=IFERROR(_xlfn.XLOOKUP(TRIM($E40),TRIM('Año 2026'!$E$3:$E$66),'Año 2026'!$O$3:$O$66),"")} -> 0 | AO40: {=IFERROR(_xlfn.XLOOKUP(TRIM($E40),TRIM('Año 2026'!$E$3:$E$66),'Año 2026'!$P$3:$P$66),"")} -> Requerimiento complementario | AP40: {=IFERROR(_xlfn.XLOOKUP(TRIM($E40),TRIM('Año 2026'!$E$3:$E$66),'Año 2026'!$Q$3:$Q$66),"")} -> 0 | AQ40: {=IFERROR(_xlfn.XLOOKUP(TRIM($E40),TRIM('Año 2026'!$E$3:$E$66),'Año 2026'!$R$3:$R$66),"")} -> 0 | AR40: {=IFERROR(_xlfn.XLOOKUP(TRIM($E40),TRIM('Año 2026'!$E$3:$E$66),'Año 2026'!$S$3:$S$66),"")} -> 0 | AS40: {=IFERROR(_xlfn.XLOOKUP(TRIM($E40),TRIM('Año 2026'!$E$3:$E$66),'Año 2026'!$T$3:$T$66),"")} -> 0 | AT40: {=IFERROR(_xlfn.XLOOKUP(TRIM($E40),TRIM('Año 2026'!$E$3:$E$66),'Año 2026'!$U$3:$U$66),"")} -> 0 | AU40: {=IFERROR(_xlfn.XLOOKUP(TRIM($E40),TRIM('Año 2026'!$E$3:$E$66),'Año 2026'!$V$3:$V$66),"")} -> Oficio N° 01813-2026-SUNEDU-DS-DIRESESU-UVE | AV40: {=IFERROR(_xlfn.XLOOKUP(TRIM($E40),TRIM('Año 2026'!$E$3:$E$66),'Año 2026'!$W$3:$W$66),"")} -> 46147 | AW40: {=IFERROR(_xlfn.XLOOKUP(TRIM($E40),TRIM('Año 2026'!$E$3:$E$66),'Año 2026'!$X$3:$X$66),"")} -> 5 | AX40: {=IFERROR(_xlfn.XLOOKUP(TRIM($E40),TRIM('Año 2026'!$E$3:$E$66),'Año 2026'!$Y$3:$Y$66),"")} | AY40: {=IFERROR(_xlfn.XLOOKUP(TRIM($E40),TRIM('Año 2026'!$E$3:$E$66),'Año 2026'!$Z$3:$Z$66),"")} | AZ40: {=IFERROR(_xlfn.XLOOKUP(TRIM($E40),TRIM('Año 2026'!$E$3:$E$66),'Año 2026'!$AA$3:$AA$66),"")} | BA40: {=IFERROR(_xlfn.XLOOKUP(TRIM($E40),TRIM('Año 2026'!$E$3:$E$66),'Año 2026'!$AB$3:$AB$66),"")} | BB40: {=IFERROR(_xlfn.XLOOKUP(TRIM($E40),TRIM('Año 2026'!$E$3:$E$66),'Año 2026'!$AC$3:$AC$66),"")} -> Entregado | BC40: {=IFERROR(_xlfn.XLOOKUP(TRIM($E40),TRIM('Año 2026'!$E$3:$E$66),'Año 2026'!$AD$3:$AD$66),"")} -> 0
A41: 40 | B41: 2025 | C41: Accion Directa | D41: MP | E41: AD-003-2026 | F41: En trámite | G41: 2025EXT0000062967-SUNEDU | H41: 26 | I41: Pública | J41: SL01 | K41: Puno | L41: San Roman | M41: Juliaca | N41: Jr. Manco lnca S/N, esquina Jr. Manco lnca con Jr. lntiraymi | O41: MLI | P41: VI | Q41: 44 | R41: Denuncia vinculada a deficiencias en el servicio de alimentación del comedor universitario de la Universidad Nacional de Juliaca, identificadas a partir de una vigilancia sanitaria realizada por DIGESA, en la que se evidenció la ausencia de certificación de Principios Generales de Higiene, la falta de manuales de Buenas Prácticas de Manufactura y de Procedimientos Higiénico-Sanitarios, la presencia de tanques elevados con suciedad y excretas de aves, ventanas abiertas sin protección en el área de preparación de alimentos, deficiencias en el control y almacenamiento de insumos, y ausencia de registros sanitarios obligatorios. Inicialmente ingresó con Denuncia, pero fue modificada a AD. | S41: MEDIA | T41: 1 | U41: Ingreso de Formato Único de Denuncia con fecha 02.12.25 | V41: 45993 | W41: Sugiero iniciar con un requerimiento de información inicial, ya que no se realizado ninguna acción. Estaría pendiente el requerimiento inicial de información. | Y41: Pendiente visita del 02.03.26 al 04.03.26 por Pablo Arróspide + Renzo Lima OS CBC VI Geraldine Rojas (Marzo-26) Priorizada para ser cerrada en abril 2026. (RL) | Z41: Sí | AA41: 46159 | AB41: =IF(AA41<TODAY(),"VENCIDO","POR VENCER") -> VENCIDO | AC41: 46166 | AD41: EN PROCESO | AE41: Informe y/o Requerimiento de información | AF41: {=IFERROR(_xlfn.XLOOKUP(TRIM($E41),TRIM('Año 2026'!$E$3:$E$66),'Año 2026'!$G$3:$G$66),"")} -> Oficio N° 00457-2026-SUNEDU-DS-DIRESESU-UVE | AG41: {=IFERROR(_xlfn.XLOOKUP(TRIM($E41),TRIM('Año 2026'!$E$3:$E$66),'Año 2026'!$H$3:$H$66),"")} -> 46057 | AH41: {=IFERROR(_xlfn.XLOOKUP(TRIM($E41),TRIM('Año 2026'!$E$3:$E$66),'Año 2026'!$I$3:$I$66),"")} -> 2 | AI41: {=IFERROR(_xlfn.XLOOKUP(TRIM($E41),TRIM('Año 2026'!$E$3:$E$66),'Año 2026'!$J$3:$J$66),"")} -> 46059 | AJ41: {=IFERROR(_xlfn.XLOOKUP(TRIM($E41),TRIM('Año 2026'!$E$3:$E$66),'Año 2026'!$K$3:$K$66),"")} -> -133 | AK41: {=IFERROR(_xlfn.XLOOKUP(TRIM($E41),TRIM('Año 2026'!$E$3:$E$66),'Año 2026'!$L$3:$L$66),"")} -> NUEVA FECHA | AL41: {=IFERROR(_xlfn.XLOOKUP(TRIM($E41),TRIM('Año 2026'!$E$3:$E$66),'Año 2026'!$M$3:$M$66),"")} -> NUEVA FECHA | AM41: {=IFERROR(_xlfn.XLOOKUP(TRIM($E41),TRIM('Año 2026'!$E$3:$E$66),'Año 2026'!$N$3:$N$66),"")} -> Ajustes al plazo | AN41: {=IFERROR(_xlfn.XLOOKUP(TRIM($E41),TRIM('Año 2026'!$E$3:$E$66),'Año 2026'!$O$3:$O$66),"")} -> 0 | AO41: {=IFERROR(_xlfn.XLOOKUP(TRIM($E41),TRIM('Año 2026'!$E$3:$E$66),'Año 2026'!$P$3:$P$66),"")} -> Prórroga | AP41: {=IFERROR(_xlfn.XLOOKUP(TRIM($E41),TRIM('Año 2026'!$E$3:$E$66),'Año 2026'!$Q$3:$Q$66),"")} -> 0 | AQ41: {=IFERROR(_xlfn.XLOOKUP(TRIM($E41),TRIM('Año 2026'!$E$3:$E$66),'Año 2026'!$R$3:$R$66),"")} -> 0 | AR41: {=IFERROR(_xlfn.XLOOKUP(TRIM($E41),TRIM('Año 2026'!$E$3:$E$66),'Año 2026'!$S$3:$S$66),"")} -> 0 | AS41: {=IFERROR(_xlfn.XLOOKUP(TRIM($E41),TRIM('Año 2026'!$E$3:$E$66),'Año 2026'!$T$3:$T$66),"")} -> 0 | AT41: {=IFERROR(_xlfn.XLOOKUP(TRIM($E41),TRIM('Año 2026'!$E$3:$E$66),'Año 2026'!$U$3:$U$66),"")} -> 0 | AU41: {=IFERROR(_xlfn.XLOOKUP(TRIM($E41),TRIM('Año 2026'!$E$3:$E$66),'Año 2026'!$V$3:$V$66),"")} -> Oficio N° 00831-2026-SUNEDU-DS-DIRESESU-UVE | AV41: {=IFERROR(_xlfn.XLOOKUP(TRIM($E41),TRIM('Año 2026'!$E$3:$E$66),'Año 2026'!$W$3:$W$66),"")} -> 46092 | AW41: {=IFERROR(_xlfn.XLOOKUP(TRIM($E41),TRIM('Año 2026'!$E$3:$E$66),'Año 2026'!$X$3:$X$66),"")} -> 5 | AX41: {=IFERROR(_xlfn.XLOOKUP(TRIM($E41),TRIM('Año 2026'!$E$3:$E$66),'Año 2026'!$Y$3:$Y$66),"")} | AY41: {=IFERROR(_xlfn.XLOOKUP(TRIM($E41),TRIM('Año 2026'!$E$3:$E$66),'Año 2026'!$Z$3:$Z$66),"")} | AZ41: {=IFERROR(_xlfn.XLOOKUP(TRIM($E41),TRIM('Año 2026'!$E$3:$E$66),'Año 2026'!$AA$3:$AA$66),"")} | BA41: {=IFERROR(_xlfn.XLOOKUP(TRIM($E41),TRIM('Año 2026'!$E$3:$E$66),'Año 2026'!$AB$3:$AB$66),"")} | BB41: {=IFERROR(_xlfn.XLOOKUP(TRIM($E41),TRIM('Año 2026'!$E$3:$E$66),'Año 2026'!$AC$3:$AC$66),"")} -> Entregado | BC41: {=IFERROR(_xlfn.XLOOKUP(TRIM($E41),TRIM('Año 2026'!$E$3:$E$66),'Año 2026'!$AD$3:$AD$66),"")} -> 0
A42: 41 | B42: 2025 | C42: Denuncia | D42: MP | E42: 03299-2025-SUNEDU/02-13 (Vinculado 03188-2025-SUNEDU/02-13) | F42: En trámite | G42: 2025EXT0000065562-SUNEDU | H42: 16 | I42: Pública | J42: SL03, SL04 | K42: Junín | L42: Tarma | M42: Acobamba | N42: SL03: Ubic. Rur. Sector Huancucro, AcobambaTarma-Junín | SL04: Predio denominado Huancucro | Acobamba-Tarma-Junín | O42: MLI | P42: III | Q42: 19, 27, 28 | R42: Denuncian que la universidad no tendrian un laboratorio de medicina humana y muchas otras cuestiones más. | S42: ALTA | T42: 1 | U42: Ingreso de Formato Único de Denuncia con fecha 11.12.25 | V42: 46002 | W42: El programa de Medicina Humana formó parte de la nueva oferta académica registrada; por lo que no se habría supervisado la implementación de su infraestructura. Estaría pendiente el requerimiento inicial de información. Lo vinculado a acoso sexual y lo de la comisión universitaria, estaría siendo atendido por el equipo de Estudiantes. | Y42: Se acumula con 03188-2025-SUNEDU/02-13 | AB42: SIN FECHA | AD42: EN PROCESO | AE42: Por estatégia no se cierra esta denuncia. | AF42: {=IFERROR(_xlfn.XLOOKUP(TRIM($E42),TRIM('Año 2026'!$E$3:$E$66),'Año 2026'!$G$3:$G$66),"")} | AG42: {=IFERROR(_xlfn.XLOOKUP(TRIM($E42),TRIM('Año 2026'!$E$3:$E$66),'Año 2026'!$H$3:$H$66),"")} | AH42: {=IFERROR(_xlfn.XLOOKUP(TRIM($E42),TRIM('Año 2026'!$E$3:$E$66),'Año 2026'!$I$3:$I$66),"")} | AI42: {=IFERROR(_xlfn.XLOOKUP(TRIM($E42),TRIM('Año 2026'!$E$3:$E$66),'Año 2026'!$J$3:$J$66),"")} | AJ42: {=IFERROR(_xlfn.XLOOKUP(TRIM($E42),TRIM('Año 2026'!$E$3:$E$66),'Año 2026'!$K$3:$K$66),"")} | AK42: {=IFERROR(_xlfn.XLOOKUP(TRIM($E42),TRIM('Año 2026'!$E$3:$E$66),'Año 2026'!$L$3:$L$66),"")} | AL42: {=IFERROR(_xlfn.XLOOKUP(TRIM($E42),TRIM('Año 2026'!$E$3:$E$66),'Año 2026'!$M$3:$M$66),"")} | AM42: {=IFERROR(_xlfn.XLOOKUP(TRIM($E42),TRIM('Año 2026'!$E$3:$E$66),'Año 2026'!$N$3:$N$66),"")} | AN42: {=IFERROR(_xlfn.XLOOKUP(TRIM($E42),TRIM('Año 2026'!$E$3:$E$66),'Año 2026'!$O$3:$O$66),"")} | AO42: {=IFERROR(_xlfn.XLOOKUP(TRIM($E42),TRIM('Año 2026'!$E$3:$E$66),'Año 2026'!$P$3:$P$66),"")} | AP42: {=IFERROR(_xlfn.XLOOKUP(TRIM($E42),TRIM('Año 2026'!$E$3:$E$66),'Año 2026'!$Q$3:$Q$66),"")} | AQ42: {=IFERROR(_xlfn.XLOOKUP(TRIM($E42),TRIM('Año 2026'!$E$3:$E$66),'Año 2026'!$R$3:$R$66),"")} | AR42: {=IFERROR(_xlfn.XLOOKUP(TRIM($E42),TRIM('Año 2026'!$E$3:$E$66),'Año 2026'!$S$3:$S$66),"")} | AS42: {=IFERROR(_xlfn.XLOOKUP(TRIM($E42),TRIM('Año 2026'!$E$3:$E$66),'Año 2026'!$T$3:$T$66),"")} | AT42: {=IFERROR(_xlfn.XLOOKUP(TRIM($E42),TRIM('Año 2026'!$E$3:$E$66),'Año 2026'!$U$3:$U$66),"")} | AU42: {=IFERROR(_xlfn.XLOOKUP(TRIM($E42),TRIM('Año 2026'!$E$3:$E$66),'Año 2026'!$V$3:$V$66),"")} | AV42: {=IFERROR(_xlfn.XLOOKUP(TRIM($E42),TRIM('Año 2026'!$E$3:$E$66),'Año 2026'!$W$3:$W$66),"")} | AW42: {=IFERROR(_xlfn.XLOOKUP(TRIM($E42),TRIM('Año 2026'!$E$3:$E$66),'Año 2026'!$X$3:$X$66),"")} | AX42: {=IFERROR(_xlfn.XLOOKUP(TRIM($E42),TRIM('Año 2026'!$E$3:$E$66),'Año 2026'!$Y$3:$Y$66),"")} | AY42: {=IFERROR(_xlfn.XLOOKUP(TRIM($E42),TRIM('Año 2026'!$E$3:$E$66),'Año 2026'!$Z$3:$Z$66),"")} | AZ42: {=IFERROR(_xlfn.XLOOKUP(TRIM($E42),TRIM('Año 2026'!$E$3:$E$66),'Año 2026'!$AA$3:$AA$66),"")} | BA42: {=IFERROR(_xlfn.XLOOKUP(TRIM($E42),TRIM('Año 2026'!$E$3:$E$66),'Año 2026'!$AB$3:$AB$66),"")} | BB42: {=IFERROR(_xlfn.XLOOKUP(TRIM($E42),TRIM('Año 2026'!$E$3:$E$66),'Año 2026'!$AC$3:$AC$66),"")} | BC42: {=IFERROR(_xlfn.XLOOKUP(TRIM($E42),TRIM('Año 2026'!$E$3:$E$66),'Año 2026'!$AD$3:$AD$66),"")}
A43: 42 | B43: 2025 | C43: Denuncia | D43: Web | E43: 01020-2025-SUNEDU/02-13 | F43: En trámite | G43: 2025EXT0000021715-SUNEDU | H43: 41 | I43: Pública | J43: SL02 | K43: La Libertad | L43: Sanchez Carrion | M43: Huamachuco | N43: Jr. Garcilaso de la Vega N° 905 | O43: MLI | P43: III | Q43: 19, 27 | R43: Hace de conocimiento que el laboratorio de biología no contaría con el espacio adecuado para la realización de las clases prácticas; además, en su oficina administrativa estaría funcionando el centro preuniversitario. Solo presentó imágenes fotograficas del laboratorio de Biología foto 1 (Materiales que se encontraban en armario de la oficina administrativa se encuentra en las mesas de prácticas del Laboratorio de Biología, ubicación de la asistente de laboratorio con sus bienes escritorio y armario que se encontraba en la oficina administrativa ahora se encuentra en el Laboratorio de Biología. | S43: ALTA | T43: 2 | U43: Se inicia indagación preliminar mediante el OFICIO N° 03963-2025-SUNEDU-DS-DIRESESU-UVE | V43: 45931 | W43: Ademas se le prorroga plazo para entrega de información requerida en la visita de inspección, de acuerdo al Acta de Supervisión suscrita el 18 de setiembre de 2025. La Universidad envia información mediante el Oficio N° 0498-2025-UNCA/P-CO ( ver item anterior) FALTA EN Z Se cuenta con IR elaborado por Manuel | X43: MANUEL HURTADO | Y43: OS Antecedentes Barzen (Feb-26) CBC III Manuel Hurtado (Feb-26) Priorizada para ser cerrada en julio 2026. (Rev. RL) | Z43: Sí | AA43: 46227 | AB43: =IF(AA43<TODAY(),"VENCIDO","POR VENCER") -> POR VENCER | AC43: 46234 | AD43: EN PROCESO | AE43: Carta y/o Oficio | AF43: {=IFERROR(_xlfn.XLOOKUP(TRIM($E43),TRIM('Año 2026'!$E$3:$E$66),'Año 2026'!$G$3:$G$66),"")} -> Oficio N° 03497-2025-SUNEDU-DS-DIRESESU-UVE (08.09.25) | AG43: {=IFERROR(_xlfn.XLOOKUP(TRIM($E43),TRIM('Año 2026'!$E$3:$E$66),'Año 2026'!$H$3:$H$66),"")} -> 45909 | AH43: {=IFERROR(_xlfn.XLOOKUP(TRIM($E43),TRIM('Año 2026'!$E$3:$E$66),'Año 2026'!$I$3:$I$66),"")} -> 2 | AI43: {=IFERROR(_xlfn.XLOOKUP(TRIM($E43),TRIM('Año 2026'!$E$3:$E$66),'Año 2026'!$J$3:$J$66),"")} -> 45911 | AJ43: {=IFERROR(_xlfn.XLOOKUP(TRIM($E43),TRIM('Año 2026'!$E$3:$E$66),'Año 2026'!$K$3:$K$66),"")} -> -281 | AK43: {=IFERROR(_xlfn.XLOOKUP(TRIM($E43),TRIM('Año 2026'!$E$3:$E$66),'Año 2026'!$L$3:$L$66),"")} -> NUEVA FECHA | AL43: {=IFERROR(_xlfn.XLOOKUP(TRIM($E43),TRIM('Año 2026'!$E$3:$E$66),'Año 2026'!$M$3:$M$66),"")} -> NUEVA FECHA | AM43: {=IFERROR(_xlfn.XLOOKUP(TRIM($E43),TRIM('Año 2026'!$E$3:$E$66),'Año 2026'!$N$3:$N$66),"")} -> Ajustes al plazo | AN43: {=IFERROR(_xlfn.XLOOKUP(TRIM($E43),TRIM('Año 2026'!$E$3:$E$66),'Año 2026'!$O$3:$O$66),"")} -> 0 | AO43: {=IFERROR(_xlfn.XLOOKUP(TRIM($E43),TRIM('Año 2026'!$E$3:$E$66),'Año 2026'!$P$3:$P$66),"")} -> Prórroga | AP43: {=IFERROR(_xlfn.XLOOKUP(TRIM($E43),TRIM('Año 2026'!$E$3:$E$66),'Año 2026'!$Q$3:$Q$66),"")} -> 0 | AQ43: {=IFERROR(_xlfn.XLOOKUP(TRIM($E43),TRIM('Año 2026'!$E$3:$E$66),'Año 2026'!$R$3:$R$66),"")} -> 0 | AR43: {=IFERROR(_xlfn.XLOOKUP(TRIM($E43),TRIM('Año 2026'!$E$3:$E$66),'Año 2026'!$S$3:$S$66),"")} -> 0 | AS43: {=IFERROR(_xlfn.XLOOKUP(TRIM($E43),TRIM('Año 2026'!$E$3:$E$66),'Año 2026'!$T$3:$T$66),"")} -> 0 | AT43: {=IFERROR(_xlfn.XLOOKUP(TRIM($E43),TRIM('Año 2026'!$E$3:$E$66),'Año 2026'!$U$3:$U$66),"")} -> 0 | AU43: {=IFERROR(_xlfn.XLOOKUP(TRIM($E43),TRIM('Año 2026'!$E$3:$E$66),'Año 2026'!$V$3:$V$66),"")} -> Oficio N° 03963-2025-SUNEDU-DS-DIRESESU-UVE | AV43: {=IFERROR(_xlfn.XLOOKUP(TRIM($E43),TRIM('Año 2026'!$E$3:$E$66),'Año 2026'!$W$3:$W$66),"")} -> 45932 | AW43: {=IFERROR(_xlfn.XLOOKUP(TRIM($E43),TRIM('Año 2026'!$E$3:$E$66),'Año 2026'!$X$3:$X$66),"")} -> 3 | AX43: {=IFERROR(_xlfn.XLOOKUP(TRIM($E43),TRIM('Año 2026'!$E$3:$E$66),'Año 2026'!$Y$3:$Y$66),"")} | AY43: {=IFERROR(_xlfn.XLOOKUP(TRIM($E43),TRIM('Año 2026'!$E$3:$E$66),'Año 2026'!$Z$3:$Z$66),"")} | AZ43: {=IFERROR(_xlfn.XLOOKUP(TRIM($E43),TRIM('Año 2026'!$E$3:$E$66),'Año 2026'!$AA$3:$AA$66),"")} | BA43: {=IFERROR(_xlfn.XLOOKUP(TRIM($E43),TRIM('Año 2026'!$E$3:$E$66),'Año 2026'!$AB$3:$AB$66),"")} | BB43: {=IFERROR(_xlfn.XLOOKUP(TRIM($E43),TRIM('Año 2026'!$E$3:$E$66),'Año 2026'!$AC$3:$AC$66),"")} -> Entregado | BC43: {=IFERROR(_xlfn.XLOOKUP(TRIM($E43),TRIM('Año 2026'!$E$3:$E$66),'Año 2026'!$AD$3:$AD$66),"")} -> 0
A44: 43 | B44: 2025 | C44: Denuncia | D44: Web | E44: 01186-2025-SUNEDU/02-13 | F44: En trámite | G44: 2025EXT0000021720-SUNEDU | H44: 41 | I44: Pública | J44: SL02 | K44: La Libertad | L44: Sanchez Carrion | M44: Huamachuco | N44: Jr. Garcilaso de la Vega N° 905 | O44: MLI | P44: III | Q44: 19 | R44: Idem al anterior EXP 2025EXT0000021715-SUNEDU | S44: ALTA | T44: 2 | U44: Denuncia recibida | W44: FALTA EN Z varios documentos, el OFICIO N° 03497-2025-SUNEDU-DS-DIRESESU-UVE, el OFICIO N° 03963-2025-SUNEDU-DS-DIRESESU-UVE, el Oficio N° 0498-2025-UNCA/P-CO (entrega de información) Se cuenta con IR elaborado por Manuel | X44: MANUEL HURTADO | Y44: OS Antecedentes Barzen (Feb-26) CBC III Manuel Hurtado (Feb-26) Priorizada para ser cerrada en julio 2026. (Rev. RL) | Z44: Sí | AA44: 46227 | AB44: =IF(AA44<TODAY(),"VENCIDO","POR VENCER") -> POR VENCER | AC44: 46234 | AD44: EN PROCESO | AF44: {=IFERROR(_xlfn.XLOOKUP(TRIM($E44),TRIM('Año 2026'!$E$3:$E$66),'Año 2026'!$G$3:$G$66),"")} -> Oficio N° 03497-2025-SUNEDU-DS-DIRESESU-UVE (08.09.25) | AG44: {=IFERROR(_xlfn.XLOOKUP(TRIM($E44),TRIM('Año 2026'!$E$3:$E$66),'Año 2026'!$H$3:$H$66),"")} -> 45909 | AH44: {=IFERROR(_xlfn.XLOOKUP(TRIM($E44),TRIM('Año 2026'!$E$3:$E$66),'Año 2026'!$I$3:$I$66),"")} -> 2 | AI44: {=IFERROR(_xlfn.XLOOKUP(TRIM($E44),TRIM('Año 2026'!$E$3:$E$66),'Año 2026'!$J$3:$J$66),"")} -> 45911 | AJ44: {=IFERROR(_xlfn.XLOOKUP(TRIM($E44),TRIM('Año 2026'!$E$3:$E$66),'Año 2026'!$K$3:$K$66),"")} -> -281 | AK44: {=IFERROR(_xlfn.XLOOKUP(TRIM($E44),TRIM('Año 2026'!$E$3:$E$66),'Año 2026'!$L$3:$L$66),"")} -> NUEVA FECHA | AL44: {=IFERROR(_xlfn.XLOOKUP(TRIM($E44),TRIM('Año 2026'!$E$3:$E$66),'Año 2026'!$M$3:$M$66),"")} -> NUEVA FECHA | AM44: {=IFERROR(_xlfn.XLOOKUP(TRIM($E44),TRIM('Año 2026'!$E$3:$E$66),'Año 2026'!$N$3:$N$66),"")} -> Ajustes al plazo | AN44: {=IFERROR(_xlfn.XLOOKUP(TRIM($E44),TRIM('Año 2026'!$E$3:$E$66),'Año 2026'!$O$3:$O$66),"")} -> 0 | AO44: {=IFERROR(_xlfn.XLOOKUP(TRIM($E44),TRIM('Año 2026'!$E$3:$E$66),'Año 2026'!$P$3:$P$66),"")} -> Prórroga | AP44: {=IFERROR(_xlfn.XLOOKUP(TRIM($E44),TRIM('Año 2026'!$E$3:$E$66),'Año 2026'!$Q$3:$Q$66),"")} -> 0 | AQ44: {=IFERROR(_xlfn.XLOOKUP(TRIM($E44),TRIM('Año 2026'!$E$3:$E$66),'Año 2026'!$R$3:$R$66),"")} -> 0 | AR44: {=IFERROR(_xlfn.XLOOKUP(TRIM($E44),TRIM('Año 2026'!$E$3:$E$66),'Año 2026'!$S$3:$S$66),"")} -> 0 | AS44: {=IFERROR(_xlfn.XLOOKUP(TRIM($E44),TRIM('Año 2026'!$E$3:$E$66),'Año 2026'!$T$3:$T$66),"")} -> 0 | AT44: {=IFERROR(_xlfn.XLOOKUP(TRIM($E44),TRIM('Año 2026'!$E$3:$E$66),'Año 2026'!$U$3:$U$66),"")} -> 0 | AU44: {=IFERROR(_xlfn.XLOOKUP(TRIM($E44),TRIM('Año 2026'!$E$3:$E$66),'Año 2026'!$V$3:$V$66),"")} -> Oficio N° 03963-2025-SUNEDU-DS-DIRESESU-UVE | AV44: {=IFERROR(_xlfn.XLOOKUP(TRIM($E44),TRIM('Año 2026'!$E$3:$E$66),'Año 2026'!$W$3:$W$66),"")} -> 45932 | AW44: {=IFERROR(_xlfn.XLOOKUP(TRIM($E44),TRIM('Año 2026'!$E$3:$E$66),'Año 2026'!$X$3:$X$66),"")} -> 3 | AX44: {=IFERROR(_xlfn.XLOOKUP(TRIM($E44),TRIM('Año 2026'!$E$3:$E$66),'Año 2026'!$Y$3:$Y$66),"")} | AY44: {=IFERROR(_xlfn.XLOOKUP(TRIM($E44),TRIM('Año 2026'!$E$3:$E$66),'Año 2026'!$Z$3:$Z$66),"")} | AZ44: {=IFERROR(_xlfn.XLOOKUP(TRIM($E44),TRIM('Año 2026'!$E$3:$E$66),'Año 2026'!$AA$3:$AA$66),"")} | BA44: {=IFERROR(_xlfn.XLOOKUP(TRIM($E44),TRIM('Año 2026'!$E$3:$E$66),'Año 2026'!$AB$3:$AB$66),"")} | BB44: {=IFERROR(_xlfn.XLOOKUP(TRIM($E44),TRIM('Año 2026'!$E$3:$E$66),'Año 2026'!$AC$3:$AC$66),"")} -> Entregado | BC44: {=IFERROR(_xlfn.XLOOKUP(TRIM($E44),TRIM('Año 2026'!$E$3:$E$66),'Año 2026'!$AD$3:$AD$66),"")} -> 0
A45: 44 | B45: 2025 | C45: Denuncia | D45: MP | E45: 02160-2025-SUNEDU/02-13 | F45: En trámite | G45: 2025EXT0000022994-SUNEDU, 2025EXT0000029151-SUNEDU | H45: 41 | I45: Pública | J45: Nuevo local | K45: La Libertad | L45: Sanchez Carrion | M45: Sanagorán | N45: Local ubicado en el distrito de Sanagorán (ex instituto). | O45: MLI | P45: III | Q45: 17, 19, 20, 21, 22, 23, 24, 27, 28, 29, 30 | R45: Se informa que la universidad habría dispuesto trasladar la Facultad de Gestión Empresarial a un inmueble ubicado en el distrito de Sanagorán, basándose solo en un acuerdo de Consejo Municipal, que aprueba la donación de dicho inmueble, y sin considerar el cumplimiento de las condiciones básicas de calidad para su funcionamiento. La Universidad señaló que, a octubre del 2025, no viene brindando el servicio educativo en el inmueble donado por la Municipalidad Distrital de Sanagorán; asimismo, indica que aún se no se formalizó el inicio de actividades académicas en el inmueble antes mencionado. La Universidad no descartó la oferta en este nuevo local; no obstante, no indicó los actuados para iniciar la oferta académica en este nuevo local. | S45: ALTA | T45: 2 | U45: OFICIO N° 04148-2025-SUNEDU-DS-DIRESESU-UVE | V45: 45945 | W45: FALTA EN Z varios documentos, el OFICIO N° 03497-2025-SUNEDU-DS-DIRESESU-UVE, el OFICIO N° 03963-2025-SUNEDU-DS-DIRESESU-UVE, el Oficio N° 0498-2025-UNCA/P-CO (entrega de información) Se cuenta con IR elaborado por Manuel | X45: MANUEL HURTADO | Y45: OS Antecedentes Barzen (Feb-26) CBC III Manuel Hurtado (Feb-26) Priorizada para ser cerrada en julio 2026. (Rev. RL) | Z45: Sí | AA45: 46227 | AB45: =IF(AA45<TODAY(),"VENCIDO","POR VENCER") -> POR VENCER | AC45: 46234 | AD45: EN PROCESO | AF45: {=IFERROR(_xlfn.XLOOKUP(TRIM($E45),TRIM('Año 2026'!$E$3:$E$66),'Año 2026'!$G$3:$G$66),"")} -> Oficio Nº 04148-2025-SUNEDU-DS-DIRESESU-UVE | AG45: {=IFERROR(_xlfn.XLOOKUP(TRIM($E45),TRIM('Año 2026'!$E$3:$E$66),'Año 2026'!$H$3:$H$66),"")} -> 45945 | AH45: {=IFERROR(_xlfn.XLOOKUP(TRIM($E45),TRIM('Año 2026'!$E$3:$E$66),'Año 2026'!$I$3:$I$66),"")} -> 3 | AI45: {=IFERROR(_xlfn.XLOOKUP(TRIM($E45),TRIM('Año 2026'!$E$3:$E$66),'Año 2026'!$J$3:$J$66),"")} -> 45950 | AJ45: {=IFERROR(_xlfn.XLOOKUP(TRIM($E45),TRIM('Año 2026'!$E$3:$E$66),'Año 2026'!$K$3:$K$66),"")} -> -242 | AK45: {=IFERROR(_xlfn.XLOOKUP(TRIM($E45),TRIM('Año 2026'!$E$3:$E$66),'Año 2026'!$L$3:$L$66),"")} -> CONCLUIDO | AL45: {=IFERROR(_xlfn.XLOOKUP(TRIM($E45),TRIM('Año 2026'!$E$3:$E$66),'Año 2026'!$M$3:$M$66),"")} -> CONCLUIDO | AM45: {=IFERROR(_xlfn.XLOOKUP(TRIM($E45),TRIM('Año 2026'!$E$3:$E$66),'Año 2026'!$N$3:$N$66),"")} -> Entregado | AN45: {=IFERROR(_xlfn.XLOOKUP(TRIM($E45),TRIM('Año 2026'!$E$3:$E$66),'Año 2026'!$O$3:$O$66),"")} -> 0 | AO45: {=IFERROR(_xlfn.XLOOKUP(TRIM($E45),TRIM('Año 2026'!$E$3:$E$66),'Año 2026'!$P$3:$P$66),"")} -> Prórroga | AP45: {=IFERROR(_xlfn.XLOOKUP(TRIM($E45),TRIM('Año 2026'!$E$3:$E$66),'Año 2026'!$Q$3:$Q$66),"")} -> 0 | AQ45: {=IFERROR(_xlfn.XLOOKUP(TRIM($E45),TRIM('Año 2026'!$E$3:$E$66),'Año 2026'!$R$3:$R$66),"")} -> 0 | AR45: {=IFERROR(_xlfn.XLOOKUP(TRIM($E45),TRIM('Año 2026'!$E$3:$E$66),'Año 2026'!$S$3:$S$66),"")} -> 0 | AS45: {=IFERROR(_xlfn.XLOOKUP(TRIM($E45),TRIM('Año 2026'!$E$3:$E$66),'Año 2026'!$T$3:$T$66),"")} -> 0 | AT45: {=IFERROR(_xlfn.XLOOKUP(TRIM($E45),TRIM('Año 2026'!$E$3:$E$66),'Año 2026'!$U$3:$U$66),"")} -> 0 | AU45: {=IFERROR(_xlfn.XLOOKUP(TRIM($E45),TRIM('Año 2026'!$E$3:$E$66),'Año 2026'!$V$3:$V$66),"")} -> 0 | AV45: {=IFERROR(_xlfn.XLOOKUP(TRIM($E45),TRIM('Año 2026'!$E$3:$E$66),'Año 2026'!$W$3:$W$66),"")} -> 0 | AW45: {=IFERROR(_xlfn.XLOOKUP(TRIM($E45),TRIM('Año 2026'!$E$3:$E$66),'Año 2026'!$X$3:$X$66),"")} -> 6 | AX45: {=IFERROR(_xlfn.XLOOKUP(TRIM($E45),TRIM('Año 2026'!$E$3:$E$66),'Año 2026'!$Y$3:$Y$66),"")} | AY45: {=IFERROR(_xlfn.XLOOKUP(TRIM($E45),TRIM('Año 2026'!$E$3:$E$66),'Año 2026'!$Z$3:$Z$66),"")} | AZ45: {=IFERROR(_xlfn.XLOOKUP(TRIM($E45),TRIM('Año 2026'!$E$3:$E$66),'Año 2026'!$AA$3:$AA$66),"")} | BA45: {=IFERROR(_xlfn.XLOOKUP(TRIM($E45),TRIM('Año 2026'!$E$3:$E$66),'Año 2026'!$AB$3:$AB$66),"")} | BB45: {=IFERROR(_xlfn.XLOOKUP(TRIM($E45),TRIM('Año 2026'!$E$3:$E$66),'Año 2026'!$AC$3:$AC$66),"")} -> Entregado | BC45: {=IFERROR(_xlfn.XLOOKUP(TRIM($E45),TRIM('Año 2026'!$E$3:$E$66),'Año 2026'!$AD$3:$AD$66),"")} -> 0
A46: 45 | B46: 2025 | C46: SNP | D46: MP | E46: 01927-2025-SUNEDU/02-13 | F46: En trámite | G46: 2025EXT0000038971-SUNEDU, 2024INT0000002755-SUNEDU | H46: 31 | I46: Pública | J46: SL01 | K46: Pasco | L46: Pasco | M46: Yanacancha | N46: Programa de vivienda Urbanización San Juan Pampa, Mz Q, Lote 1, Sector Centro Comercial | O46: MLI | P46: III | Q46: 27, 28 | R46: Denuncia referida a la presunta falta de implementación del programa de Ingeniería Metalúrgica de la Universidad Nacional Daniel Alcides Carrión, consistente en la inexistencia y/o insuficiencia de laboratorios, talleres, reactivos, materiales y equipamiento necesario para el desarrollo de prácticas académicas, lo que habría limitado la formación de competencias profesionales de los estudiantes. Asimismo, se reporta la falta de asignación de ambientes adecuados para los laboratorios pedagógicos, la inoperatividad de equipos especializados —como el equipo de absorción atómica— por ausencia de personal capacitado, así como deficiencias en la dotación de insumos básicos para el inicio del semestre académico. Adicionalmente, se advierten presuntas deficiencias en la gestión administrativa vinculadas a la demora en la entrega de ambientes, falta de atención a reclamos formales presentados por estudiantes y egresados, y ausencia de acciones oportunas para garantizar condiciones mínimas de infraestructura y equipamiento. | S46: ALTA | T46: 1 | U46: Ingreso de Denuncia/Se escala a SNP | V46: 45853 | W46: En la visita de inspección de octubre de 2025, no se solicitó información vinculada a esta denuncia. Falta elaborar el oficio de requerimiento. Y luego se acumulará con la SNP 01709-2023-SUNEDU/02-13 | Y46: Pendiente visita en junio 2026 CBC III Carla La Torre Priorizada para ser cerrada en noviembre 2026. | Z46: Sí | AA46: 46346 | AB46: =IF(AA46<TODAY(),"VENCIDO","POR VENCER") -> POR VENCER | AC46: 46353 | AD46: EN PROCESO | AE46: Informe de Resultados | AF46: {=IFERROR(_xlfn.XLOOKUP(TRIM($E46),TRIM('Año 2026'!$E$3:$E$66),'Año 2026'!$G$3:$G$66),"")} -> 05589-2025-SUNEDU-DS-DIRESESU-UVE | AG46: {=IFERROR(_xlfn.XLOOKUP(TRIM($E46),TRIM('Año 2026'!$E$3:$E$66),'Año 2026'!$H$3:$H$66),"")} -> 46029 | AH46: {=IFERROR(_xlfn.XLOOKUP(TRIM($E46),TRIM('Año 2026'!$E$3:$E$66),'Año 2026'!$I$3:$I$66),"")} -> 5 | AI46: {=IFERROR(_xlfn.XLOOKUP(TRIM($E46),TRIM('Año 2026'!$E$3:$E$66),'Año 2026'!$J$3:$J$66),"")} -> 46094 | AJ46: {=IFERROR(_xlfn.XLOOKUP(TRIM($E46),TRIM('Año 2026'!$E$3:$E$66),'Año 2026'!$K$3:$K$66),"")} -> -98 | AK46: {=IFERROR(_xlfn.XLOOKUP(TRIM($E46),TRIM('Año 2026'!$E$3:$E$66),'Año 2026'!$L$3:$L$66),"")} -> NUEVA FECHA | AL46: {=IFERROR(_xlfn.XLOOKUP(TRIM($E46),TRIM('Año 2026'!$E$3:$E$66),'Año 2026'!$M$3:$M$66),"")} -> NUEVA FECHA | AM46: {=IFERROR(_xlfn.XLOOKUP(TRIM($E46),TRIM('Año 2026'!$E$3:$E$66),'Año 2026'!$N$3:$N$66),"")} -> Ajustes al plazo | AN46: {=IFERROR(_xlfn.XLOOKUP(TRIM($E46),TRIM('Año 2026'!$E$3:$E$66),'Año 2026'!$O$3:$O$66),"")} -> 0 | AO46: {=IFERROR(_xlfn.XLOOKUP(TRIM($E46),TRIM('Año 2026'!$E$3:$E$66),'Año 2026'!$P$3:$P$66),"")} -> Prórroga | AP46: {=IFERROR(_xlfn.XLOOKUP(TRIM($E46),TRIM('Año 2026'!$E$3:$E$66),'Año 2026'!$Q$3:$Q$66),"")} -> 0 | AQ46: {=IFERROR(_xlfn.XLOOKUP(TRIM($E46),TRIM('Año 2026'!$E$3:$E$66),'Año 2026'!$R$3:$R$66),"")} -> 0 | AR46: {=IFERROR(_xlfn.XLOOKUP(TRIM($E46),TRIM('Año 2026'!$E$3:$E$66),'Año 2026'!$S$3:$S$66),"")} -> 0 | AS46: {=IFERROR(_xlfn.XLOOKUP(TRIM($E46),TRIM('Año 2026'!$E$3:$E$66),'Año 2026'!$T$3:$T$66),"")} -> 0 | AT46: {=IFERROR(_xlfn.XLOOKUP(TRIM($E46),TRIM('Año 2026'!$E$3:$E$66),'Año 2026'!$U$3:$U$66),"")} -> 0 | AU46: {=IFERROR(_xlfn.XLOOKUP(TRIM($E46),TRIM('Año 2026'!$E$3:$E$66),'Año 2026'!$V$3:$V$66),"")} -> 0 | AV46: {=IFERROR(_xlfn.XLOOKUP(TRIM($E46),TRIM('Año 2026'!$E$3:$E$66),'Año 2026'!$W$3:$W$66),"")} -> 0 | AW46: {=IFERROR(_xlfn.XLOOKUP(TRIM($E46),TRIM('Año 2026'!$E$3:$E$66),'Año 2026'!$X$3:$X$66),"")} -> 0 | AX46: {=IFERROR(_xlfn.XLOOKUP(TRIM($E46),TRIM('Año 2026'!$E$3:$E$66),'Año 2026'!$Y$3:$Y$66),"")} -> 0 | AY46: {=IFERROR(_xlfn.XLOOKUP(TRIM($E46),TRIM('Año 2026'!$E$3:$E$66),'Año 2026'!$Z$3:$Z$66),"")} -> 0 | AZ46: {=IFERROR(_xlfn.XLOOKUP(TRIM($E46),TRIM('Año 2026'!$E$3:$E$66),'Año 2026'!$AA$3:$AA$66),"")} -> 0 | BA46: {=IFERROR(_xlfn.XLOOKUP(TRIM($E46),TRIM('Año 2026'!$E$3:$E$66),'Año 2026'!$AB$3:$AB$66),"")} -> 0 | BB46: {=IFERROR(_xlfn.XLOOKUP(TRIM($E46),TRIM('Año 2026'!$E$3:$E$66),'Año 2026'!$AC$3:$AC$66),"")} -> Entregado | BC46: {=IFERROR(_xlfn.XLOOKUP(TRIM($E46),TRIM('Año 2026'!$E$3:$E$66),'Año 2026'!$AD$3:$AD$66),"")} -> No se atendió la prórroga
A47: 46 | B47: 2025 | C47: SNP | D47: Web | E47: 02619-2025-SUNEDU/02-13 | F47: En trámite | G47: 2025EXT0000049372-SUNEDU, 2024INT0000002755-SUNEDU | H47: 31 | I47: Pública | J47: SL01 | K47: Pasco | L47: Pasco | M47: Yanacancha | N47: Programa de vivienda Urbanización San Juan Pampa, Mz Q, Lote 1, Sector Centro Comercial | O47: MLI | P47: III | Q47: 17, 19, 20, 27, 28 | R47: Denuncia referida a la Universidad Nacional Daniel Alcides Carrión (UNDAC), consistente en la falta de infraestructura propia y adecuada para el desarrollo de las actividades académicas de la Facultad de Ciencias de la Comunicación, la utilización de aulas prestadas correspondientes a la Facultad de Educación sin contar con autorización ni implementación suficiente, así como la advertencia de un eventual desalojo de los ambientes actualmente ocupados, lo que comprometería la continuidad del servicio educativo. Asimismo, se reporta la inexistencia de ambientes adecuados para el desarrollo de la Escuela Profesional de Ciencias de la Comunicación, así como la ausencia de laboratorios y de condiciones mínimas de funcionamiento. | S47: ALTA | T47: 1 | U47: Requerimiento de información con Oficio N° 05589-2025-SUNEDU-DS-DIRESESU-UVE | V47: 45910 | W47: En la visita se identificó que, la “Facultad de Ciencias de la Comunicación” ubicada en el local SL01, no cuenta con infraestructura propia; en tal sentido, para la oferta del programa de "Ciencias de la Comunicación", utiliza ambientes (aulas y dos laboratorios) prestados de la “Facultad de Educación”, donde se identificó observaciones de seguridad y mantenimiento. Asimismo, se advierte que no implementó el laboratorio de cómputo, requerido para la oferta académica del programa. En cuanto firmen el oficio se eleva a SNP. | Y47: Pendiente revisión de información, para determinar si se requiere información complementaria. CBC III Carla La Torre Priorizada para ser cerrada en noviembre 2026. | Z47: Sí | AA47: 46346 | AB47: =IF(AA47<TODAY(),"VENCIDO","POR VENCER") -> POR VENCER | AC47: 46353 | AD47: EN PROCESO | AE47: Informe de Resultados | AF47: {=IFERROR(_xlfn.XLOOKUP(TRIM($E47),TRIM('Año 2026'!$E$3:$E$66),'Año 2026'!$G$3:$G$66),"")} -> 05589-2025-SUNEDU-DS-DIRESESU-UVE | AG47: {=IFERROR(_xlfn.XLOOKUP(TRIM($E47),TRIM('Año 2026'!$E$3:$E$66),'Año 2026'!$H$3:$H$66),"")} -> 46029 | AH47: {=IFERROR(_xlfn.XLOOKUP(TRIM($E47),TRIM('Año 2026'!$E$3:$E$66),'Año 2026'!$I$3:$I$66),"")} -> 5 | AI47: {=IFERROR(_xlfn.XLOOKUP(TRIM($E47),TRIM('Año 2026'!$E$3:$E$66),'Año 2026'!$J$3:$J$66),"")} -> 46094 | AJ47: {=IFERROR(_xlfn.XLOOKUP(TRIM($E47),TRIM('Año 2026'!$E$3:$E$66),'Año 2026'!$K$3:$K$66),"")} -> -98 | AK47: {=IFERROR(_xlfn.XLOOKUP(TRIM($E47),TRIM('Año 2026'!$E$3:$E$66),'Año 2026'!$L$3:$L$66),"")} -> NUEVA FECHA | AL47: {=IFERROR(_xlfn.XLOOKUP(TRIM($E47),TRIM('Año 2026'!$E$3:$E$66),'Año 2026'!$M$3:$M$66),"")} -> NUEVA FECHA | AM47: {=IFERROR(_xlfn.XLOOKUP(TRIM($E47),TRIM('Año 2026'!$E$3:$E$66),'Año 2026'!$N$3:$N$66),"")} -> Ajustes al plazo | AN47: {=IFERROR(_xlfn.XLOOKUP(TRIM($E47),TRIM('Año 2026'!$E$3:$E$66),'Año 2026'!$O$3:$O$66),"")} -> 0 | AO47: {=IFERROR(_xlfn.XLOOKUP(TRIM($E47),TRIM('Año 2026'!$E$3:$E$66),'Año 2026'!$P$3:$P$66),"")} -> Prórroga | AP47: {=IFERROR(_xlfn.XLOOKUP(TRIM($E47),TRIM('Año 2026'!$E$3:$E$66),'Año 2026'!$Q$3:$Q$66),"")} -> 0 | AQ47: {=IFERROR(_xlfn.XLOOKUP(TRIM($E47),TRIM('Año 2026'!$E$3:$E$66),'Año 2026'!$R$3:$R$66),"")} -> 0 | AR47: {=IFERROR(_xlfn.XLOOKUP(TRIM($E47),TRIM('Año 2026'!$E$3:$E$66),'Año 2026'!$S$3:$S$66),"")} -> 0 | AS47: {=IFERROR(_xlfn.XLOOKUP(TRIM($E47),TRIM('Año 2026'!$E$3:$E$66),'Año 2026'!$T$3:$T$66),"")} -> 0 | AT47: {=IFERROR(_xlfn.XLOOKUP(TRIM($E47),TRIM('Año 2026'!$E$3:$E$66),'Año 2026'!$U$3:$U$66),"")} -> 0 | AU47: {=IFERROR(_xlfn.XLOOKUP(TRIM($E47),TRIM('Año 2026'!$E$3:$E$66),'Año 2026'!$V$3:$V$66),"")} -> 0 | AV47: {=IFERROR(_xlfn.XLOOKUP(TRIM($E47),TRIM('Año 2026'!$E$3:$E$66),'Año 2026'!$W$3:$W$66),"")} -> 0 | AW47: {=IFERROR(_xlfn.XLOOKUP(TRIM($E47),TRIM('Año 2026'!$E$3:$E$66),'Año 2026'!$X$3:$X$66),"")} -> 0 | AX47: {=IFERROR(_xlfn.XLOOKUP(TRIM($E47),TRIM('Año 2026'!$E$3:$E$66),'Año 2026'!$Y$3:$Y$66),"")} -> 0 | AY47: {=IFERROR(_xlfn.XLOOKUP(TRIM($E47),TRIM('Año 2026'!$E$3:$E$66),'Año 2026'!$Z$3:$Z$66),"")} -> 0 | AZ47: {=IFERROR(_xlfn.XLOOKUP(TRIM($E47),TRIM('Año 2026'!$E$3:$E$66),'Año 2026'!$AA$3:$AA$66),"")} -> 0 | BA47: {=IFERROR(_xlfn.XLOOKUP(TRIM($E47),TRIM('Año 2026'!$E$3:$E$66),'Año 2026'!$AB$3:$AB$66),"")} -> 0 | BB47: {=IFERROR(_xlfn.XLOOKUP(TRIM($E47),TRIM('Año 2026'!$E$3:$E$66),'Año 2026'!$AC$3:$AC$66),"")} -> Entregado | BC47: {=IFERROR(_xlfn.XLOOKUP(TRIM($E47),TRIM('Año 2026'!$E$3:$E$66),'Año 2026'!$AD$3:$AD$66),"")} -> No se atendió la prórroga
A48: 47 | B48: 2025 | C48: SNP | D48: No programada - oficio | E48: 01560-2025-SUNEDU/02-13 | F48: Atendido | H48: 40 | I48: Pública | J48: F03L01, Local IES Nuestra Señora del Carmen de Lircay | K48: Huancavelica | L48: Angaraes | M48: Lircay | N48: F03L01: Av. Centenario N° 1200 del Barrio Pueblo Nuevo | Local IES: Av. Esmeralda N.° 414, Barrio Bellavista | O48: MLI | P48: III, VI | Q48: 19, 21, 22, 24, 27, 30, 43, 44, 45, 46, 47, 48, 50 | R48: Denuncia referida a la Universidad Nacional de Huancavelica, derivada del traslado de la oferta académica de las Escuelas Profesionales de Ingeniería de Minas e Ingeniería Civil al local de la Institución Educativa “Nuestra Señora del Carmen” de Lircay, en el marco de un convenio de cooperación interinstitucional. Las presuntas deficiencias estarían relacionadas con la adecuación y disponibilidad de aulas, laboratorios y servicios complementarios (servicio de tópico, psicopedagogía, biblioteca y PRODAP), así como con el uso compartido de ambientes para el desarrollo de actividades académicas. Asimismo, se advierte la necesidad de verificar la correspondencia entre dicho traslado y la infraestructura existente en el local F03L01 de la filial Angaraes, considerando la construcción de nueva infraestructura universitaria y la habilitación de ambientes temporales, a fin de asegurar la continuidad, seguridad y sostenibilidad del servicio educativo conforme al Modelo de Licenciamiento y la normativa vigente. | S48: ALTA | T48: 1 | U48: Respuesta por parte de la Universidad a los requerimientos realizados en el Acta de Supervisión, mediante Oficio N° 000788-2025-RECTOR del 25.11.25 | V48: 45986 | W48: Se tiene un IR preliminar elaborado por Jenny Mendez, pendiente de revisión final. Tener en cuenta que no se ha requerido información sobre el indicador 17, considerar un requerimiento complementario. | X48: PABLO ARRÓSPIDE | Y48: Antecedentes Susana Varas CBC III y VI Pablo Arrópsidee 09.02.26 al 23.02.26 Priorizada para ser cerrada en junio 2026. (Rev. RL) | Z48: Sí | AA48: 46101 | AB48: =IF(AA48<TODAY(),"VENCIDO","POR VENCER") -> VENCIDO | AC48: 46101 | AD48: COMPLETADO | AE48: INFORME DE RESULTADOS N° 00051-2026-SUNEDU-DS-DIRESESU-UVE | AF48: {=IFERROR(_xlfn.XLOOKUP(TRIM($E48),TRIM('Año 2026'!$E$3:$E$66),'Año 2026'!$G$3:$G$66),"")} | AG48: {=IFERROR(_xlfn.XLOOKUP(TRIM($E48),TRIM('Año 2026'!$E$3:$E$66),'Año 2026'!$H$3:$H$66),"")} | AH48: {=IFERROR(_xlfn.XLOOKUP(TRIM($E48),TRIM('Año 2026'!$E$3:$E$66),'Año 2026'!$I$3:$I$66),"")} | AI48: {=IFERROR(_xlfn.XLOOKUP(TRIM($E48),TRIM('Año 2026'!$E$3:$E$66),'Año 2026'!$J$3:$J$66),"")} | AJ48: {=IFERROR(_xlfn.XLOOKUP(TRIM($E48),TRIM('Año 2026'!$E$3:$E$66),'Año 2026'!$K$3:$K$66),"")} | AK48: {=IFERROR(_xlfn.XLOOKUP(TRIM($E48),TRIM('Año 2026'!$E$3:$E$66),'Año 2026'!$L$3:$L$66),"")} | AL48: {=IFERROR(_xlfn.XLOOKUP(TRIM($E48),TRIM('Año 2026'!$E$3:$E$66),'Año 2026'!$M$3:$M$66),"")} | AM48: {=IFERROR(_xlfn.XLOOKUP(TRIM($E48),TRIM('Año 2026'!$E$3:$E$66),'Año 2026'!$N$3:$N$66),"")} | AN48: {=IFERROR(_xlfn.XLOOKUP(TRIM($E48),TRIM('Año 2026'!$E$3:$E$66),'Año 2026'!$O$3:$O$66),"")} | AO48: {=IFERROR(_xlfn.XLOOKUP(TRIM($E48),TRIM('Año 2026'!$E$3:$E$66),'Año 2026'!$P$3:$P$66),"")} | AP48: {=IFERROR(_xlfn.XLOOKUP(TRIM($E48),TRIM('Año 2026'!$E$3:$E$66),'Año 2026'!$Q$3:$Q$66),"")} | AQ48: {=IFERROR(_xlfn.XLOOKUP(TRIM($E48),TRIM('Año 2026'!$E$3:$E$66),'Año 2026'!$R$3:$R$66),"")} | AR48: {=IFERROR(_xlfn.XLOOKUP(TRIM($E48),TRIM('Año 2026'!$E$3:$E$66),'Año 2026'!$S$3:$S$66),"")} | AS48: {=IFERROR(_xlfn.XLOOKUP(TRIM($E48),TRIM('Año 2026'!$E$3:$E$66),'Año 2026'!$T$3:$T$66),"")} | AT48: {=IFERROR(_xlfn.XLOOKUP(TRIM($E48),TRIM('Año 2026'!$E$3:$E$66),'Año 2026'!$U$3:$U$66),"")} | AU48: {=IFERROR(_xlfn.XLOOKUP(TRIM($E48),TRIM('Año 2026'!$E$3:$E$66),'Año 2026'!$V$3:$V$66),"")} | AV48: {=IFERROR(_xlfn.XLOOKUP(TRIM($E48),TRIM('Año 2026'!$E$3:$E$66),'Año 2026'!$W$3:$W$66),"")} | AW48: {=IFERROR(_xlfn.XLOOKUP(TRIM($E48),TRIM('Año 2026'!$E$3:$E$66),'Año 2026'!$X$3:$X$66),"")} | AX48: {=IFERROR(_xlfn.XLOOKUP(TRIM($E48),TRIM('Año 2026'!$E$3:$E$66),'Año 2026'!$Y$3:$Y$66),"")} | AY48: {=IFERROR(_xlfn.XLOOKUP(TRIM($E48),TRIM('Año 2026'!$E$3:$E$66),'Año 2026'!$Z$3:$Z$66),"")} | AZ48: {=IFERROR(_xlfn.XLOOKUP(TRIM($E48),TRIM('Año 2026'!$E$3:$E$66),'Año 2026'!$AA$3:$AA$66),"")} | BA48: {=IFERROR(_xlfn.XLOOKUP(TRIM($E48),TRIM('Año 2026'!$E$3:$E$66),'Año 2026'!$AB$3:$AB$66),"")} | BB48: {=IFERROR(_xlfn.XLOOKUP(TRIM($E48),TRIM('Año 2026'!$E$3:$E$66),'Año 2026'!$AC$3:$AC$66),"")} | BC48: {=IFERROR(_xlfn.XLOOKUP(TRIM($E48),TRIM('Año 2026'!$E$3:$E$66),'Año 2026'!$AD$3:$AD$66),"")}
A49: 48 | B49: 2025 | C49: Denuncia | D49: Web | E49: 02798-2025-SUNEDU/02-13 | F49: En trámite | G49: 2025EXT0000052884-SUNEDU, 2026EXT0000016351-SUNEDU | H49: 41 | I49: Pública | J49: Nuevo local | K49: La Libertad | L49: Sanchez Carrion | M49: Sanagorán | N49: Local ubicado en el distrito de Sanagorán (ex instituto). | O49: MLI | P49: III | Q49: 17, 19, 20, 21, 22, 23, 24, 27, 28, 29, 30 | R49: Denuncia que debido al incremento de los alumnos, la Universidad no mantendría las condiciones básicas de calidad en el nuevo local académico. La denuncia va por el incremento de número de vacantes de 40 a 60 estudiantes, cuyo incremento podría impactar en la ocupabilidad de la infraestructura. También, la denuncia está vinculada con el EXP. 02798-2025-SUNEDU/02-13, por el traslado de oferta de programas a un nuevo local. En este caso, entre otros, presentan evidencias del inicio de actividades, en abril de 2025, en el nuevo local ubicado en el distrito de Sanagorán; asimismo, muestran evidencias de una comunicación del 22 de mayo de 2025 de “suspensión temporal de actividades académicas y administrativas por acondicionamiento. | S49: ALTA | T49: 2 | U49: Denuncia recibida | V49: 45931 | W49: En tal sentido, a la fecha no se tiene certeza si la Universidad cuenta con infraestructura para atender la demanda del incremento de estudiantes matriculados (por la demanda de vacantes). Asimismo, no se tiene certeza si la Universidad culminó la adecuación del nuevo local, y si dio inició a las actividades académicas en dicho local. En la Visista de setiembre 2025 no se debió tomar en cuenta este caso debido a la fcha de ingreso de la presenteb denuncia (validar con Pablo), se debe señalar que no fue incluido en los oficios anteriores. Solicitar a Adrián su vinculación a expedientes anteriores | Y49: Pendiente proyectar requerimiento de información. Priorizada para ser cerrada en julio 2026. (Rev. RL) | Z49: Sí | AA49: 46227 | AB49: =IF(AA49<TODAY(),"VENCIDO","POR VENCER") -> POR VENCER | AC49: 46234 | AD49: EN PROCESO | AE49: Carta y/o Oficio | AF49: {=IFERROR(_xlfn.XLOOKUP(TRIM($E49),TRIM('Año 2026'!$E$3:$E$66),'Año 2026'!$G$3:$G$66),"")} -> 0 | AG49: {=IFERROR(_xlfn.XLOOKUP(TRIM($E49),TRIM('Año 2026'!$E$3:$E$66),'Año 2026'!$H$3:$H$66),"")} -> 0 | AH49: {=IFERROR(_xlfn.XLOOKUP(TRIM($E49),TRIM('Año 2026'!$E$3:$E$66),'Año 2026'!$I$3:$I$66),"")} -> 0 | AI49: {=IFERROR(_xlfn.XLOOKUP(TRIM($E49),TRIM('Año 2026'!$E$3:$E$66),'Año 2026'!$J$3:$J$66),"")} -> 0 | AJ49: {=IFERROR(_xlfn.XLOOKUP(TRIM($E49),TRIM('Año 2026'!$E$3:$E$66),'Año 2026'!$K$3:$K$66),"")} -> 0 | AK49: {=IFERROR(_xlfn.XLOOKUP(TRIM($E49),TRIM('Año 2026'!$E$3:$E$66),'Año 2026'!$L$3:$L$66),"")} -> 0 | AL49: {=IFERROR(_xlfn.XLOOKUP(TRIM($E49),TRIM('Año 2026'!$E$3:$E$66),'Año 2026'!$M$3:$M$66),"")} -> 0 | AM49: {=IFERROR(_xlfn.XLOOKUP(TRIM($E49),TRIM('Año 2026'!$E$3:$E$66),'Año 2026'!$N$3:$N$66),"")} -> 0 | AN49: {=IFERROR(_xlfn.XLOOKUP(TRIM($E49),TRIM('Año 2026'!$E$3:$E$66),'Año 2026'!$O$3:$O$66),"")} -> 0 | AO49: {=IFERROR(_xlfn.XLOOKUP(TRIM($E49),TRIM('Año 2026'!$E$3:$E$66),'Año 2026'!$P$3:$P$66),"")} -> 0 | AP49: {=IFERROR(_xlfn.XLOOKUP(TRIM($E49),TRIM('Año 2026'!$E$3:$E$66),'Año 2026'!$Q$3:$Q$66),"")} -> 0 | AQ49: {=IFERROR(_xlfn.XLOOKUP(TRIM($E49),TRIM('Año 2026'!$E$3:$E$66),'Año 2026'!$R$3:$R$66),"")} -> 0 | AR49: {=IFERROR(_xlfn.XLOOKUP(TRIM($E49),TRIM('Año 2026'!$E$3:$E$66),'Año 2026'!$S$3:$S$66),"")} -> 0 | AS49: {=IFERROR(_xlfn.XLOOKUP(TRIM($E49),TRIM('Año 2026'!$E$3:$E$66),'Año 2026'!$T$3:$T$66),"")} -> 0 | AT49: {=IFERROR(_xlfn.XLOOKUP(TRIM($E49),TRIM('Año 2026'!$E$3:$E$66),'Año 2026'!$U$3:$U$66),"")} -> 0 | AU49: {=IFERROR(_xlfn.XLOOKUP(TRIM($E49),TRIM('Año 2026'!$E$3:$E$66),'Año 2026'!$V$3:$V$66),"")} -> 0 | AV49: {=IFERROR(_xlfn.XLOOKUP(TRIM($E49),TRIM('Año 2026'!$E$3:$E$66),'Año 2026'!$W$3:$W$66),"")} -> 0 | AW49: {=IFERROR(_xlfn.XLOOKUP(TRIM($E49),TRIM('Año 2026'!$E$3:$E$66),'Año 2026'!$X$3:$X$66),"")} -> 0 | AX49: {=IFERROR(_xlfn.XLOOKUP(TRIM($E49),TRIM('Año 2026'!$E$3:$E$66),'Año 2026'!$Y$3:$Y$66),"")} -> 0 | AY49: {=IFERROR(_xlfn.XLOOKUP(TRIM($E49),TRIM('Año 2026'!$E$3:$E$66),'Año 2026'!$Z$3:$Z$66),"")} -> 0 | AZ49: {=IFERROR(_xlfn.XLOOKUP(TRIM($E49),TRIM('Año 2026'!$E$3:$E$66),'Año 2026'!$AA$3:$AA$66),"")} -> 0 | BA49: {=IFERROR(_xlfn.XLOOKUP(TRIM($E49),TRIM('Año 2026'!$E$3:$E$66),'Año 2026'!$AB$3:$AB$66),"")} -> 0 | BB49: {=IFERROR(_xlfn.XLOOKUP(TRIM($E49),TRIM('Año 2026'!$E$3:$E$66),'Año 2026'!$AC$3:$AC$66),"")} -> 0 | BC49: {=IFERROR(_xlfn.XLOOKUP(TRIM($E49),TRIM('Año 2026'!$E$3:$E$66),'Año 2026'!$AD$3:$AD$66),"")} -> 0
A50: 49 | B50: 2025 | C50: Accion Directa | D50: Correo electrónico | E50: AD-020-2025 | F50: En trámite | G50: 2024EXT0000037874-SUNEDU | H50: 55 | I50: Pública | J50: SL01 | K50: Lima | L50: Huaura | M50: Huacho | N50: Av. Mercedes Indacochea N° 609 - Puerta 01 | O50: MLI | P50: IV, V, VIII | R50: El caso involucra 3 denuncias, i) mediante Oficio N° 131-2024-FENDUP del 29 de agosto de 2024, la UVE tomó conocimiento, entre otros aspectos, sobre la presunta concentración de asesorías y jurados de tesis en pocos docentes, así como la no publicación de los trabajos de investigación en el portal de la Universidad Nacional José Faustino Sánchez Carrión, vinculado con la CBC IV del Modelo de Licenciamiento Institucional. ii) Sobre deficiencias en el PI con CUI 21334406. iii)mediante OFICIO-02052-2025-MINEDU-VMGP-DIGESU denuncia sobre el PI anterior. | S50: MEDIA | T50: 2 | U50: La Universidad remitió información en nov2025 ante el pedido del oficio de requerimiento de información de nov2025. Se cuenta con 1 Informe elaborado que requiere revisión. | V50: 45978 | W50: Si bien se cuenta con un informe que analiza la denuncia desde CBC III y IV, requiere de una revisión minuciona de los aspectos relacionados en estricto con la denuncia (invetigación, docentes), así como requiere del análisis de los proyectos de inversión referidos en la documentación de la visita y en la remitida por la Universidad. No se ha leabdora don IR de la CBC III, esta pendiente. Se cuenta con información proporcionada por la Universidad durante la VI realizada del 10 al 13 de Noviembre 2025. | Y50: Falta elaborar Informe | AB50: SIN FECHA | AD50: EN PROCESO | AE50: Informe y/o Requerimiento de información | AF50: {=IFERROR(_xlfn.XLOOKUP(TRIM($E50),TRIM('Año 2026'!$E$3:$E$66),'Año 2026'!$G$3:$G$66),"")} -> Oficio N° 00829-2024-SUNEDU-DS-DIRESESU-UVE | AG50: {=IFERROR(_xlfn.XLOOKUP(TRIM($E50),TRIM('Año 2026'!$E$3:$E$66),'Año 2026'!$H$3:$H$66),"")} -> 45610 | AH50: {=IFERROR(_xlfn.XLOOKUP(TRIM($E50),TRIM('Año 2026'!$E$3:$E$66),'Año 2026'!$I$3:$I$66),"")} -> 5 | AI50: {=IFERROR(_xlfn.XLOOKUP(TRIM($E50),TRIM('Año 2026'!$E$3:$E$66),'Año 2026'!$J$3:$J$66),"")} -> 45617 | AJ50: {=IFERROR(_xlfn.XLOOKUP(TRIM($E50),TRIM('Año 2026'!$E$3:$E$66),'Año 2026'!$K$3:$K$66),"")} -> -575 | AK50: {=IFERROR(_xlfn.XLOOKUP(TRIM($E50),TRIM('Año 2026'!$E$3:$E$66),'Año 2026'!$L$3:$L$66),"")} -> NUEVA FECHA | AL50: {=IFERROR(_xlfn.XLOOKUP(TRIM($E50),TRIM('Año 2026'!$E$3:$E$66),'Año 2026'!$M$3:$M$66),"")} -> NUEVA FECHA | AM50: {=IFERROR(_xlfn.XLOOKUP(TRIM($E50),TRIM('Año 2026'!$E$3:$E$66),'Año 2026'!$N$3:$N$66),"")} -> Ajustes al plazo | AN50: {=IFERROR(_xlfn.XLOOKUP(TRIM($E50),TRIM('Año 2026'!$E$3:$E$66),'Año 2026'!$O$3:$O$66),"")} -> 0 | AO50: {=IFERROR(_xlfn.XLOOKUP(TRIM($E50),TRIM('Año 2026'!$E$3:$E$66),'Año 2026'!$P$3:$P$66),"")} -> Visita de inspección | AP50: {=IFERROR(_xlfn.XLOOKUP(TRIM($E50),TRIM('Año 2026'!$E$3:$E$66),'Año 2026'!$Q$3:$Q$66),"")} -> 0 | AQ50: {=IFERROR(_xlfn.XLOOKUP(TRIM($E50),TRIM('Año 2026'!$E$3:$E$66),'Año 2026'!$R$3:$R$66),"")} -> 0 | AR50: {=IFERROR(_xlfn.XLOOKUP(TRIM($E50),TRIM('Año 2026'!$E$3:$E$66),'Año 2026'!$S$3:$S$66),"")} -> 0 | AS50: {=IFERROR(_xlfn.XLOOKUP(TRIM($E50),TRIM('Año 2026'!$E$3:$E$66),'Año 2026'!$T$3:$T$66),"")} -> 0 | AT50: {=IFERROR(_xlfn.XLOOKUP(TRIM($E50),TRIM('Año 2026'!$E$3:$E$66),'Año 2026'!$U$3:$U$66),"")} -> 0 | AU50: {=IFERROR(_xlfn.XLOOKUP(TRIM($E50),TRIM('Año 2026'!$E$3:$E$66),'Año 2026'!$V$3:$V$66),"")} -> Acta de supervisión | AV50: {=IFERROR(_xlfn.XLOOKUP(TRIM($E50),TRIM('Año 2026'!$E$3:$E$66),'Año 2026'!$W$3:$W$66),"")} -> 45974 | AW50: {=IFERROR(_xlfn.XLOOKUP(TRIM($E50),TRIM('Año 2026'!$E$3:$E$66),'Año 2026'!$X$3:$X$66),"")} -> 3 | AX50: {=IFERROR(_xlfn.XLOOKUP(TRIM($E50),TRIM('Año 2026'!$E$3:$E$66),'Año 2026'!$Y$3:$Y$66),"")} | AY50: {=IFERROR(_xlfn.XLOOKUP(TRIM($E50),TRIM('Año 2026'!$E$3:$E$66),'Año 2026'!$Z$3:$Z$66),"")} | AZ50: {=IFERROR(_xlfn.XLOOKUP(TRIM($E50),TRIM('Año 2026'!$E$3:$E$66),'Año 2026'!$AA$3:$AA$66),"")} | BA50: {=IFERROR(_xlfn.XLOOKUP(TRIM($E50),TRIM('Año 2026'!$E$3:$E$66),'Año 2026'!$AB$3:$AB$66),"")} | BB50: {=IFERROR(_xlfn.XLOOKUP(TRIM($E50),TRIM('Año 2026'!$E$3:$E$66),'Año 2026'!$AC$3:$AC$66),"")} -> Entregado | BC50: {=IFERROR(_xlfn.XLOOKUP(TRIM($E50),TRIM('Año 2026'!$E$3:$E$66),'Año 2026'!$AD$3:$AD$66),"")} -> 0
